Workbook

Sheet NeatRescue — Hackathon submissi
A1: NeatRescue — Hackathon submission · User-reported facts — not independently audited
A2: Financial model (5 pages) · Main Scenario
A4: Variable / dimension | B4: Value
A5: Actual customers | B5: =0 -> 0
A6: Actual monthly revenue | B6: =0 -> 0
A7: Actual cash | B7: =0 -> 0
A8: Committed funding | B8: =0 -> 0
A9: Synthetic incorrect payment rows | B9: =4 -> 4
A10: Synthetic rows after incomplete fix | B10: =1 -> 1
A11: Synthetic correct rows after independent verification | B11: =3 -> 3

Sheet NeatRescue — Hackathon subm (2)
A1: NeatRescue — Hackathon submission · 12-month scenario comparison — hypothetical
A2: Financial model (5 pages) · Main Scenario
A4: Variable / dimension | B4: Value | C4: Value > Conservative | D4: Value > Growth | E4: Value > Bootstrap $5,000 — hypothetical | F4: Value > Bootstrap no-sales stress — hypothetical
A5: 12-month revenue | B5: =SUM('NeatRescue — Hackathon subm (3)'!B5,'NeatRescue — Hackathon subm (3)'!C5,'NeatRescue — Hackathon subm (3)'!D5,'NeatRescue — Hackathon subm (3)'!E5,'NeatRescue — Hackathon subm (3)'!F5,'NeatRescue — Hackathon subm (3)'!G5,'NeatRescue — Hackathon subm (3)'!H5,'NeatRescue — Hackathon subm (3)'!I5,'NeatRescue — Hackathon subm (3)'!J5,'NeatRescue — Hackathon subm (3)'!K5,'NeatRescue — Hackathon subm (3)'!L5,'NeatRescue — Hackathon subm (3)'!M5) -> 31649.645 | C5: =SUM('NeatRescue — Hackathon subm (3)'!B6,'NeatRescue — Hackathon subm (3)'!C6,'NeatRescue — Hackathon subm (3)'!D6,'NeatRescue — Hackathon subm (3)'!E6,'NeatRescue — Hackathon subm (3)'!F6,'NeatRescue — Hackathon subm (3)'!G6,'NeatRescue — Hackathon subm (3)'!H6,'NeatRescue — Hackathon subm (3)'!I6,'NeatRescue — Hackathon subm (3)'!J6,'NeatRescue — Hackathon subm (3)'!K6,'NeatRescue — Hackathon subm (3)'!L6,'NeatRescue — Hackathon subm (3)'!M6) -> 7062.133 | D5: =SUM('NeatRescue — Hackathon subm (3)'!B7,'NeatRescue — Hackathon subm (3)'!C7,'NeatRescue — Hackathon subm (3)'!D7,'NeatRescue — Hackathon subm (3)'!E7,'NeatRescue — Hackathon subm (3)'!F7,'NeatRescue — Hackathon subm (3)'!G7,'NeatRescue — Hackathon subm (3)'!H7,'NeatRescue — Hackathon subm (3)'!I7,'NeatRescue — Hackathon subm (3)'!J7,'NeatRescue — Hackathon subm (3)'!K7,'NeatRescue — Hackathon subm (3)'!L7,'NeatRescue — Hackathon subm (3)'!M7) -> 83648.393 | E5: =SUM('Model inputs'!D67,'Model inputs'!E67,'Model inputs'!F67,'Model inputs'!G67,'Model inputs'!H67,'Model inputs'!I67,'Model inputs'!J67,'Model inputs'!K67,'Model inputs'!L67,'Model inputs'!M67,'Model inputs'!N67,'Model inputs'!B67) -> 31649.645 | F5: =SUM('Model inputs'!D62,'Model inputs'!E62,'Model inputs'!F62,'Model inputs'!G62,'Model inputs'!H62,'Model inputs'!I62,'Model inputs'!J62,'Model inputs'!K62,'Model inputs'!L62,'Model inputs'!M62,'Model inputs'!N62,'Model inputs'!B62) -> 0
A6: 12-month cost of revenue | B6: =SUM('NeatRescue — Cash & scenarios ·'!B6,'NeatRescue — Cash & scenarios ·'!C6,'NeatRescue — Cash & scenarios ·'!D6,'NeatRescue — Cash & scenarios ·'!E6,'NeatRescue — Cash & scenarios ·'!F6,'NeatRescue — Cash & scenarios ·'!G6,'NeatRescue — Cash & scenarios ·'!H6,'NeatRescue — Cash & scenarios ·'!I6,'NeatRescue — Cash & scenarios ·'!J6,'NeatRescue — Cash & scenarios ·'!K6,'NeatRescue — Cash & scenarios ·'!L6,'NeatRescue — Cash & scenarios ·'!M6) -> 12404.905 | C6: =SUM('Model inputs'!D28,'Model inputs'!E28,'Model inputs'!F28,'Model inputs'!G28,'Model inputs'!H28,'Model inputs'!I28,'Model inputs'!J28,'Model inputs'!K28,'Model inputs'!L28,'Model inputs'!M28,'Model inputs'!N28,'Model inputs'!B28) -> 4741.6743 | D6: =SUM('Model inputs'!D26,'Model inputs'!E26,'Model inputs'!F26,'Model inputs'!G26,'Model inputs'!H26,'Model inputs'!I26,'Model inputs'!J26,'Model inputs'!K26,'Model inputs'!L26,'Model inputs'!M26,'Model inputs'!N26,'Model inputs'!B26) -> 28349.568 | E6: =SUM('Model inputs'!D27,'Model inputs'!E27,'Model inputs'!F27,'Model inputs'!G27,'Model inputs'!H27,'Model inputs'!I27,'Model inputs'!J27,'Model inputs'!K27,'Model inputs'!L27,'Model inputs'!M27,'Model inputs'!N27,'Model inputs'!B27) -> 12404.905 | F6: =SUM('Model inputs'!D25,'Model inputs'!E25,'Model inputs'!F25,'Model inputs'!G25,'Model inputs'!H25,'Model inputs'!I25,'Model inputs'!J25,'Model inputs'!K25,'Model inputs'!L25,'Model inputs'!M25,'Model inputs'!N25,'Model inputs'!B25) -> 2700
A7: 12-month gross profit | B7: ='NeatRescue — Hackathon subm (2)'!B5-'NeatRescue — Hackathon subm (2)'!B6 -> 19244.74 | C7: ='NeatRescue — Hackathon subm (2)'!C5-'NeatRescue — Hackathon subm (2)'!C6 -> 2320.4586 | D7: ='NeatRescue — Hackathon subm (2)'!D5-'NeatRescue — Hackathon subm (2)'!D6 -> 55298.825 | E7: ='NeatRescue — Hackathon subm (2)'!E5-'NeatRescue — Hackathon subm (2)'!E6 -> 19244.74 | F7: ='NeatRescue — Hackathon subm (2)'!F5-'NeatRescue — Hackathon subm (2)'!F6 -> -2700
A8: 12-month gross margin | B8: =IFERROR('NeatRescue — Hackathon subm (2)'!B7/'NeatRescue — Hackathon subm (2)'!B5,"") -> 0.60805547 | C8: =IFERROR('NeatRescue — Hackathon subm (2)'!C7/'NeatRescue — Hackathon subm (2)'!C5,"") -> 0.32857759 | D8: =IFERROR('NeatRescue — Hackathon subm (2)'!D7/'NeatRescue — Hackathon subm (2)'!D5,"") -> 0.66108652 | E8: =IFERROR('NeatRescue — Hackathon subm (2)'!E7/'NeatRescue — Hackathon subm (2)'!E5,"") -> 0.60805547 | F8: =IFERROR('NeatRescue — Hackathon subm (2)'!F7/'NeatRescue — Hackathon subm (2)'!F5,"")
A9: 12-month operating expenses | B9: =SUM('NeatRescue — Cash & scenarios ·'!B13,'NeatRescue — Cash & scenarios ·'!C13,'NeatRescue — Cash & scenarios ·'!D13,'NeatRescue — Cash & scenarios ·'!E13,'NeatRescue — Cash & scenarios ·'!F13,'NeatRescue — Cash & scenarios ·'!G13,'NeatRescue — Cash & scenarios ·'!H13,'NeatRescue — Cash & scenarios ·'!I13,'NeatRescue — Cash & scenarios ·'!J13,'NeatRescue — Cash & scenarios ·'!K13,'NeatRescue — Cash & scenarios ·'!L13,'NeatRescue — Cash & scenarios ·'!M13) -> 2900 | C9: =SUM('Model inputs'!D52,'Model inputs'!E52,'Model inputs'!F52,'Model inputs'!G52,'Model inputs'!H52,'Model inputs'!I52,'Model inputs'!J52,'Model inputs'!K52,'Model inputs'!L52,'Model inputs'!M52,'Model inputs'!N52,'Model inputs'!B52) -> 2000 | D9: =SUM('Model inputs'!D50,'Model inputs'!E50,'Model inputs'!F50,'Model inputs'!G50,'Model inputs'!H50,'Model inputs'!I50,'Model inputs'!J50,'Model inputs'!K50,'Model inputs'!L50,'Model inputs'!M50,'Model inputs'!N50,'Model inputs'!B50) -> 4700 | E9: =SUM('Model inputs'!D51,'Model inputs'!E51,'Model inputs'!F51,'Model inputs'!G51,'Model inputs'!H51,'Model inputs'!I51,'Model inputs'!J51,'Model inputs'!K51,'Model inputs'!L51,'Model inputs'!M51,'Model inputs'!N51,'Model inputs'!B51) -> 2900 | F9: =SUM('Model inputs'!D49,'Model inputs'!E49,'Model inputs'!F49,'Model inputs'!G49,'Model inputs'!H49,'Model inputs'!I49,'Model inputs'!J49,'Model inputs'!K49,'Model inputs'!L49,'Model inputs'!M49,'Model inputs'!N49,'Model inputs'!B49) -> 2900
A10: 12-month operating profit | B10: ='NeatRescue — Hackathon subm (2)'!B7-'NeatRescue — Hackathon subm (2)'!B9 -> 16344.74 | C10: ='NeatRescue — Hackathon subm (2)'!C7-'NeatRescue — Hackathon subm (2)'!C9 -> 320.45863 | D10: ='NeatRescue — Hackathon subm (2)'!D7-'NeatRescue — Hackathon subm (2)'!D9 -> 50598.825 | E10: ='NeatRescue — Hackathon subm (2)'!E7-'NeatRescue — Hackathon subm (2)'!E9 -> 16344.74 | F10: ='NeatRescue — Hackathon subm (2)'!F7-'NeatRescue — Hackathon subm (2)'!F9 -> -5600
A11: Month 12 customers | B11: =IF('NeatRescue — Revenue & costs ·'!M14="","",'NeatRescue — Revenue & costs ·'!M14) -> 51.961366 | C11: =IF('Model inputs'!B23="","",'Model inputs'!B23) -> 12.023801 | D11: =IF('Model inputs'!B21="","",'Model inputs'!B21) -> 155.21359 | E11: =IF('Model inputs'!B22="","",'Model inputs'!B22) -> 51.961366 | F11: =IF('Model inputs'!B20="","",'Model inputs'!B20) -> 0
A12: Month 12 revenue | B12: =IF('NeatRescue — Hackathon subm (3)'!M5="","",'NeatRescue — Hackathon subm (3)'!M5) -> 5559.8661 | C12: =IF('NeatRescue — Hackathon subm (3)'!M6="","",'NeatRescue — Hackathon subm (3)'!M6) -> 1017.2136 | D12: =IF('NeatRescue — Hackathon subm (3)'!M7="","",'NeatRescue — Hackathon subm (3)'!M7) -> 16607.854 | E12: =IF('Model inputs'!B67="","",'Model inputs'!B67) -> 5559.8661 | F12: =IF('Model inputs'!B62="","",'Model inputs'!B62) -> 0
A13: Month 12 gross margin | B13: =IF('NeatRescue — Cash & scenarios ·'!M8="","",'NeatRescue — Cash & scenarios ·'!M8) -> 0.65289589 | C13: =IF('Model inputs'!B38="","",'Model inputs'!B38) -> 0.48970586 | D13: =IF('Model inputs'!B36="","",'Model inputs'!B36) -> 0.67981668 | E13: =IF('Model inputs'!B37="","",'Model inputs'!B37) -> 0.65289589 | F13: =IF('Model inputs'!B35="","",'Model inputs'!B35)
A14: Month 12 operating profit | B14: =IF('NeatRescue — Hackathon subm (3)'!M8="","",'NeatRescue — Hackathon subm (3)'!M8) -> 3405.0137 | C14: =IF('NeatRescue — Hackathon subm (3)'!M9="","",'NeatRescue — Hackathon subm (3)'!M9) -> 348.13545 | D14: =IF('NeatRescue — Hackathon subm (3)'!M10="","",'NeatRescue — Hackathon subm (3)'!M10) -> 10915.296 | E14: =IF('Model inputs'!B56="","",'Model inputs'!B56) -> 3405.0137 | F14: =IF('Model inputs'!B54="","",'Model inputs'!B54) -> -450
A15: Month 12 cash | B15: =IF('NeatRescue — Cash & scenarios ·'!M17="","",'NeatRescue — Cash & scenarios ·'!M17) -> 16344.74 | C15: =IF('Model inputs'!B15="","",'Model inputs'!B15) -> 320.45863 | D15: =IF('Model inputs'!B13="","",'Model inputs'!B13) -> 50598.825 | E15: =IF('NeatRescue — Cash & scenari (2)'!M6="","",'NeatRescue — Cash & scenari (2)'!M6) -> 21344.74 | F15: =IF('NeatRescue — Cash & scenari (2)'!M7="","",'NeatRescue — Cash & scenari (2)'!M7) -> -600
A16: Peak funding gap | B16: =MAX('NeatRescue — Cash & scenarios ·'!B18,'NeatRescue — Cash & scenarios ·'!C18,'NeatRescue — Cash & scenarios ·'!D18,'NeatRescue — Cash & scenarios ·'!E18,'NeatRescue — Cash & scenarios ·'!F18,'NeatRescue — Cash & scenarios ·'!G18,'NeatRescue — Cash & scenarios ·'!H18,'NeatRescue — Cash & scenarios ·'!I18,'NeatRescue — Cash & scenarios ·'!J18,'NeatRescue — Cash & scenarios ·'!K18,'NeatRescue — Cash & scenarios ·'!L18,'NeatRescue — Cash & scenarios ·'!M18) -> 427.43 | C16: =MAX('Model inputs'!D33,'Model inputs'!E33,'Model inputs'!F33,'Model inputs'!G33,'Model inputs'!H33,'Model inputs'!I33,'Model inputs'!J33,'Model inputs'!K33,'Model inputs'!L33,'Model inputs'!M33,'Model inputs'!N33,'Model inputs'!B33) -> 1017.1518 | D16: =MAX('Model inputs'!D31,'Model inputs'!E31,'Model inputs'!F31,'Model inputs'!G31,'Model inputs'!H31,'Model inputs'!I31,'Model inputs'!J31,'Model inputs'!K31,'Model inputs'!L31,'Model inputs'!M31,'Model inputs'!N31,'Model inputs'!B31) -> 354.86 | E16: =MAX('Model inputs'!D32,'Model inputs'!E32,'Model inputs'!F32,'Model inputs'!G32,'Model inputs'!H32,'Model inputs'!I32,'Model inputs'!J32,'Model inputs'!K32,'Model inputs'!L32,'Model inputs'!M32,'Model inputs'!N32,'Model inputs'!B32) -> 0 | F16: =MAX('Model inputs'!D30,'Model inputs'!E30,'Model inputs'!F30,'Model inputs'!G30,'Model inputs'!H30,'Model inputs'!I30,'Model inputs'!J30,'Model inputs'!K30,'Model inputs'!L30,'Model inputs'!M30,'Model inputs'!N30,'Model inputs'!B30) -> 600
A17: Lowest projected cash | B17: =MIN('NeatRescue — Cash & scenarios ·'!B17,'NeatRescue — Cash & scenarios ·'!C17,'NeatRescue — Cash & scenarios ·'!D17,'NeatRescue — Cash & scenarios ·'!E17,'NeatRescue — Cash & scenarios ·'!F17,'NeatRescue — Cash & scenarios ·'!G17,'NeatRescue — Cash & scenarios ·'!H17,'NeatRescue — Cash & scenarios ·'!I17,'NeatRescue — Cash & scenarios ·'!J17,'NeatRescue — Cash & scenarios ·'!K17,'NeatRescue — Cash & scenarios ·'!L17,'NeatRescue — Cash & scenarios ·'!M17) -> -427.43 | C17: =MIN('Model inputs'!D15,'Model inputs'!E15,'Model inputs'!F15,'Model inputs'!G15,'Model inputs'!H15,'Model inputs'!I15,'Model inputs'!J15,'Model inputs'!K15,'Model inputs'!L15,'Model inputs'!M15,'Model inputs'!N15,'Model inputs'!B15) -> -1017.1518 | D17: =MIN('Model inputs'!D13,'Model inputs'!E13,'Model inputs'!F13,'Model inputs'!G13,'Model inputs'!H13,'Model inputs'!I13,'Model inputs'!J13,'Model inputs'!K13,'Model inputs'!L13,'Model inputs'!M13,'Model inputs'!N13,'Model inputs'!B13) -> -354.86 | E17: =MIN('NeatRescue — Cash & scenari (2)'!B6,'NeatRescue — Cash & scenari (2)'!C6,'NeatRescue — Cash & scenari (2)'!D6,'NeatRescue — Cash & scenari (2)'!E6,'NeatRescue — Cash & scenari (2)'!F6,'NeatRescue — Cash & scenari (2)'!G6,'NeatRescue — Cash & scenari (2)'!H6,'NeatRescue — Cash & scenari (2)'!I6,'NeatRescue — Cash & scenari (2)'!J6,'NeatRescue — Cash & scenari (2)'!K6,'NeatRescue — Cash & scenari (2)'!L6,'NeatRescue — Cash & scenari (2)'!M6) -> 4572.57 | F17: =MIN('NeatRescue — Cash & scenari (2)'!B7,'NeatRescue — Cash & scenari (2)'!C7,'NeatRescue — Cash & scenari (2)'!D7,'NeatRescue — Cash & scenari (2)'!E7,'NeatRescue — Cash & scenari (2)'!F7,'NeatRescue — Cash & scenari (2)'!G7,'NeatRescue — Cash & scenari (2)'!H7,'NeatRescue — Cash & scenari (2)'!I7,'NeatRescue — Cash & scenari (2)'!J7,'NeatRescue — Cash & scenari (2)'!K7,'NeatRescue — Cash & scenari (2)'!L7,'NeatRescue — Cash & scenari (2)'!M7) -> -600
A18: Month 12 break-even customers | B18: =IF('NeatRescue — Cash & scenarios ·'!M21="","",'NeatRescue — Cash & scenarios ·'!M21) -> 7 | C18: =IF('Model inputs'!B10="","",'Model inputs'!B10) -> 7 | D18: =IF('Model inputs'!B8="","",'Model inputs'!B8) -> 9 | E18: =IF('Model inputs'!B9="","",'Model inputs'!B9) -> 7 | F18: =IF('Model inputs'!B7="","",'Model inputs'!B7)

Sheet NeatRescue — Hackathon subm (3)
A1: NeatRescue — Hackathon submission · Monthly revenue & operating profit — three cases
A2: Financial model (5 pages) · Main Scenario
A4: Variable / dimension | B4: 2026-10 | C4: 2026-11 | D4: 2026-12 | E4: 2027-01 | F4: 2027-02 | G4: 2027-03 | H4: 2027-04 | I4: 2027-05 | J4: 2027-06 | K4: 2027-07 | L4: 2027-08 | M4: 2027-09
A5: Revenue | B5: =SUM('NeatRescue — Revenue & costs ·'!B27,'NeatRescue — Revenue & costs ·'!B28) -> 321 | C5: =SUM('NeatRescue — Revenue & costs ·'!C27,'NeatRescue — Revenue & costs ·'!C28) -> 658.05 | D5: =SUM('NeatRescue — Revenue & costs ·'!D27,'NeatRescue — Revenue & costs ·'!D28) -> 1013.5575 | E5: =SUM('NeatRescue — Revenue & costs ·'!E27,'NeatRescue — Revenue & costs ·'!E28) -> 1390.1306 | F5: =SUM('NeatRescue — Revenue & costs ·'!F27,'NeatRescue — Revenue & costs ·'!F28) -> 1790.6002 | G5: =SUM('NeatRescue — Revenue & costs ·'!G27,'NeatRescue — Revenue & costs ·'!G28) -> 2218.0439 | H5: =SUM('NeatRescue — Revenue & costs ·'!H27,'NeatRescue — Revenue & costs ·'!H28) -> 2675.8128 | I5: =SUM('NeatRescue — Revenue & costs ·'!I27,'NeatRescue — Revenue & costs ·'!I28) -> 3167.5603 | ... M5: =SUM('NeatRescue — Revenue & costs ·'!M27,'NeatRescue — Revenue & costs ·'!M28) -> 5559.8661
A6: Revenue > Conservative | B6: =SUM('Model inputs'!D70,'Model inputs'!D71) -> 105.75 | C6: =SUM('Model inputs'!E70,'Model inputs'!E71) -> 206.2125 | D6: =SUM('Model inputs'!F70,'Model inputs'!F71) -> 301.90568 | E6: =SUM('Model inputs'!G70,'Model inputs'!G71) -> 393.3091 | F6: =SUM('Model inputs'!H70,'Model inputs'!H71) -> 480.86693 | G6: =SUM('Model inputs'!I70,'Model inputs'!I71) -> 564.99081 | H6: =SUM('Model inputs'!J70,'Model inputs'!J71) -> 646.06257 | I6: =SUM('Model inputs'!K70,'Model inputs'!K71) -> 724.43673 | ... L6: =SUM('Model inputs'!N70,'Model inputs'!N71) -> 946.55526 | M6: =SUM('Model inputs'!B70,'Model inputs'!B71) -> 1017.2136
A7: Revenue > Growth | B7: =SUM('Model inputs'!D65,'Model inputs'!D66) -> 642 | C7: =SUM('Model inputs'!E65,'Model inputs'!E66) -> 1361.04 | D7: =SUM('Model inputs'!F65,'Model inputs'!F66) -> 2169.2538 | E7: =SUM('Model inputs'!G65,'Model inputs'!G66) -> 3080.5779 | F7: =SUM('Model inputs'!H65,'Model inputs'!H66) -> 4111.0226 | G7: =SUM('Model inputs'!I65,'Model inputs'!I66) -> 5278.9832 | H7: =SUM('Model inputs'!J65,'Model inputs'!J66) -> 6605.5988 | I7: =SUM('Model inputs'!K65,'Model inputs'!K66) -> 8115.1636 | ... L7: =SUM('Model inputs'!N65,'Model inputs'!N66) -> 14042.288 | M7: =SUM('Model inputs'!B65,'Model inputs'!B66) -> 16607.854
A8: Operating profit | B8: ='NeatRescue — Cash & scenarios ·'!B7-'NeatRescue — Cash & scenarios ·'!B13 -> -427.43 | C8: ='NeatRescue — Cash & scenarios ·'!C7-'NeatRescue — Cash & scenarios ·'!C13 -> 6.2685 | D8: ='NeatRescue — Cash & scenarios ·'!D7-'NeatRescue — Cash & scenarios ·'!D13 -> 252.76478 | E8: ='NeatRescue — Cash & scenarios ·'!E7-'NeatRescue — Cash & scenarios ·'!E13 -> 513.86721 | F8: ='NeatRescue — Cash & scenarios ·'!F7-'NeatRescue — Cash & scenarios ·'!F13 -> 791.53858 | G8: ='NeatRescue — Cash & scenarios ·'!G7-'NeatRescue — Cash & scenarios ·'!G13 -> 1087.9129 | H8: ='NeatRescue — Cash & scenarios ·'!H7-'NeatRescue — Cash & scenarios ·'!H13 -> 1405.3136 | I8: ='NeatRescue — Cash & scenarios ·'!I7-'NeatRescue — Cash & scenarios ·'!I13 -> 1746.2738 | ... M8: ='NeatRescue — Cash & scenarios ·'!M7-'NeatRescue — Cash & scenarios ·'!M13 -> 3405.0137
A9: Operating profit > Conservative | B9: ='Model inputs'!D41-'Model inputs'!D52 -> -499.8225 | C9: ='Model inputs'!E41-'Model inputs'!E52 -> -228.40387 | D9: ='Model inputs'!F41-'Model inputs'!F52 -> -160.37576 | E9: ='Model inputs'!G41-'Model inputs'!G52 -> -95.397211 | F9: ='Model inputs'!H41-'Model inputs'!H52 -> -33.152495 | G9: ='Model inputs'!I41-'Model inputs'!I52 -> 26.651031 | H9: ='Model inputs'!J41-'Model inputs'!J52 -> 84.284815 | I9: ='Model inputs'!K41-'Model inputs'!K52 -> 140.00087 | ... L9: ='Model inputs'!N41-'Model inputs'!N52 -> 297.90457 | M9: ='Model inputs'!B41-'Model inputs'!B52 -> 348.13545
A10: Operating profit > Growth | B10: ='Model inputs'!D40-'Model inputs'!D50 -> -354.86 | C10: ='Model inputs'!E40-'Model inputs'!E50 -> 343.6968 | D10: ='Model inputs'!F40-'Model inputs'!F50 -> 904.08355 | E10: ='Model inputs'!G40-'Model inputs'!G50 -> 1535.9633 | F10: ='Model inputs'!H40-'Model inputs'!H50 -> 2250.4371 | G10: ='Model inputs'!I40-'Model inputs'!I50 -> 3060.2595 | H10: ='Model inputs'!J40-'Model inputs'!J50 -> 3980.0876 | I10: ='Model inputs'!K40-'Model inputs'!K50 -> 5026.7662 | ... L10: ='Model inputs'!N40-'Model inputs'!N50 -> 9136.4236 | M10: ='Model inputs'!B40-'Model inputs'!B50 -> 10915.296

Sheet NeatRescue — Assumptions & simu
A1: NeatRescue — Assumptions & simulator · Operating assumptions — hypothetical USD
A2: Financial model (5 pages) · Main Scenario
A4: Variable / dimension | B4: Value
A5: Monthly acquisition growth | B5: =0.1 -> 0.1
A6: Monthly customer churn | B6: =0.05 -> 0.05
A7: Inference cost per verification | B7: =0.05 -> 0.05
A8: Compute cost per verification | B8: =0.015 -> 0.015
A9: Logging cost per verification | B9: =0.005 -> 0.005
A10: Monthly hosting budget | B10: =60 -> 60
A11: Monthly compute baseline | B11: =40 -> 40
A12: Monthly logging baseline | B12: =25 -> 25
A13: Monthly security budget | B13: =75 -> 75
A14: Monthly support baseline | B14: =100 -> 100
A15: Monthly acquisition budget | B15: =150 -> 150
A16: Launch expense | B16: =200 -> 200
A17: Opening cash | B17: =0 -> 0
A18: Payment processing rate | B18: =0.03 -> 0.03
A19: Founder monthly pay | B19: =0 -> 0
A20: Minimum cash reserve | B20: =0 -> 0

Sheet NeatRescue — Assumptions & (2)
A1: NeatRescue — Assumptions & simulator · Pricing & acquisition assumptions — hypothetical
A2: Financial model (5 pages) · Main Scenario
A4: Variable / dimension | B4: Monthly subscription price | C4: Included verifications | D4: Verifications per customer | E4: Overage price per verification | F4: Support cost per customer | G4: First-month new customers
A5: Starter | B5: =49 -> 49 | C5: =100 -> 100 | D5: =120 -> 120 | E5: =0.1 -> 0.1 | F5: =2 -> 2 | G5: =2 -> 2
A6: Team | B6: =199 -> 199 | C6: =600 -> 600 | D6: =800 -> 800 | E6: =0.1 -> 0.1 | F6: =12 -> 12 | G6: =1 -> 1

Sheet NeatRescue — Assumptions & (3)
A1: NeatRescue — Assumptions & simulator · Per-customer contribution & usage price floor
A2: Financial model (5 pages) · Main Scenario
A4: Variable / dimension | B4: Effective monthly bill | C4: Verification unit cost | D4: Unit contribution per customer | E4: Unit contribution percentage | F4: Usage inference break-even ceiling | G4: Minimum usage price at cost
A5: Starter | B5: ='NeatRescue — Assumptions & (2)'!B5+MAX('NeatRescue — Assumptions & (2)'!D5-'NeatRescue — Assumptions & (2)'!C5,0)*'NeatRescue — Assumptions & (2)'!E5 -> 51 | C5: ='NeatRescue — Assumptions & simu'!B7+'NeatRescue — Assumptions & simu'!B8+'NeatRescue — Assumptions & simu'!B9 -> 0.07 | D5: ='NeatRescue — Assumptions & (3)'!B5*(1-'NeatRescue — Assumptions & simu'!B18)-'NeatRescue — Assumptions & (2)'!D5*'NeatRescue — Assumptions & (3)'!C5-'NeatRescue — Assumptions & (2)'!F5 -> 39.07 | E5: =IFERROR('NeatRescue — Assumptions & (3)'!D5/'NeatRescue — Assumptions & (3)'!B5,"") -> 0.76607843 | F5: ='NeatRescue — Assumptions & (2)'!E5*(1-'NeatRescue — Assumptions & simu'!B18)-'NeatRescue — Assumptions & simu'!B8-'NeatRescue — Assumptions & simu'!B9 -> 0.077 | G5: =IFERROR('NeatRescue — Assumptions & (3)'!C5/(1-'NeatRescue — Assumptions & simu'!B18),"") -> 0.072164948
A6: Team | B6: ='NeatRescue — Assumptions & (2)'!B6+MAX('NeatRescue — Assumptions & (2)'!D6-'NeatRescue — Assumptions & (2)'!C6,0)*'NeatRescue — Assumptions & (2)'!E6 -> 219 | C6: ='NeatRescue — Assumptions & simu'!B7+'NeatRescue — Assumptions & simu'!B8+'NeatRescue — Assumptions & simu'!B9 -> 0.07 | D6: ='NeatRescue — Assumptions & (3)'!B6*(1-'NeatRescue — Assumptions & simu'!B18)-'NeatRescue — Assumptions & (2)'!D6*'NeatRescue — Assumptions & (3)'!C6-'NeatRescue — Assumptions & (2)'!F6 -> 144.43 | E6: =IFERROR('NeatRescue — Assumptions & (3)'!D6/'NeatRescue — Assumptions & (3)'!B6,"") -> 0.65949772 | F6: ='NeatRescue — Assumptions & (2)'!E6*(1-'NeatRescue — Assumptions & simu'!B18)-'NeatRescue — Assumptions & simu'!B8-'NeatRescue — Assumptions & simu'!B9 -> 0.077 | G6: =IFERROR('NeatRescue — Assumptions & (3)'!C6/(1-'NeatRescue — Assumptions & simu'!B18),"") -> 0.072164948

Sheet NeatRescue — Revenue & costs ·
A1: NeatRescue — Revenue & costs · Customers, usage & unit economics
A2: Financial model (5 pages) · Main Scenario
A4: Variable / dimension | B4: 2026-10 | C4: 2026-11 | D4: 2026-12 | E4: 2027-01 | F4: 2027-02 | G4: 2027-03 | H4: 2027-04 | I4: 2027-05 | J4: 2027-06 | K4: 2027-07 | L4: 2027-08 | M4: 2027-09
A5: New customers | B5: =SUM('NeatRescue — Revenue & costs ·'!B6,'NeatRescue — Revenue & costs ·'!B7) -> 3 | C5: =SUM('NeatRescue — Revenue & costs ·'!C6,'NeatRescue — Revenue & costs ·'!C7) -> 3.3 | D5: =SUM('NeatRescue — Revenue & costs ·'!D6,'NeatRescue — Revenue & costs ·'!D7) -> 3.63 | E5: =SUM('NeatRescue — Revenue & costs ·'!E6,'NeatRescue — Revenue & costs ·'!E7) -> 3.993 | F5: =SUM('NeatRescue — Revenue & costs ·'!F6,'NeatRescue — Revenue & costs ·'!F7) -> 4.3923 | G5: =SUM('NeatRescue — Revenue & costs ·'!G6,'NeatRescue — Revenue & costs ·'!G7) -> 4.83153 | H5: =SUM('NeatRescue — Revenue & costs ·'!H6,'NeatRescue — Revenue & costs ·'!H7) -> 5.314683 | I5: =SUM('NeatRescue — Revenue & costs ·'!I6,'NeatRescue — Revenue & costs ·'!I7) -> 5.8461513 | ... M5: =SUM('NeatRescue — Revenue & costs ·'!M6,'NeatRescue — Revenue & costs ·'!M7) -> 8.5593501
A6: Starter | B6: =IF('NeatRescue — Assumptions & (2)'!G5="","",'NeatRescue — Assumptions & (2)'!G5) -> 2 | C6: ='NeatRescue — Revenue & costs ·'!B6*(1+'NeatRescue — Assumptions & simu'!B5) -> 2.2 | D6: ='NeatRescue — Revenue & costs ·'!C6*(1+'NeatRescue — Assumptions & simu'!B5) -> 2.42 | E6: ='NeatRescue — Revenue & costs ·'!D6*(1+'NeatRescue — Assumptions & simu'!B5) -> 2.662 | F6: ='NeatRescue — Revenue & costs ·'!E6*(1+'NeatRescue — Assumptions & simu'!B5) -> 2.9282 | G6: ='NeatRescue — Revenue & costs ·'!F6*(1+'NeatRescue — Assumptions & simu'!B5) -> 3.22102 | H6: ='NeatRescue — Revenue & costs ·'!G6*(1+'NeatRescue — Assumptions & simu'!B5) -> 3.543122 | I6: ='NeatRescue — Revenue & costs ·'!H6*(1+'NeatRescue — Assumptions & simu'!B5) -> 3.8974342 | J6: ='NeatRescue — Revenue & costs ·'!I6*(1+'NeatRescue — Assumptions & simu'!B5) -> 4.2871776 | K6: ='NeatRescue — Revenue & costs ·'!J6*(1+'NeatRescue — Assumptions & simu'!B5) -> 4.7158954 | L6: ='NeatRescue — Revenue & costs ·'!K6*(1+'NeatRescue — Assumptions & simu'!B5) -> 5.1874849 | M6: ='NeatRescue — Revenue & costs ·'!L6*(1+'NeatRescue — Assumptions & simu'!B5) -> 5.7062334
A7: Team | B7: =IF('NeatRescue — Assumptions & (2)'!G6="","",'NeatRescue — Assumptions & (2)'!G6) -> 1 | C7: ='NeatRescue — Revenue & costs ·'!B7*(1+'NeatRescue — Assumptions & simu'!B5) -> 1.1 | D7: ='NeatRescue — Revenue & costs ·'!C7*(1+'NeatRescue — Assumptions & simu'!B5) -> 1.21 | E7: ='NeatRescue — Revenue & costs ·'!D7*(1+'NeatRescue — Assumptions & simu'!B5) -> 1.331 | F7: ='NeatRescue — Revenue & costs ·'!E7*(1+'NeatRescue — Assumptions & simu'!B5) -> 1.4641 | G7: ='NeatRescue — Revenue & costs ·'!F7*(1+'NeatRescue — Assumptions & simu'!B5) -> 1.61051 | H7: ='NeatRescue — Revenue & costs ·'!G7*(1+'NeatRescue — Assumptions & simu'!B5) -> 1.771561 | I7: ='NeatRescue — Revenue & costs ·'!H7*(1+'NeatRescue — Assumptions & simu'!B5) -> 1.9487171 | J7: ='NeatRescue — Revenue & costs ·'!I7*(1+'NeatRescue — Assumptions & simu'!B5) -> 2.1435888 | K7: ='NeatRescue — Revenue & costs ·'!J7*(1+'NeatRescue — Assumptions & simu'!B5) -> 2.3579477 | L7: ='NeatRescue — Revenue & costs ·'!K7*(1+'NeatRescue — Assumptions & simu'!B5) -> 2.5937425 | M7: ='NeatRescue — Revenue & costs ·'!L7*(1+'NeatRescue — Assumptions & simu'!B5) -> 2.8531167
A8: Opening customers | B8: =SUM('NeatRescue — Revenue & costs ·'!B9,'NeatRescue — Revenue & costs ·'!B10) -> 0 | C8: =SUM('NeatRescue — Revenue & costs ·'!C9,'NeatRescue — Revenue & costs ·'!C10) -> 3 | D8: =SUM('NeatRescue — Revenue & costs ·'!D9,'NeatRescue — Revenue & costs ·'!D10) -> 6.15 | E8: =SUM('NeatRescue — Revenue & costs ·'!E9,'NeatRescue — Revenue & costs ·'!E10) -> 9.4725 | F8: =SUM('NeatRescue — Revenue & costs ·'!F9,'NeatRescue — Revenue & costs ·'!F10) -> 12.991875 | G8: =SUM('NeatRescue — Revenue & costs ·'!G9,'NeatRescue — Revenue & costs ·'!G10) -> 16.734581 | H8: =SUM('NeatRescue — Revenue & costs ·'!H9,'NeatRescue — Revenue & costs ·'!H10) -> 20.729382 | I8: =SUM('NeatRescue — Revenue & costs ·'!I9,'NeatRescue — Revenue & costs ·'!I10) -> 25.007596 | ... M8: =SUM('NeatRescue — Revenue & costs ·'!M9,'NeatRescue — Revenue & costs ·'!M10) -> 45.686332
A9: Starter | B9: =IF('Model inputs'!C18="","",'Model inputs'!C18) -> 0 | C9: =IF('NeatRescue — Revenue & costs ·'!B15="","",'NeatRescue — Revenue & costs ·'!B15) -> 2 | D9: =IF('NeatRescue — Revenue & costs ·'!C15="","",'NeatRescue — Revenue & costs ·'!C15) -> 4.1 | E9: =IF('NeatRescue — Revenue & costs ·'!D15="","",'NeatRescue — Revenue & costs ·'!D15) -> 6.315 | F9: =IF('NeatRescue — Revenue & costs ·'!E15="","",'NeatRescue — Revenue & costs ·'!E15) -> 8.66125 | G9: =IF('NeatRescue — Revenue & costs ·'!F15="","",'NeatRescue — Revenue & costs ·'!F15) -> 11.156388 | H9: =IF('NeatRescue — Revenue & costs ·'!G15="","",'NeatRescue — Revenue & costs ·'!G15) -> 13.819588 | I9: =IF('NeatRescue — Revenue & costs ·'!H15="","",'NeatRescue — Revenue & costs ·'!H15) -> 16.671731 | J9: =IF('NeatRescue — Revenue & costs ·'!I15="","",'NeatRescue — Revenue & costs ·'!I15) -> 19.735578 | ... M9: =IF('NeatRescue — Revenue & costs ·'!L15="","",'NeatRescue — Revenue & costs ·'!L15) -> 30.457555
A10: Team | B10: =IF('Model inputs'!C19="","",'Model inputs'!C19) -> 0 | C10: =IF('NeatRescue — Revenue & costs ·'!B16="","",'NeatRescue — Revenue & costs ·'!B16) -> 1 | D10: =IF('NeatRescue — Revenue & costs ·'!C16="","",'NeatRescue — Revenue & costs ·'!C16) -> 2.05 | E10: =IF('NeatRescue — Revenue & costs ·'!D16="","",'NeatRescue — Revenue & costs ·'!D16) -> 3.1575 | F10: =IF('NeatRescue — Revenue & costs ·'!E16="","",'NeatRescue — Revenue & costs ·'!E16) -> 4.330625 | G10: =IF('NeatRescue — Revenue & costs ·'!F16="","",'NeatRescue — Revenue & costs ·'!F16) -> 5.5781938 | H10: =IF('NeatRescue — Revenue & costs ·'!G16="","",'NeatRescue — Revenue & costs ·'!G16) -> 6.9097941 | I10: =IF('NeatRescue — Revenue & costs ·'!H16="","",'NeatRescue — Revenue & costs ·'!H16) -> 8.3358654 | J10: =IF('NeatRescue — Revenue & costs ·'!I16="","",'NeatRescue — Revenue & costs ·'!I16) -> 9.8677892 | ... M10: =IF('NeatRescue — Revenue & costs ·'!L16="","",'NeatRescue — Revenue & costs ·'!L16) -> 15.228777
A11: Churned customers | B11: =SUM('NeatRescue — Revenue & costs ·'!B12,'NeatRescue — Revenue & costs ·'!B13) -> 0 | C11: =SUM('NeatRescue — Revenue & costs ·'!C12,'NeatRescue — Revenue & costs ·'!C13) -> 0.15 | D11: =SUM('NeatRescue — Revenue & costs ·'!D12,'NeatRescue — Revenue & costs ·'!D13) -> 0.3075 | E11: =SUM('NeatRescue — Revenue & costs ·'!E12,'NeatRescue — Revenue & costs ·'!E13) -> 0.473625 | F11: =SUM('NeatRescue — Revenue & costs ·'!F12,'NeatRescue — Revenue & costs ·'!F13) -> 0.64959375 | G11: =SUM('NeatRescue — Revenue & costs ·'!G12,'NeatRescue — Revenue & costs ·'!G13) -> 0.83672906 | H11: =SUM('NeatRescue — Revenue & costs ·'!H12,'NeatRescue — Revenue & costs ·'!H13) -> 1.0364691 | I11: =SUM('NeatRescue — Revenue & costs ·'!I12,'NeatRescue — Revenue & costs ·'!I13) -> 1.2503798 | ... M11: =SUM('NeatRescue — Revenue & costs ·'!M12,'NeatRescue — Revenue & costs ·'!M13) -> 2.2843166
A12: Starter | B12: ='NeatRescue — Revenue & costs ·'!B9*'NeatRescue — Assumptions & simu'!B6 -> 0 | C12: ='NeatRescue — Revenue & costs ·'!C9*'NeatRescue — Assumptions & simu'!B6 -> 0.1 | D12: ='NeatRescue — Revenue & costs ·'!D9*'NeatRescue — Assumptions & simu'!B6 -> 0.205 | E12: ='NeatRescue — Revenue & costs ·'!E9*'NeatRescue — Assumptions & simu'!B6 -> 0.31575 | F12: ='NeatRescue — Revenue & costs ·'!F9*'NeatRescue — Assumptions & simu'!B6 -> 0.4330625 | G12: ='NeatRescue — Revenue & costs ·'!G9*'NeatRescue — Assumptions & simu'!B6 -> 0.55781938 | H12: ='NeatRescue — Revenue & costs ·'!H9*'NeatRescue — Assumptions & simu'!B6 -> 0.69097941 | I12: ='NeatRescue — Revenue & costs ·'!I9*'NeatRescue — Assumptions & simu'!B6 -> 0.83358654 | J12: ='NeatRescue — Revenue & costs ·'!J9*'NeatRescue — Assumptions & simu'!B6 -> 0.98677892 | K12: ='NeatRescue — Revenue & costs ·'!K9*'NeatRescue — Assumptions & simu'!B6 -> 1.1517989 | L12: ='NeatRescue — Revenue & costs ·'!L9*'NeatRescue — Assumptions & simu'!B6 -> 1.3300037 | M12: ='NeatRescue — Revenue & costs ·'!M9*'NeatRescue — Assumptions & simu'!B6 -> 1.5228777
A13: Team | B13: ='NeatRescue — Revenue & costs ·'!B10*'NeatRescue — Assumptions & simu'!B6 -> 0 | C13: ='NeatRescue — Revenue & costs ·'!C10*'NeatRescue — Assumptions & simu'!B6 -> 0.05 | D13: ='NeatRescue — Revenue & costs ·'!D10*'NeatRescue — Assumptions & simu'!B6 -> 0.1025 | E13: ='NeatRescue — Revenue & costs ·'!E10*'NeatRescue — Assumptions & simu'!B6 -> 0.157875 | F13: ='NeatRescue — Revenue & costs ·'!F10*'NeatRescue — Assumptions & simu'!B6 -> 0.21653125 | G13: ='NeatRescue — Revenue & costs ·'!G10*'NeatRescue — Assumptions & simu'!B6 -> 0.27890969 | H13: ='NeatRescue — Revenue & costs ·'!H10*'NeatRescue — Assumptions & simu'!B6 -> 0.3454897 | I13: ='NeatRescue — Revenue & costs ·'!I10*'NeatRescue — Assumptions & simu'!B6 -> 0.41679327 | J13: ='NeatRescue — Revenue & costs ·'!J10*'NeatRescue — Assumptions & simu'!B6 -> 0.49338946 | K13: ='NeatRescue — Revenue & costs ·'!K10*'NeatRescue — Assumptions & simu'!B6 -> 0.57589943 | L13: ='NeatRescue — Revenue & costs ·'!L10*'NeatRescue — Assumptions & simu'!B6 -> 0.66500184 | M13: ='NeatRescue — Revenue & costs ·'!M10*'NeatRescue — Assumptions & simu'!B6 -> 0.76143887
A14: Closing customers | B14: =SUM('NeatRescue — Revenue & costs ·'!B15,'NeatRescue — Revenue & costs ·'!B16) -> 3 | C14: =SUM('NeatRescue — Revenue & costs ·'!C15,'NeatRescue — Revenue & costs ·'!C16) -> 6.15 | D14: =SUM('NeatRescue — Revenue & costs ·'!D15,'NeatRescue — Revenue & costs ·'!D16) -> 9.4725 | E14: =SUM('NeatRescue — Revenue & costs ·'!E15,'NeatRescue — Revenue & costs ·'!E16) -> 12.991875 | F14: =SUM('NeatRescue — Revenue & costs ·'!F15,'NeatRescue — Revenue & costs ·'!F16) -> 16.734581 | G14: =SUM('NeatRescue — Revenue & costs ·'!G15,'NeatRescue — Revenue & costs ·'!G16) -> 20.729382 | H14: =SUM('NeatRescue — Revenue & costs ·'!H15,'NeatRescue — Revenue & costs ·'!H16) -> 25.007596 | I14: =SUM('NeatRescue — Revenue & costs ·'!I15,'NeatRescue — Revenue & costs ·'!I16) -> 29.603368 | ... M14: =SUM('NeatRescue — Revenue & costs ·'!M15,'NeatRescue — Revenue & costs ·'!M16) -> 51.961366
A15: Starter | B15: ='NeatRescue — Revenue & costs ·'!B9+'NeatRescue — Revenue & costs ·'!B6-'NeatRescue — Revenue & costs ·'!B12 -> 2 | C15: ='NeatRescue — Revenue & costs ·'!C9+'NeatRescue — Revenue & costs ·'!C6-'NeatRescue — Revenue & costs ·'!C12 -> 4.1 | D15: ='NeatRescue — Revenue & costs ·'!D9+'NeatRescue — Revenue & costs ·'!D6-'NeatRescue — Revenue & costs ·'!D12 -> 6.315 | E15: ='NeatRescue — Revenue & costs ·'!E9+'NeatRescue — Revenue & costs ·'!E6-'NeatRescue — Revenue & costs ·'!E12 -> 8.66125 | F15: ='NeatRescue — Revenue & costs ·'!F9+'NeatRescue — Revenue & costs ·'!F6-'NeatRescue — Revenue & costs ·'!F12 -> 11.156388 | G15: ='NeatRescue — Revenue & costs ·'!G9+'NeatRescue — Revenue & costs ·'!G6-'NeatRescue — Revenue & costs ·'!G12 -> 13.819588 | H15: ='NeatRescue — Revenue & costs ·'!H9+'NeatRescue — Revenue & costs ·'!H6-'NeatRescue — Revenue & costs ·'!H12 -> 16.671731 | I15: ='NeatRescue — Revenue & costs ·'!I9+'NeatRescue — Revenue & costs ·'!I6-'NeatRescue — Revenue & costs ·'!I12 -> 19.735578 | ... M15: ='NeatRescue — Revenue & costs ·'!M9+'NeatRescue — Revenue & costs ·'!M6-'NeatRescue — Revenue & costs ·'!M12 -> 34.640911
A16: Team | B16: ='NeatRescue — Revenue & costs ·'!B10+'NeatRescue — Revenue & costs ·'!B7-'NeatRescue — Revenue & costs ·'!B13 -> 1 | C16: ='NeatRescue — Revenue & costs ·'!C10+'NeatRescue — Revenue & costs ·'!C7-'NeatRescue — Revenue & costs ·'!C13 -> 2.05 | D16: ='NeatRescue — Revenue & costs ·'!D10+'NeatRescue — Revenue & costs ·'!D7-'NeatRescue — Revenue & costs ·'!D13 -> 3.1575 | E16: ='NeatRescue — Revenue & costs ·'!E10+'NeatRescue — Revenue & costs ·'!E7-'NeatRescue — Revenue & costs ·'!E13 -> 4.330625 | F16: ='NeatRescue — Revenue & costs ·'!F10+'NeatRescue — Revenue & costs ·'!F7-'NeatRescue — Revenue & costs ·'!F13 -> 5.5781938 | G16: ='NeatRescue — Revenue & costs ·'!G10+'NeatRescue — Revenue & costs ·'!G7-'NeatRescue — Revenue & costs ·'!G13 -> 6.9097941 | H16: ='NeatRescue — Revenue & costs ·'!H10+'NeatRescue — Revenue & costs ·'!H7-'NeatRescue — Revenue & costs ·'!H13 -> 8.3358654 | I16: ='NeatRescue — Revenue & costs ·'!I10+'NeatRescue — Revenue & costs ·'!I7-'NeatRescue — Revenue & costs ·'!I13 -> 9.8677892 | ... M16: ='NeatRescue — Revenue & costs ·'!M10+'NeatRescue — Revenue & costs ·'!M7-'NeatRescue — Revenue & costs ·'!M13 -> 17.320455
A17: Billed verifications | B17: =SUM('NeatRescue — Revenue & costs ·'!B18,'NeatRescue — Revenue & costs ·'!B19) -> 1040 | C17: =SUM('NeatRescue — Revenue & costs ·'!C18,'NeatRescue — Revenue & costs ·'!C19) -> 2132 | D17: =SUM('NeatRescue — Revenue & costs ·'!D18,'NeatRescue — Revenue & costs ·'!D19) -> 3283.8 | E17: =SUM('NeatRescue — Revenue & costs ·'!E18,'NeatRescue — Revenue & costs ·'!E19) -> 4503.85 | F17: =SUM('NeatRescue — Revenue & costs ·'!F18,'NeatRescue — Revenue & costs ·'!F19) -> 5801.3215 | G17: =SUM('NeatRescue — Revenue & costs ·'!G18,'NeatRescue — Revenue & costs ·'!G19) -> 7186.1858 | H17: =SUM('NeatRescue — Revenue & costs ·'!H18,'NeatRescue — Revenue & costs ·'!H19) -> 8669.3 | I17: =SUM('NeatRescue — Revenue & costs ·'!I18,'NeatRescue — Revenue & costs ·'!I19) -> 10262.501 | ... M17: =SUM('NeatRescue — Revenue & costs ·'!M18,'NeatRescue — Revenue & costs ·'!M19) -> 18013.273
A18: Starter | B18: ='NeatRescue — Revenue & costs ·'!B15*'NeatRescue — Assumptions & (2)'!D5 -> 240 | C18: ='NeatRescue — Revenue & costs ·'!C15*'NeatRescue — Assumptions & (2)'!D5 -> 492 | D18: ='NeatRescue — Revenue & costs ·'!D15*'NeatRescue — Assumptions & (2)'!D5 -> 757.8 | E18: ='NeatRescue — Revenue & costs ·'!E15*'NeatRescue — Assumptions & (2)'!D5 -> 1039.35 | F18: ='NeatRescue — Revenue & costs ·'!F15*'NeatRescue — Assumptions & (2)'!D5 -> 1338.7665 | G18: ='NeatRescue — Revenue & costs ·'!G15*'NeatRescue — Assumptions & (2)'!D5 -> 1658.3506 | H18: ='NeatRescue — Revenue & costs ·'!H15*'NeatRescue — Assumptions & (2)'!D5 -> 2000.6077 | I18: ='NeatRescue — Revenue & costs ·'!I15*'NeatRescue — Assumptions & (2)'!D5 -> 2368.2694 | J18: ='NeatRescue — Revenue & costs ·'!J15*'NeatRescue — Assumptions & (2)'!D5 -> 2764.3173 | K18: ='NeatRescue — Revenue & costs ·'!K15*'NeatRescue — Assumptions & (2)'!D5 -> 3192.0088 | L18: ='NeatRescue — Revenue & costs ·'!L15*'NeatRescue — Assumptions & (2)'!D5 -> 3654.9066 | M18: ='NeatRescue — Revenue & costs ·'!M15*'NeatRescue — Assumptions & (2)'!D5 -> 4156.9093
A19: Team | B19: ='NeatRescue — Revenue & costs ·'!B16*'NeatRescue — Assumptions & (2)'!D6 -> 800 | C19: ='NeatRescue — Revenue & costs ·'!C16*'NeatRescue — Assumptions & (2)'!D6 -> 1640 | D19: ='NeatRescue — Revenue & costs ·'!D16*'NeatRescue — Assumptions & (2)'!D6 -> 2526 | E19: ='NeatRescue — Revenue & costs ·'!E16*'NeatRescue — Assumptions & (2)'!D6 -> 3464.5 | F19: ='NeatRescue — Revenue & costs ·'!F16*'NeatRescue — Assumptions & (2)'!D6 -> 4462.555 | G19: ='NeatRescue — Revenue & costs ·'!G16*'NeatRescue — Assumptions & (2)'!D6 -> 5527.8353 | H19: ='NeatRescue — Revenue & costs ·'!H16*'NeatRescue — Assumptions & (2)'!D6 -> 6668.6923 | I19: ='NeatRescue — Revenue & costs ·'!I16*'NeatRescue — Assumptions & (2)'!D6 -> 7894.2314 | J19: ='NeatRescue — Revenue & costs ·'!J16*'NeatRescue — Assumptions & (2)'!D6 -> 9214.3908 | K19: ='NeatRescue — Revenue & costs ·'!K16*'NeatRescue — Assumptions & (2)'!D6 -> 10640.029 | L19: ='NeatRescue — Revenue & costs ·'!L16*'NeatRescue — Assumptions & (2)'!D6 -> 12183.022 | M19: ='NeatRescue — Revenue & costs ·'!M16*'NeatRescue — Assumptions & (2)'!D6 -> 13856.364
A20: Subscription revenue | B20: =SUM('NeatRescue — Revenue & costs ·'!B21,'NeatRescue — Revenue & costs ·'!B22) -> 297 | C20: =SUM('NeatRescue — Revenue & costs ·'!C21,'NeatRescue — Revenue & costs ·'!C22) -> 608.85 | D20: =SUM('NeatRescue — Revenue & costs ·'!D21,'NeatRescue — Revenue & costs ·'!D22) -> 937.7775 | E20: =SUM('NeatRescue — Revenue & costs ·'!E21,'NeatRescue — Revenue & costs ·'!E22) -> 1286.1956 | F20: =SUM('NeatRescue — Revenue & costs ·'!F21,'NeatRescue — Revenue & costs ·'!F22) -> 1656.7235 | G20: =SUM('NeatRescue — Revenue & costs ·'!G21,'NeatRescue — Revenue & costs ·'!G22) -> 2052.2088 | H20: =SUM('NeatRescue — Revenue & costs ·'!H21,'NeatRescue — Revenue & costs ·'!H22) -> 2475.752 | I20: =SUM('NeatRescue — Revenue & costs ·'!I21,'NeatRescue — Revenue & costs ·'!I22) -> 2930.7334 | ... M20: =SUM('NeatRescue — Revenue & costs ·'!M21,'NeatRescue — Revenue & costs ·'!M22) -> 5144.1752
A21: Starter | B21: ='NeatRescue — Revenue & costs ·'!B15*'NeatRescue — Assumptions & (2)'!B5 -> 98 | C21: ='NeatRescue — Revenue & costs ·'!C15*'NeatRescue — Assumptions & (2)'!B5 -> 200.9 | D21: ='NeatRescue — Revenue & costs ·'!D15*'NeatRescue — Assumptions & (2)'!B5 -> 309.435 | E21: ='NeatRescue — Revenue & costs ·'!E15*'NeatRescue — Assumptions & (2)'!B5 -> 424.40125 | F21: ='NeatRescue — Revenue & costs ·'!F15*'NeatRescue — Assumptions & (2)'!B5 -> 546.66299 | G21: ='NeatRescue — Revenue & costs ·'!G15*'NeatRescue — Assumptions & (2)'!B5 -> 677.15982 | H21: ='NeatRescue — Revenue & costs ·'!H15*'NeatRescue — Assumptions & (2)'!B5 -> 816.91481 | I21: ='NeatRescue — Revenue & costs ·'!I15*'NeatRescue — Assumptions & (2)'!B5 -> 967.04334 | J21: ='NeatRescue — Revenue & costs ·'!J15*'NeatRescue — Assumptions & (2)'!B5 -> 1128.7629 | K21: ='NeatRescue — Revenue & costs ·'!K15*'NeatRescue — Assumptions & (2)'!B5 -> 1303.4036 | L21: ='NeatRescue — Revenue & costs ·'!L15*'NeatRescue — Assumptions & (2)'!B5 -> 1492.4202 | M21: ='NeatRescue — Revenue & costs ·'!M15*'NeatRescue — Assumptions & (2)'!B5 -> 1697.4046
A22: Team | B22: ='NeatRescue — Revenue & costs ·'!B16*'NeatRescue — Assumptions & (2)'!B6 -> 199 | C22: ='NeatRescue — Revenue & costs ·'!C16*'NeatRescue — Assumptions & (2)'!B6 -> 407.95 | D22: ='NeatRescue — Revenue & costs ·'!D16*'NeatRescue — Assumptions & (2)'!B6 -> 628.3425 | E22: ='NeatRescue — Revenue & costs ·'!E16*'NeatRescue — Assumptions & (2)'!B6 -> 861.79438 | F22: ='NeatRescue — Revenue & costs ·'!F16*'NeatRescue — Assumptions & (2)'!B6 -> 1110.0606 | G22: ='NeatRescue — Revenue & costs ·'!G16*'NeatRescue — Assumptions & (2)'!B6 -> 1375.049 | H22: ='NeatRescue — Revenue & costs ·'!H16*'NeatRescue — Assumptions & (2)'!B6 -> 1658.8372 | I22: ='NeatRescue — Revenue & costs ·'!I16*'NeatRescue — Assumptions & (2)'!B6 -> 1963.69 | J22: ='NeatRescue — Revenue & costs ·'!J16*'NeatRescue — Assumptions & (2)'!B6 -> 2292.0797 | K22: ='NeatRescue — Revenue & costs ·'!K16*'NeatRescue — Assumptions & (2)'!B6 -> 2646.7073 | L22: ='NeatRescue — Revenue & costs ·'!L16*'NeatRescue — Assumptions & (2)'!B6 -> 3030.5267 | M22: ='NeatRescue — Revenue & costs ·'!M16*'NeatRescue — Assumptions & (2)'!B6 -> 3446.7706
A23: Verification overage revenue | B23: =SUM('NeatRescue — Revenue & costs ·'!B24,'NeatRescue — Revenue & costs ·'!B25) -> 24 | C23: =SUM('NeatRescue — Revenue & costs ·'!C24,'NeatRescue — Revenue & costs ·'!C25) -> 49.2 | D23: =SUM('NeatRescue — Revenue & costs ·'!D24,'NeatRescue — Revenue & costs ·'!D25) -> 75.78 | E23: =SUM('NeatRescue — Revenue & costs ·'!E24,'NeatRescue — Revenue & costs ·'!E25) -> 103.935 | F23: =SUM('NeatRescue — Revenue & costs ·'!F24,'NeatRescue — Revenue & costs ·'!F25) -> 133.87665 | G23: =SUM('NeatRescue — Revenue & costs ·'!G24,'NeatRescue — Revenue & costs ·'!G25) -> 165.83506 | H23: =SUM('NeatRescue — Revenue & costs ·'!H24,'NeatRescue — Revenue & costs ·'!H25) -> 200.06077 | I23: =SUM('NeatRescue — Revenue & costs ·'!I24,'NeatRescue — Revenue & costs ·'!I25) -> 236.82694 | ... M23: =SUM('NeatRescue — Revenue & costs ·'!M24,'NeatRescue — Revenue & costs ·'!M25) -> 415.69093
A24: Starter | B24: ='NeatRescue — Revenue & costs ·'!B15*MAX('NeatRescue — Assumptions & (2)'!D5-'NeatRescue — Assumptions & (2)'!C5,0)*'NeatRescue — Assumptions & (2)'!E5 -> 4 | C24: ='NeatRescue — Revenue & costs ·'!C15*MAX('NeatRescue — Assumptions & (2)'!D5-'NeatRescue — Assumptions & (2)'!C5,0)*'NeatRescue — Assumptions & (2)'!E5 -> 8.2 | D24: ='NeatRescue — Revenue & costs ·'!D15*MAX('NeatRescue — Assumptions & (2)'!D5-'NeatRescue — Assumptions & (2)'!C5,0)*'NeatRescue — Assumptions & (2)'!E5 -> 12.63 | E24: ='NeatRescue — Revenue & costs ·'!E15*MAX('NeatRescue — Assumptions & (2)'!D5-'NeatRescue — Assumptions & (2)'!C5,0)*'NeatRescue — Assumptions & (2)'!E5 -> 17.3225 | F24: ='NeatRescue — Revenue & costs ·'!F15*MAX('NeatRescue — Assumptions & (2)'!D5-'NeatRescue — Assumptions & (2)'!C5,0)*'NeatRescue — Assumptions & (2)'!E5 -> 22.312775 | G24: ='NeatRescue — Revenue & costs ·'!G15*MAX('NeatRescue — Assumptions & (2)'!D5-'NeatRescue — Assumptions & (2)'!C5,0)*'NeatRescue — Assumptions & (2)'!E5 -> 27.639176 | H24: ='NeatRescue — Revenue & costs ·'!H15*MAX('NeatRescue — Assumptions & (2)'!D5-'NeatRescue — Assumptions & (2)'!C5,0)*'NeatRescue — Assumptions & (2)'!E5 -> 33.343461 | I24: ='NeatRescue — Revenue & costs ·'!I15*MAX('NeatRescue — Assumptions & (2)'!D5-'NeatRescue — Assumptions & (2)'!C5,0)*'NeatRescue — Assumptions & (2)'!E5 -> 39.471157 | J24: ='NeatRescue — Revenue & costs ·'!J15*MAX('NeatRescue — Assumptions & (2)'!D5-'NeatRescue — Assumptions & (2)'!C5,0)*'NeatRescue — Assumptions & (2)'!E5 -> 46.071954 | K24: ='NeatRescue — Revenue & costs ·'!K15*MAX('NeatRescue — Assumptions & (2)'!D5-'NeatRescue — Assumptions & (2)'!C5,0)*'NeatRescue — Assumptions & (2)'!E5 -> 53.200147 | L24: ='NeatRescue — Revenue & costs ·'!L15*MAX('NeatRescue — Assumptions & (2)'!D5-'NeatRescue — Assumptions & (2)'!C5,0)*'NeatRescue — Assumptions & (2)'!E5 -> 60.91511 | M24: ='NeatRescue — Revenue & costs ·'!M15*MAX('NeatRescue — Assumptions & (2)'!D5-'NeatRescue — Assumptions & (2)'!C5,0)*'NeatRescue — Assumptions & (2)'!E5 -> 69.281821
A25: Team | B25: ='NeatRescue — Revenue & costs ·'!B16*MAX('NeatRescue — Assumptions & (2)'!D6-'NeatRescue — Assumptions & (2)'!C6,0)*'NeatRescue — Assumptions & (2)'!E6 -> 20 | C25: ='NeatRescue — Revenue & costs ·'!C16*MAX('NeatRescue — Assumptions & (2)'!D6-'NeatRescue — Assumptions & (2)'!C6,0)*'NeatRescue — Assumptions & (2)'!E6 -> 41 | D25: ='NeatRescue — Revenue & costs ·'!D16*MAX('NeatRescue — Assumptions & (2)'!D6-'NeatRescue — Assumptions & (2)'!C6,0)*'NeatRescue — Assumptions & (2)'!E6 -> 63.15 | E25: ='NeatRescue — Revenue & costs ·'!E16*MAX('NeatRescue — Assumptions & (2)'!D6-'NeatRescue — Assumptions & (2)'!C6,0)*'NeatRescue — Assumptions & (2)'!E6 -> 86.6125 | F25: ='NeatRescue — Revenue & costs ·'!F16*MAX('NeatRescue — Assumptions & (2)'!D6-'NeatRescue — Assumptions & (2)'!C6,0)*'NeatRescue — Assumptions & (2)'!E6 -> 111.56388 | G25: ='NeatRescue — Revenue & costs ·'!G16*MAX('NeatRescue — Assumptions & (2)'!D6-'NeatRescue — Assumptions & (2)'!C6,0)*'NeatRescue — Assumptions & (2)'!E6 -> 138.19588 | H25: ='NeatRescue — Revenue & costs ·'!H16*MAX('NeatRescue — Assumptions & (2)'!D6-'NeatRescue — Assumptions & (2)'!C6,0)*'NeatRescue — Assumptions & (2)'!E6 -> 166.71731 | I25: ='NeatRescue — Revenue & costs ·'!I16*MAX('NeatRescue — Assumptions & (2)'!D6-'NeatRescue — Assumptions & (2)'!C6,0)*'NeatRescue — Assumptions & (2)'!E6 -> 197.35578 | J25: ='NeatRescue — Revenue & costs ·'!J16*MAX('NeatRescue — Assumptions & (2)'!D6-'NeatRescue — Assumptions & (2)'!C6,0)*'NeatRescue — Assumptions & (2)'!E6 -> 230.35977 | K25: ='NeatRescue — Revenue & costs ·'!K16*MAX('NeatRescue — Assumptions & (2)'!D6-'NeatRescue — Assumptions & (2)'!C6,0)*'NeatRescue — Assumptions & (2)'!E6 -> 266.00074 | L25: ='NeatRescue — Revenue & costs ·'!L16*MAX('NeatRescue — Assumptions & (2)'!D6-'NeatRescue — Assumptions & (2)'!C6,0)*'NeatRescue — Assumptions & (2)'!E6 -> 304.57555 | M25: ='NeatRescue — Revenue & costs ·'!M16*MAX('NeatRescue — Assumptions & (2)'!D6-'NeatRescue — Assumptions & (2)'!C6,0)*'NeatRescue — Assumptions & (2)'!E6 -> 346.40911
A26: Revenue | B26: =SUM('NeatRescue — Revenue & costs ·'!B27,'NeatRescue — Revenue & costs ·'!B28) -> 321 | C26: =SUM('NeatRescue — Revenue & costs ·'!C27,'NeatRescue — Revenue & costs ·'!C28) -> 658.05 | D26: =SUM('NeatRescue — Revenue & costs ·'!D27,'NeatRescue — Revenue & costs ·'!D28) -> 1013.5575 | E26: =SUM('NeatRescue — Revenue & costs ·'!E27,'NeatRescue — Revenue & costs ·'!E28) -> 1390.1306 | F26: =SUM('NeatRescue — Revenue & costs ·'!F27,'NeatRescue — Revenue & costs ·'!F28) -> 1790.6002 | G26: =SUM('NeatRescue — Revenue & costs ·'!G27,'NeatRescue — Revenue & costs ·'!G28) -> 2218.0439 | H26: =SUM('NeatRescue — Revenue & costs ·'!H27,'NeatRescue — Revenue & costs ·'!H28) -> 2675.8128 | I26: =SUM('NeatRescue — Revenue & costs ·'!I27,'NeatRescue — Revenue & costs ·'!I28) -> 3167.5603 | ... M26: =SUM('NeatRescue — Revenue & costs ·'!M27,'NeatRescue — Revenue & costs ·'!M28) -> 5559.8661
A27: Starter | B27: ='NeatRescue — Revenue & costs ·'!B21+'NeatRescue — Revenue & costs ·'!B24 -> 102 | C27: ='NeatRescue — Revenue & costs ·'!C21+'NeatRescue — Revenue & costs ·'!C24 -> 209.1 | D27: ='NeatRescue — Revenue & costs ·'!D21+'NeatRescue — Revenue & costs ·'!D24 -> 322.065 | E27: ='NeatRescue — Revenue & costs ·'!E21+'NeatRescue — Revenue & costs ·'!E24 -> 441.72375 | F27: ='NeatRescue — Revenue & costs ·'!F21+'NeatRescue — Revenue & costs ·'!F24 -> 568.97576 | G27: ='NeatRescue — Revenue & costs ·'!G21+'NeatRescue — Revenue & costs ·'!G24 -> 704.79899 | H27: ='NeatRescue — Revenue & costs ·'!H21+'NeatRescue — Revenue & costs ·'!H24 -> 850.25827 | I27: ='NeatRescue — Revenue & costs ·'!I21+'NeatRescue — Revenue & costs ·'!I24 -> 1006.5145 | ... M27: ='NeatRescue — Revenue & costs ·'!M21+'NeatRescue — Revenue & costs ·'!M24 -> 1766.6864
A28: Team | B28: ='NeatRescue — Revenue & costs ·'!B22+'NeatRescue — Revenue & costs ·'!B25 -> 219 | C28: ='NeatRescue — Revenue & costs ·'!C22+'NeatRescue — Revenue & costs ·'!C25 -> 448.95 | D28: ='NeatRescue — Revenue & costs ·'!D22+'NeatRescue — Revenue & costs ·'!D25 -> 691.4925 | E28: ='NeatRescue — Revenue & costs ·'!E22+'NeatRescue — Revenue & costs ·'!E25 -> 948.40688 | F28: ='NeatRescue — Revenue & costs ·'!F22+'NeatRescue — Revenue & costs ·'!F25 -> 1221.6244 | G28: ='NeatRescue — Revenue & costs ·'!G22+'NeatRescue — Revenue & costs ·'!G25 -> 1513.2449 | H28: ='NeatRescue — Revenue & costs ·'!H22+'NeatRescue — Revenue & costs ·'!H25 -> 1825.5545 | I28: ='NeatRescue — Revenue & costs ·'!I22+'NeatRescue — Revenue & costs ·'!I25 -> 2161.0458 | ... M28: ='NeatRescue — Revenue & costs ·'!M22+'NeatRescue — Revenue & costs ·'!M25 -> 3793.1797
A29: Inference expense | B29: =SUM('NeatRescue — Revenue & costs ·'!B30,'NeatRescue — Revenue & costs ·'!B31) -> 52 | C29: =SUM('NeatRescue — Revenue & costs ·'!C30,'NeatRescue — Revenue & costs ·'!C31) -> 106.6 | D29: =SUM('NeatRescue — Revenue & costs ·'!D30,'NeatRescue — Revenue & costs ·'!D31) -> 164.19 | E29: =SUM('NeatRescue — Revenue & costs ·'!E30,'NeatRescue — Revenue & costs ·'!E31) -> 225.1925 | F29: =SUM('NeatRescue — Revenue & costs ·'!F30,'NeatRescue — Revenue & costs ·'!F31) -> 290.06608 | G29: =SUM('NeatRescue — Revenue & costs ·'!G30,'NeatRescue — Revenue & costs ·'!G31) -> 359.30929 | H29: =SUM('NeatRescue — Revenue & costs ·'!H30,'NeatRescue — Revenue & costs ·'!H31) -> 433.465 | I29: =SUM('NeatRescue — Revenue & costs ·'!I30,'NeatRescue — Revenue & costs ·'!I31) -> 513.12504 | ... M29: =SUM('NeatRescue — Revenue & costs ·'!M30,'NeatRescue — Revenue & costs ·'!M31) -> 900.66367
A30: Starter | B30: ='NeatRescue — Revenue & costs ·'!B18*'NeatRescue — Assumptions & simu'!B7 -> 12 | C30: ='NeatRescue — Revenue & costs ·'!C18*'NeatRescue — Assumptions & simu'!B7 -> 24.6 | D30: ='NeatRescue — Revenue & costs ·'!D18*'NeatRescue — Assumptions & simu'!B7 -> 37.89 | E30: ='NeatRescue — Revenue & costs ·'!E18*'NeatRescue — Assumptions & simu'!B7 -> 51.9675 | F30: ='NeatRescue — Revenue & costs ·'!F18*'NeatRescue — Assumptions & simu'!B7 -> 66.938325 | G30: ='NeatRescue — Revenue & costs ·'!G18*'NeatRescue — Assumptions & simu'!B7 -> 82.917529 | H30: ='NeatRescue — Revenue & costs ·'!H18*'NeatRescue — Assumptions & simu'!B7 -> 100.03038 | I30: ='NeatRescue — Revenue & costs ·'!I18*'NeatRescue — Assumptions & simu'!B7 -> 118.41347 | J30: ='NeatRescue — Revenue & costs ·'!J18*'NeatRescue — Assumptions & simu'!B7 -> 138.21586 | K30: ='NeatRescue — Revenue & costs ·'!K18*'NeatRescue — Assumptions & simu'!B7 -> 159.60044 | L30: ='NeatRescue — Revenue & costs ·'!L18*'NeatRescue — Assumptions & simu'!B7 -> 182.74533 | M30: ='NeatRescue — Revenue & costs ·'!M18*'NeatRescue — Assumptions & simu'!B7 -> 207.84546
A31: Team | B31: ='NeatRescue — Revenue & costs ·'!B19*'NeatRescue — Assumptions & simu'!B7 -> 40 | C31: ='NeatRescue — Revenue & costs ·'!C19*'NeatRescue — Assumptions & simu'!B7 -> 82 | D31: ='NeatRescue — Revenue & costs ·'!D19*'NeatRescue — Assumptions & simu'!B7 -> 126.3 | E31: ='NeatRescue — Revenue & costs ·'!E19*'NeatRescue — Assumptions & simu'!B7 -> 173.225 | F31: ='NeatRescue — Revenue & costs ·'!F19*'NeatRescue — Assumptions & simu'!B7 -> 223.12775 | G31: ='NeatRescue — Revenue & costs ·'!G19*'NeatRescue — Assumptions & simu'!B7 -> 276.39176 | H31: ='NeatRescue — Revenue & costs ·'!H19*'NeatRescue — Assumptions & simu'!B7 -> 333.43461 | I31: ='NeatRescue — Revenue & costs ·'!I19*'NeatRescue — Assumptions & simu'!B7 -> 394.71157 | J31: ='NeatRescue — Revenue & costs ·'!J19*'NeatRescue — Assumptions & simu'!B7 -> 460.71954 | K31: ='NeatRescue — Revenue & costs ·'!K19*'NeatRescue — Assumptions & simu'!B7 -> 532.00147 | L31: ='NeatRescue — Revenue & costs ·'!L19*'NeatRescue — Assumptions & simu'!B7 -> 609.1511 | M31: ='NeatRescue — Revenue & costs ·'!M19*'NeatRescue — Assumptions & simu'!B7 -> 692.81821
A32: Variable compute expense | B32: =SUM('NeatRescue — Revenue & costs ·'!B33,'NeatRescue — Revenue & costs ·'!B34) -> 15.6 | C32: =SUM('NeatRescue — Revenue & costs ·'!C33,'NeatRescue — Revenue & costs ·'!C34) -> 31.98 | D32: =SUM('NeatRescue — Revenue & costs ·'!D33,'NeatRescue — Revenue & costs ·'!D34) -> 49.257 | E32: =SUM('NeatRescue — Revenue & costs ·'!E33,'NeatRescue — Revenue & costs ·'!E34) -> 67.55775 | F32: =SUM('NeatRescue — Revenue & costs ·'!F33,'NeatRescue — Revenue & costs ·'!F34) -> 87.019823 | G32: =SUM('NeatRescue — Revenue & costs ·'!G33,'NeatRescue — Revenue & costs ·'!G34) -> 107.79279 | H32: =SUM('NeatRescue — Revenue & costs ·'!H33,'NeatRescue — Revenue & costs ·'!H34) -> 130.0395 | I32: =SUM('NeatRescue — Revenue & costs ·'!I33,'NeatRescue — Revenue & costs ·'!I34) -> 153.93751 | ... M32: =SUM('NeatRescue — Revenue & costs ·'!M33,'NeatRescue — Revenue & costs ·'!M34) -> 270.1991
A33: Starter | B33: ='NeatRescue — Revenue & costs ·'!B18*'NeatRescue — Assumptions & simu'!B8 -> 3.6 | C33: ='NeatRescue — Revenue & costs ·'!C18*'NeatRescue — Assumptions & simu'!B8 -> 7.38 | D33: ='NeatRescue — Revenue & costs ·'!D18*'NeatRescue — Assumptions & simu'!B8 -> 11.367 | E33: ='NeatRescue — Revenue & costs ·'!E18*'NeatRescue — Assumptions & simu'!B8 -> 15.59025 | F33: ='NeatRescue — Revenue & costs ·'!F18*'NeatRescue — Assumptions & simu'!B8 -> 20.081498 | G33: ='NeatRescue — Revenue & costs ·'!G18*'NeatRescue — Assumptions & simu'!B8 -> 24.875259 | H33: ='NeatRescue — Revenue & costs ·'!H18*'NeatRescue — Assumptions & simu'!B8 -> 30.009115 | I33: ='NeatRescue — Revenue & costs ·'!I18*'NeatRescue — Assumptions & simu'!B8 -> 35.524041 | J33: ='NeatRescue — Revenue & costs ·'!J18*'NeatRescue — Assumptions & simu'!B8 -> 41.464759 | K33: ='NeatRescue — Revenue & costs ·'!K18*'NeatRescue — Assumptions & simu'!B8 -> 47.880133 | L33: ='NeatRescue — Revenue & costs ·'!L18*'NeatRescue — Assumptions & simu'!B8 -> 54.823599 | M33: ='NeatRescue — Revenue & costs ·'!M18*'NeatRescue — Assumptions & simu'!B8 -> 62.353639
A34: Team | B34: ='NeatRescue — Revenue & costs ·'!B19*'NeatRescue — Assumptions & simu'!B8 -> 12 | C34: ='NeatRescue — Revenue & costs ·'!C19*'NeatRescue — Assumptions & simu'!B8 -> 24.6 | D34: ='NeatRescue — Revenue & costs ·'!D19*'NeatRescue — Assumptions & simu'!B8 -> 37.89 | E34: ='NeatRescue — Revenue & costs ·'!E19*'NeatRescue — Assumptions & simu'!B8 -> 51.9675 | F34: ='NeatRescue — Revenue & costs ·'!F19*'NeatRescue — Assumptions & simu'!B8 -> 66.938325 | G34: ='NeatRescue — Revenue & costs ·'!G19*'NeatRescue — Assumptions & simu'!B8 -> 82.917529 | H34: ='NeatRescue — Revenue & costs ·'!H19*'NeatRescue — Assumptions & simu'!B8 -> 100.03038 | I34: ='NeatRescue — Revenue & costs ·'!I19*'NeatRescue — Assumptions & simu'!B8 -> 118.41347 | J34: ='NeatRescue — Revenue & costs ·'!J19*'NeatRescue — Assumptions & simu'!B8 -> 138.21586 | K34: ='NeatRescue — Revenue & costs ·'!K19*'NeatRescue — Assumptions & simu'!B8 -> 159.60044 | L34: ='NeatRescue — Revenue & costs ·'!L19*'NeatRescue — Assumptions & simu'!B8 -> 182.74533 | M34: ='NeatRescue — Revenue & costs ·'!M19*'NeatRescue — Assumptions & simu'!B8 -> 207.84546
A35: Variable logging expense | B35: =SUM('NeatRescue — Revenue & costs ·'!B36,'NeatRescue — Revenue & costs ·'!B37) -> 5.2 | C35: =SUM('NeatRescue — Revenue & costs ·'!C36,'NeatRescue — Revenue & costs ·'!C37) -> 10.66 | D35: =SUM('NeatRescue — Revenue & costs ·'!D36,'NeatRescue — Revenue & costs ·'!D37) -> 16.419 | E35: =SUM('NeatRescue — Revenue & costs ·'!E36,'NeatRescue — Revenue & costs ·'!E37) -> 22.51925 | F35: =SUM('NeatRescue — Revenue & costs ·'!F36,'NeatRescue — Revenue & costs ·'!F37) -> 29.006608 | G35: =SUM('NeatRescue — Revenue & costs ·'!G36,'NeatRescue — Revenue & costs ·'!G37) -> 35.930929 | H35: =SUM('NeatRescue — Revenue & costs ·'!H36,'NeatRescue — Revenue & costs ·'!H37) -> 43.3465 | I35: =SUM('NeatRescue — Revenue & costs ·'!I36,'NeatRescue — Revenue & costs ·'!I37) -> 51.312504 | ... M35: =SUM('NeatRescue — Revenue & costs ·'!M36,'NeatRescue — Revenue & costs ·'!M37) -> 90.066367
A36: Starter | B36: ='NeatRescue — Revenue & costs ·'!B18*'NeatRescue — Assumptions & simu'!B9 -> 1.2 | C36: ='NeatRescue — Revenue & costs ·'!C18*'NeatRescue — Assumptions & simu'!B9 -> 2.46 | D36: ='NeatRescue — Revenue & costs ·'!D18*'NeatRescue — Assumptions & simu'!B9 -> 3.789 | E36: ='NeatRescue — Revenue & costs ·'!E18*'NeatRescue — Assumptions & simu'!B9 -> 5.19675 | F36: ='NeatRescue — Revenue & costs ·'!F18*'NeatRescue — Assumptions & simu'!B9 -> 6.6938325 | G36: ='NeatRescue — Revenue & costs ·'!G18*'NeatRescue — Assumptions & simu'!B9 -> 8.2917529 | H36: ='NeatRescue — Revenue & costs ·'!H18*'NeatRescue — Assumptions & simu'!B9 -> 10.003038 | I36: ='NeatRescue — Revenue & costs ·'!I18*'NeatRescue — Assumptions & simu'!B9 -> 11.841347 | J36: ='NeatRescue — Revenue & costs ·'!J18*'NeatRescue — Assumptions & simu'!B9 -> 13.821586 | K36: ='NeatRescue — Revenue & costs ·'!K18*'NeatRescue — Assumptions & simu'!B9 -> 15.960044 | L36: ='NeatRescue — Revenue & costs ·'!L18*'NeatRescue — Assumptions & simu'!B9 -> 18.274533 | M36: ='NeatRescue — Revenue & costs ·'!M18*'NeatRescue — Assumptions & simu'!B9 -> 20.784546
A37: Team | B37: ='NeatRescue — Revenue & costs ·'!B19*'NeatRescue — Assumptions & simu'!B9 -> 4 | C37: ='NeatRescue — Revenue & costs ·'!C19*'NeatRescue — Assumptions & simu'!B9 -> 8.2 | D37: ='NeatRescue — Revenue & costs ·'!D19*'NeatRescue — Assumptions & simu'!B9 -> 12.63 | E37: ='NeatRescue — Revenue & costs ·'!E19*'NeatRescue — Assumptions & simu'!B9 -> 17.3225 | F37: ='NeatRescue — Revenue & costs ·'!F19*'NeatRescue — Assumptions & simu'!B9 -> 22.312775 | G37: ='NeatRescue — Revenue & costs ·'!G19*'NeatRescue — Assumptions & simu'!B9 -> 27.639176 | H37: ='NeatRescue — Revenue & costs ·'!H19*'NeatRescue — Assumptions & simu'!B9 -> 33.343461 | I37: ='NeatRescue — Revenue & costs ·'!I19*'NeatRescue — Assumptions & simu'!B9 -> 39.471157 | J37: ='NeatRescue — Revenue & costs ·'!J19*'NeatRescue — Assumptions & simu'!B9 -> 46.071954 | K37: ='NeatRescue — Revenue & costs ·'!K19*'NeatRescue — Assumptions & simu'!B9 -> 53.200147 | L37: ='NeatRescue — Revenue & costs ·'!L19*'NeatRescue — Assumptions & simu'!B9 -> 60.91511 | M37: ='NeatRescue — Revenue & costs ·'!M19*'NeatRescue — Assumptions & simu'!B9 -> 69.281821
A38: Variable support expense | B38: =SUM('NeatRescue — Revenue & costs ·'!B39,'NeatRescue — Revenue & costs ·'!B40) -> 16 | C38: =SUM('NeatRescue — Revenue & costs ·'!C39,'NeatRescue — Revenue & costs ·'!C40) -> 32.8 | D38: =SUM('NeatRescue — Revenue & costs ·'!D39,'NeatRescue — Revenue & costs ·'!D40) -> 50.52 | E38: =SUM('NeatRescue — Revenue & costs ·'!E39,'NeatRescue — Revenue & costs ·'!E40) -> 69.29 | F38: =SUM('NeatRescue — Revenue & costs ·'!F39,'NeatRescue — Revenue & costs ·'!F40) -> 89.2511 | G38: =SUM('NeatRescue — Revenue & costs ·'!G39,'NeatRescue — Revenue & costs ·'!G40) -> 110.55671 | H38: =SUM('NeatRescue — Revenue & costs ·'!H39,'NeatRescue — Revenue & costs ·'!H40) -> 133.37385 | I38: =SUM('NeatRescue — Revenue & costs ·'!I39,'NeatRescue — Revenue & costs ·'!I40) -> 157.88463 | ... M38: =SUM('NeatRescue — Revenue & costs ·'!M39,'NeatRescue — Revenue & costs ·'!M40) -> 277.12728
A39: Starter | B39: ='NeatRescue — Revenue & costs ·'!B15*'NeatRescue — Assumptions & (2)'!F5 -> 4 | C39: ='NeatRescue — Revenue & costs ·'!C15*'NeatRescue — Assumptions & (2)'!F5 -> 8.2 | D39: ='NeatRescue — Revenue & costs ·'!D15*'NeatRescue — Assumptions & (2)'!F5 -> 12.63 | E39: ='NeatRescue — Revenue & costs ·'!E15*'NeatRescue — Assumptions & (2)'!F5 -> 17.3225 | F39: ='NeatRescue — Revenue & costs ·'!F15*'NeatRescue — Assumptions & (2)'!F5 -> 22.312775 | G39: ='NeatRescue — Revenue & costs ·'!G15*'NeatRescue — Assumptions & (2)'!F5 -> 27.639176 | H39: ='NeatRescue — Revenue & costs ·'!H15*'NeatRescue — Assumptions & (2)'!F5 -> 33.343461 | I39: ='NeatRescue — Revenue & costs ·'!I15*'NeatRescue — Assumptions & (2)'!F5 -> 39.471157 | J39: ='NeatRescue — Revenue & costs ·'!J15*'NeatRescue — Assumptions & (2)'!F5 -> 46.071954 | K39: ='NeatRescue — Revenue & costs ·'!K15*'NeatRescue — Assumptions & (2)'!F5 -> 53.200147 | L39: ='NeatRescue — Revenue & costs ·'!L15*'NeatRescue — Assumptions & (2)'!F5 -> 60.91511 | M39: ='NeatRescue — Revenue & costs ·'!M15*'NeatRescue — Assumptions & (2)'!F5 -> 69.281821
A40: Team | B40: ='NeatRescue — Revenue & costs ·'!B16*'NeatRescue — Assumptions & (2)'!F6 -> 12 | C40: ='NeatRescue — Revenue & costs ·'!C16*'NeatRescue — Assumptions & (2)'!F6 -> 24.6 | D40: ='NeatRescue — Revenue & costs ·'!D16*'NeatRescue — Assumptions & (2)'!F6 -> 37.89 | E40: ='NeatRescue — Revenue & costs ·'!E16*'NeatRescue — Assumptions & (2)'!F6 -> 51.9675 | F40: ='NeatRescue — Revenue & costs ·'!F16*'NeatRescue — Assumptions & (2)'!F6 -> 66.938325 | G40: ='NeatRescue — Revenue & costs ·'!G16*'NeatRescue — Assumptions & (2)'!F6 -> 82.917529 | H40: ='NeatRescue — Revenue & costs ·'!H16*'NeatRescue — Assumptions & (2)'!F6 -> 100.03038 | I40: ='NeatRescue — Revenue & costs ·'!I16*'NeatRescue — Assumptions & (2)'!F6 -> 118.41347 | J40: ='NeatRescue — Revenue & costs ·'!J16*'NeatRescue — Assumptions & (2)'!F6 -> 138.21586 | K40: ='NeatRescue — Revenue & costs ·'!K16*'NeatRescue — Assumptions & (2)'!F6 -> 159.60044 | L40: ='NeatRescue — Revenue & costs ·'!L16*'NeatRescue — Assumptions & (2)'!F6 -> 182.74533 | M40: ='NeatRescue — Revenue & costs ·'!M16*'NeatRescue — Assumptions & (2)'!F6 -> 207.84546
A41: Payment processing expense | B41: =SUM('NeatRescue — Revenue & costs ·'!B42,'NeatRescue — Revenue & costs ·'!B43) -> 9.63 | C41: =SUM('NeatRescue — Revenue & costs ·'!C42,'NeatRescue — Revenue & costs ·'!C43) -> 19.7415 | D41: =SUM('NeatRescue — Revenue & costs ·'!D42,'NeatRescue — Revenue & costs ·'!D43) -> 30.406725 | E41: =SUM('NeatRescue — Revenue & costs ·'!E42,'NeatRescue — Revenue & costs ·'!E43) -> 41.703919 | F41: =SUM('NeatRescue — Revenue & costs ·'!F42,'NeatRescue — Revenue & costs ·'!F43) -> 53.718006 | G41: =SUM('NeatRescue — Revenue & costs ·'!G42,'NeatRescue — Revenue & costs ·'!G43) -> 66.541317 | H41: =SUM('NeatRescue — Revenue & costs ·'!H42,'NeatRescue — Revenue & costs ·'!H43) -> 80.274383 | I41: =SUM('NeatRescue — Revenue & costs ·'!I42,'NeatRescue — Revenue & costs ·'!I43) -> 95.02681 | ... M41: =SUM('NeatRescue — Revenue & costs ·'!M42,'NeatRescue — Revenue & costs ·'!M43) -> 166.79598
A42: Starter | B42: ='NeatRescue — Revenue & costs ·'!B27*'NeatRescue — Assumptions & simu'!B18 -> 3.06 | C42: ='NeatRescue — Revenue & costs ·'!C27*'NeatRescue — Assumptions & simu'!B18 -> 6.273 | D42: ='NeatRescue — Revenue & costs ·'!D27*'NeatRescue — Assumptions & simu'!B18 -> 9.66195 | E42: ='NeatRescue — Revenue & costs ·'!E27*'NeatRescue — Assumptions & simu'!B18 -> 13.251713 | F42: ='NeatRescue — Revenue & costs ·'!F27*'NeatRescue — Assumptions & simu'!B18 -> 17.069273 | G42: ='NeatRescue — Revenue & costs ·'!G27*'NeatRescue — Assumptions & simu'!B18 -> 21.14397 | H42: ='NeatRescue — Revenue & costs ·'!H27*'NeatRescue — Assumptions & simu'!B18 -> 25.507748 | I42: ='NeatRescue — Revenue & costs ·'!I27*'NeatRescue — Assumptions & simu'!B18 -> 30.195435 | J42: ='NeatRescue — Revenue & costs ·'!J27*'NeatRescue — Assumptions & simu'!B18 -> 35.245045 | K42: ='NeatRescue — Revenue & costs ·'!K27*'NeatRescue — Assumptions & simu'!B18 -> 40.698113 | L42: ='NeatRescue — Revenue & costs ·'!L27*'NeatRescue — Assumptions & simu'!B18 -> 46.600059 | M42: ='NeatRescue — Revenue & costs ·'!M27*'NeatRescue — Assumptions & simu'!B18 -> 53.000593
A43: Team | B43: ='NeatRescue — Revenue & costs ·'!B28*'NeatRescue — Assumptions & simu'!B18 -> 6.57 | C43: ='NeatRescue — Revenue & costs ·'!C28*'NeatRescue — Assumptions & simu'!B18 -> 13.4685 | D43: ='NeatRescue — Revenue & costs ·'!D28*'NeatRescue — Assumptions & simu'!B18 -> 20.744775 | E43: ='NeatRescue — Revenue & costs ·'!E28*'NeatRescue — Assumptions & simu'!B18 -> 28.452206 | F43: ='NeatRescue — Revenue & costs ·'!F28*'NeatRescue — Assumptions & simu'!B18 -> 36.648733 | G43: ='NeatRescue — Revenue & costs ·'!G28*'NeatRescue — Assumptions & simu'!B18 -> 45.397347 | H43: ='NeatRescue — Revenue & costs ·'!H28*'NeatRescue — Assumptions & simu'!B18 -> 54.766635 | I43: ='NeatRescue — Revenue & costs ·'!I28*'NeatRescue — Assumptions & simu'!B18 -> 64.831375 | J43: ='NeatRescue — Revenue & costs ·'!J28*'NeatRescue — Assumptions & simu'!B18 -> 75.673185 | K43: ='NeatRescue — Revenue & costs ·'!K28*'NeatRescue — Assumptions & simu'!B18 -> 87.381242 | L43: ='NeatRescue — Revenue & costs ·'!L28*'NeatRescue — Assumptions & simu'!B18 -> 100.05307 | M43: ='NeatRescue — Revenue & costs ·'!M28*'NeatRescue — Assumptions & simu'!B18 -> 113.79539
A44: Variable cost of revenue | B44: =SUM('NeatRescue — Revenue & costs ·'!B45,'NeatRescue — Revenue & costs ·'!B46) -> 98.43 | C44: =SUM('NeatRescue — Revenue & costs ·'!C45,'NeatRescue — Revenue & costs ·'!C46) -> 201.7815 | D44: =SUM('NeatRescue — Revenue & costs ·'!D45,'NeatRescue — Revenue & costs ·'!D46) -> 310.79273 | E44: =SUM('NeatRescue — Revenue & costs ·'!E45,'NeatRescue — Revenue & costs ·'!E46) -> 426.26342 | F44: =SUM('NeatRescue — Revenue & costs ·'!F45,'NeatRescue — Revenue & costs ·'!F46) -> 549.06161 | G44: =SUM('NeatRescue — Revenue & costs ·'!G45,'NeatRescue — Revenue & costs ·'!G46) -> 680.13103 | H44: =SUM('NeatRescue — Revenue & costs ·'!H45,'NeatRescue — Revenue & costs ·'!H46) -> 820.49923 | I44: =SUM('NeatRescue — Revenue & costs ·'!I45,'NeatRescue — Revenue & costs ·'!I46) -> 971.28649 | ... M44: =SUM('NeatRescue — Revenue & costs ·'!M45,'NeatRescue — Revenue & costs ·'!M46) -> 1704.8524
A45: Starter | B45: ='NeatRescue — Revenue & costs ·'!B30+'NeatRescue — Revenue & costs ·'!B33+'NeatRescue — Revenue & costs ·'!B36+'NeatRescue — Revenue & costs ·'!B39+'NeatRescue — Revenue & costs ·'!B42 -> 23.86 | C45: ='NeatRescue — Revenue & costs ·'!C30+'NeatRescue — Revenue & costs ·'!C33+'NeatRescue — Revenue & costs ·'!C36+'NeatRescue — Revenue & costs ·'!C39+'NeatRescue — Revenue & costs ·'!C42 -> 48.913 | D45: ='NeatRescue — Revenue & costs ·'!D30+'NeatRescue — Revenue & costs ·'!D33+'NeatRescue — Revenue & costs ·'!D36+'NeatRescue — Revenue & costs ·'!D39+'NeatRescue — Revenue & costs ·'!D42 -> 75.33795 | E45: ='NeatRescue — Revenue & costs ·'!E30+'NeatRescue — Revenue & costs ·'!E33+'NeatRescue — Revenue & costs ·'!E36+'NeatRescue — Revenue & costs ·'!E39+'NeatRescue — Revenue & costs ·'!E42 -> 103.32871 | F45: ='NeatRescue — Revenue & costs ·'!F30+'NeatRescue — Revenue & costs ·'!F33+'NeatRescue — Revenue & costs ·'!F36+'NeatRescue — Revenue & costs ·'!F39+'NeatRescue — Revenue & costs ·'!F42 -> 133.0957 | G45: ='NeatRescue — Revenue & costs ·'!G30+'NeatRescue — Revenue & costs ·'!G33+'NeatRescue — Revenue & costs ·'!G36+'NeatRescue — Revenue & costs ·'!G39+'NeatRescue — Revenue & costs ·'!G42 -> 164.86769 | H45: ='NeatRescue — Revenue & costs ·'!H30+'NeatRescue — Revenue & costs ·'!H33+'NeatRescue — Revenue & costs ·'!H36+'NeatRescue — Revenue & costs ·'!H39+'NeatRescue — Revenue & costs ·'!H42 -> 198.89375 | I45: ='NeatRescue — Revenue & costs ·'!I30+'NeatRescue — Revenue & costs ·'!I33+'NeatRescue — Revenue & costs ·'!I36+'NeatRescue — Revenue & costs ·'!I39+'NeatRescue — Revenue & costs ·'!I42 -> 235.44545 | ... M45: ='NeatRescue — Revenue & costs ·'!M30+'NeatRescue — Revenue & costs ·'!M33+'NeatRescue — Revenue & costs ·'!M36+'NeatRescue — Revenue & costs ·'!M39+'NeatRescue — Revenue & costs ·'!M42 -> 413.26606
A46: Team | B46: ='NeatRescue — Revenue & costs ·'!B31+'NeatRescue — Revenue & costs ·'!B34+'NeatRescue — Revenue & costs ·'!B37+'NeatRescue — Revenue & costs ·'!B40+'NeatRescue — Revenue & costs ·'!B43 -> 74.57 | C46: ='NeatRescue — Revenue & costs ·'!C31+'NeatRescue — Revenue & costs ·'!C34+'NeatRescue — Revenue & costs ·'!C37+'NeatRescue — Revenue & costs ·'!C40+'NeatRescue — Revenue & costs ·'!C43 -> 152.8685 | D46: ='NeatRescue — Revenue & costs ·'!D31+'NeatRescue — Revenue & costs ·'!D34+'NeatRescue — Revenue & costs ·'!D37+'NeatRescue — Revenue & costs ·'!D40+'NeatRescue — Revenue & costs ·'!D43 -> 235.45478 | E46: ='NeatRescue — Revenue & costs ·'!E31+'NeatRescue — Revenue & costs ·'!E34+'NeatRescue — Revenue & costs ·'!E37+'NeatRescue — Revenue & costs ·'!E40+'NeatRescue — Revenue & costs ·'!E43 -> 322.93471 | F46: ='NeatRescue — Revenue & costs ·'!F31+'NeatRescue — Revenue & costs ·'!F34+'NeatRescue — Revenue & costs ·'!F37+'NeatRescue — Revenue & costs ·'!F40+'NeatRescue — Revenue & costs ·'!F43 -> 415.96591 | G46: ='NeatRescue — Revenue & costs ·'!G31+'NeatRescue — Revenue & costs ·'!G34+'NeatRescue — Revenue & costs ·'!G37+'NeatRescue — Revenue & costs ·'!G40+'NeatRescue — Revenue & costs ·'!G43 -> 515.26334 | H46: ='NeatRescue — Revenue & costs ·'!H31+'NeatRescue — Revenue & costs ·'!H34+'NeatRescue — Revenue & costs ·'!H37+'NeatRescue — Revenue & costs ·'!H40+'NeatRescue — Revenue & costs ·'!H43 -> 621.60548 | I46: ='NeatRescue — Revenue & costs ·'!I31+'NeatRescue — Revenue & costs ·'!I34+'NeatRescue — Revenue & costs ·'!I37+'NeatRescue — Revenue & costs ·'!I40+'NeatRescue — Revenue & costs ·'!I43 -> 735.84104 | ... M46: ='NeatRescue — Revenue & costs ·'!M31+'NeatRescue — Revenue & costs ·'!M34+'NeatRescue — Revenue & costs ·'!M37+'NeatRescue — Revenue & costs ·'!M40+'NeatRescue — Revenue & costs ·'!M43 -> 1291.5863
A47: Contribution margin | B47: ='NeatRescue — Revenue & costs ·'!B26-'NeatRescue — Revenue & costs ·'!B44 -> 222.57 | C47: ='NeatRescue — Revenue & costs ·'!C26-'NeatRescue — Revenue & costs ·'!C44 -> 456.2685 | D47: ='NeatRescue — Revenue & costs ·'!D26-'NeatRescue — Revenue & costs ·'!D44 -> 702.76478 | E47: ='NeatRescue — Revenue & costs ·'!E26-'NeatRescue — Revenue & costs ·'!E44 -> 963.86721 | F47: ='NeatRescue — Revenue & costs ·'!F26-'NeatRescue — Revenue & costs ·'!F44 -> 1241.5386 | G47: ='NeatRescue — Revenue & costs ·'!G26-'NeatRescue — Revenue & costs ·'!G44 -> 1537.9129 | H47: ='NeatRescue — Revenue & costs ·'!H26-'NeatRescue — Revenue & costs ·'!H44 -> 1855.3136 | I47: ='NeatRescue — Revenue & costs ·'!I26-'NeatRescue — Revenue & costs ·'!I44 -> 2196.2738 | ... M47: ='NeatRescue — Revenue & costs ·'!M26-'NeatRescue — Revenue & costs ·'!M44 -> 3855.0137
A48: Starter | B48: ='NeatRescue — Revenue & costs ·'!B27-'NeatRescue — Revenue & costs ·'!B45 -> 78.14 | C48: ='NeatRescue — Revenue & costs ·'!C27-'NeatRescue — Revenue & costs ·'!C45 -> 160.187 | D48: ='NeatRescue — Revenue & costs ·'!D27-'NeatRescue — Revenue & costs ·'!D45 -> 246.72705 | E48: ='NeatRescue — Revenue & costs ·'!E27-'NeatRescue — Revenue & costs ·'!E45 -> 338.39504 | F48: ='NeatRescue — Revenue & costs ·'!F27-'NeatRescue — Revenue & costs ·'!F45 -> 435.88006 | G48: ='NeatRescue — Revenue & costs ·'!G27-'NeatRescue — Revenue & costs ·'!G45 -> 539.93131 | H48: ='NeatRescue — Revenue & costs ·'!H27-'NeatRescue — Revenue & costs ·'!H45 -> 651.36452 | I48: ='NeatRescue — Revenue & costs ·'!I27-'NeatRescue — Revenue & costs ·'!I45 -> 771.06905 | ... M48: ='NeatRescue — Revenue & costs ·'!M27-'NeatRescue — Revenue & costs ·'!M45 -> 1353.4204
A49: Team | B49: ='NeatRescue — Revenue & costs ·'!B28-'NeatRescue — Revenue & costs ·'!B46 -> 144.43 | C49: ='NeatRescue — Revenue & costs ·'!C28-'NeatRescue — Revenue & costs ·'!C46 -> 296.0815 | D49: ='NeatRescue — Revenue & costs ·'!D28-'NeatRescue — Revenue & costs ·'!D46 -> 456.03773 | E49: ='NeatRescue — Revenue & costs ·'!E28-'NeatRescue — Revenue & costs ·'!E46 -> 625.47217 | F49: ='NeatRescue — Revenue & costs ·'!F28-'NeatRescue — Revenue & costs ·'!F46 -> 805.65852 | G49: ='NeatRescue — Revenue & costs ·'!G28-'NeatRescue — Revenue & costs ·'!G46 -> 997.98156 | H49: ='NeatRescue — Revenue & costs ·'!H28-'NeatRescue — Revenue & costs ·'!H46 -> 1203.949 | I49: ='NeatRescue — Revenue & costs ·'!I28-'NeatRescue — Revenue & costs ·'!I46 -> 1425.2048 | ... M49: ='NeatRescue — Revenue & costs ·'!M28-'NeatRescue — Revenue & costs ·'!M46 -> 2501.5934
A50: Contribution margin percentage | B50: =IFERROR('NeatRescue — Revenue & costs ·'!B47/'NeatRescue — Revenue & costs ·'!B26,"") -> 0.69336449 | C50: =IFERROR('NeatRescue — Revenue & costs ·'!C47/'NeatRescue — Revenue & costs ·'!C26,"") -> 0.69336449 | D50: =IFERROR('NeatRescue — Revenue & costs ·'!D47/'NeatRescue — Revenue & costs ·'!D26,"") -> 0.69336449 | E50: =IFERROR('NeatRescue — Revenue & costs ·'!E47/'NeatRescue — Revenue & costs ·'!E26,"") -> 0.69336449 | F50: =IFERROR('NeatRescue — Revenue & costs ·'!F47/'NeatRescue — Revenue & costs ·'!F26,"") -> 0.69336449 | G50: =IFERROR('NeatRescue — Revenue & costs ·'!G47/'NeatRescue — Revenue & costs ·'!G26,"") -> 0.69336449 | H50: =IFERROR('NeatRescue — Revenue & costs ·'!H47/'NeatRescue — Revenue & costs ·'!H26,"") -> 0.69336449 | I50: =IFERROR('NeatRescue — Revenue & costs ·'!I47/'NeatRescue — Revenue & costs ·'!I26,"") -> 0.69336449 | ... M50: =IFERROR('NeatRescue — Revenue & costs ·'!M47/'NeatRescue — Revenue & costs ·'!M26,"") -> 0.69336449
A51: Starter | B51: =IFERROR('NeatRescue — Revenue & costs ·'!B48/'NeatRescue — Revenue & costs ·'!B27,"") -> 0.76607843 | C51: =IFERROR('NeatRescue — Revenue & costs ·'!C48/'NeatRescue — Revenue & costs ·'!C27,"") -> 0.76607843 | D51: =IFERROR('NeatRescue — Revenue & costs ·'!D48/'NeatRescue — Revenue & costs ·'!D27,"") -> 0.76607843 | E51: =IFERROR('NeatRescue — Revenue & costs ·'!E48/'NeatRescue — Revenue & costs ·'!E27,"") -> 0.76607843 | F51: =IFERROR('NeatRescue — Revenue & costs ·'!F48/'NeatRescue — Revenue & costs ·'!F27,"") -> 0.76607843 | G51: =IFERROR('NeatRescue — Revenue & costs ·'!G48/'NeatRescue — Revenue & costs ·'!G27,"") -> 0.76607843 | H51: =IFERROR('NeatRescue — Revenue & costs ·'!H48/'NeatRescue — Revenue & costs ·'!H27,"") -> 0.76607843 | I51: =IFERROR('NeatRescue — Revenue & costs ·'!I48/'NeatRescue — Revenue & costs ·'!I27,"") -> 0.76607843 | ... M51: =IFERROR('NeatRescue — Revenue & costs ·'!M48/'NeatRescue — Revenue & costs ·'!M27,"") -> 0.76607843
A52: Team | B52: =IFERROR('NeatRescue — Revenue & costs ·'!B49/'NeatRescue — Revenue & costs ·'!B28,"") -> 0.65949772 | C52: =IFERROR('NeatRescue — Revenue & costs ·'!C49/'NeatRescue — Revenue & costs ·'!C28,"") -> 0.65949772 | D52: =IFERROR('NeatRescue — Revenue & costs ·'!D49/'NeatRescue — Revenue & costs ·'!D28,"") -> 0.65949772 | E52: =IFERROR('NeatRescue — Revenue & costs ·'!E49/'NeatRescue — Revenue & costs ·'!E28,"") -> 0.65949772 | F52: =IFERROR('NeatRescue — Revenue & costs ·'!F49/'NeatRescue — Revenue & costs ·'!F28,"") -> 0.65949772 | G52: =IFERROR('NeatRescue — Revenue & costs ·'!G49/'NeatRescue — Revenue & costs ·'!G28,"") -> 0.65949772 | H52: =IFERROR('NeatRescue — Revenue & costs ·'!H49/'NeatRescue — Revenue & costs ·'!H28,"") -> 0.65949772 | I52: =IFERROR('NeatRescue — Revenue & costs ·'!I49/'NeatRescue — Revenue & costs ·'!I28,"") -> 0.65949772 | ... M52: =IFERROR('NeatRescue — Revenue & costs ·'!M49/'NeatRescue — Revenue & costs ·'!M28,"") -> 0.65949772

Sheet NeatRescue — Cash & scenarios ·
A1: NeatRescue — Cash & scenarios · Profit, burn & cash runway
A2: Financial model (5 pages) · Main Scenario
A4: Variable / dimension | B4: 2026-10 | C4: 2026-11 | D4: 2026-12 | E4: 2027-01 | F4: 2027-02 | G4: 2027-03 | H4: 2027-04 | I4: 2027-05 | J4: 2027-06 | K4: 2027-07 | L4: 2027-08 | M4: 2027-09
A5: Fixed delivery costs | B5: ='NeatRescue — Assumptions & simu'!B10+'NeatRescue — Assumptions & simu'!B11+'NeatRescue — Assumptions & simu'!B12+'NeatRescue — Assumptions & simu'!B14 -> 225 | C5: ='NeatRescue — Assumptions & simu'!B10+'NeatRescue — Assumptions & simu'!B11+'NeatRescue — Assumptions & simu'!B12+'NeatRescue — Assumptions & simu'!B14 -> 225 | D5: ='NeatRescue — Assumptions & simu'!B10+'NeatRescue — Assumptions & simu'!B11+'NeatRescue — Assumptions & simu'!B12+'NeatRescue — Assumptions & simu'!B14 -> 225 | E5: ='NeatRescue — Assumptions & simu'!B10+'NeatRescue — Assumptions & simu'!B11+'NeatRescue — Assumptions & simu'!B12+'NeatRescue — Assumptions & simu'!B14 -> 225 | F5: ='NeatRescue — Assumptions & simu'!B10+'NeatRescue — Assumptions & simu'!B11+'NeatRescue — Assumptions & simu'!B12+'NeatRescue — Assumptions & simu'!B14 -> 225 | G5: ='NeatRescue — Assumptions & simu'!B10+'NeatRescue — Assumptions & simu'!B11+'NeatRescue — Assumptions & simu'!B12+'NeatRescue — Assumptions & simu'!B14 -> 225 | H5: ='NeatRescue — Assumptions & simu'!B10+'NeatRescue — Assumptions & simu'!B11+'NeatRescue — Assumptions & simu'!B12+'NeatRescue — Assumptions & simu'!B14 -> 225 | I5: ='NeatRescue — Assumptions & simu'!B10+'NeatRescue — Assumptions & simu'!B11+'NeatRescue — Assumptions & simu'!B12+'NeatRescue — Assumptions & simu'!B14 -> 225 | J5: ='NeatRescue — Assumptions & simu'!B10+'NeatRescue — Assumptions & simu'!B11+'NeatRescue — Assumptions & simu'!B12+'NeatRescue — Assumptions & simu'!B14 -> 225 | K5: ='NeatRescue — Assumptions & simu'!B10+'NeatRescue — Assumptions & simu'!B11+'NeatRescue — Assumptions & simu'!B12+'NeatRescue — Assumptions & simu'!B14 -> 225 | L5: ='NeatRescue — Assumptions & simu'!B10+'NeatRescue — Assumptions & simu'!B11+'NeatRescue — Assumptions & simu'!B12+'NeatRescue — Assumptions & simu'!B14 -> 225 | M5: ='NeatRescue — Assumptions & simu'!B10+'NeatRescue — Assumptions & simu'!B11+'NeatRescue — Assumptions & simu'!B12+'NeatRescue — Assumptions & simu'!B14 -> 225
A6: Cost of revenue | B6: ='NeatRescue — Revenue & costs ·'!B44+'NeatRescue — Cash & scenarios ·'!B5 -> 323.43 | C6: ='NeatRescue — Revenue & costs ·'!C44+'NeatRescue — Cash & scenarios ·'!C5 -> 426.7815 | D6: ='NeatRescue — Revenue & costs ·'!D44+'NeatRescue — Cash & scenarios ·'!D5 -> 535.79273 | E6: ='NeatRescue — Revenue & costs ·'!E44+'NeatRescue — Cash & scenarios ·'!E5 -> 651.26342 | F6: ='NeatRescue — Revenue & costs ·'!F44+'NeatRescue — Cash & scenarios ·'!F5 -> 774.06161 | G6: ='NeatRescue — Revenue & costs ·'!G44+'NeatRescue — Cash & scenarios ·'!G5 -> 905.13103 | H6: ='NeatRescue — Revenue & costs ·'!H44+'NeatRescue — Cash & scenarios ·'!H5 -> 1045.4992 | I6: ='NeatRescue — Revenue & costs ·'!I44+'NeatRescue — Cash & scenarios ·'!I5 -> 1196.2865 | ... M6: ='NeatRescue — Revenue & costs ·'!M44+'NeatRescue — Cash & scenarios ·'!M5 -> 1929.8524
A7: Gross profit | B7: ='NeatRescue — Hackathon subm (3)'!B5-'NeatRescue — Cash & scenarios ·'!B6 -> -2.43 | C7: ='NeatRescue — Hackathon subm (3)'!C5-'NeatRescue — Cash & scenarios ·'!C6 -> 231.2685 | D7: ='NeatRescue — Hackathon subm (3)'!D5-'NeatRescue — Cash & scenarios ·'!D6 -> 477.76478 | E7: ='NeatRescue — Hackathon subm (3)'!E5-'NeatRescue — Cash & scenarios ·'!E6 -> 738.86721 | F7: ='NeatRescue — Hackathon subm (3)'!F5-'NeatRescue — Cash & scenarios ·'!F6 -> 1016.5386 | G7: ='NeatRescue — Hackathon subm (3)'!G5-'NeatRescue — Cash & scenarios ·'!G6 -> 1312.9129 | H7: ='NeatRescue — Hackathon subm (3)'!H5-'NeatRescue — Cash & scenarios ·'!H6 -> 1630.3136 | I7: ='NeatRescue — Hackathon subm (3)'!I5-'NeatRescue — Cash & scenarios ·'!I6 -> 1971.2738 | ... M7: ='NeatRescue — Hackathon subm (3)'!M5-'NeatRescue — Cash & scenarios ·'!M6 -> 3630.0137
A8: Gross margin | B8: =IFERROR('NeatRescue — Cash & scenarios ·'!B7/'NeatRescue — Hackathon subm (3)'!B5,"") -> -0.0075700935 | C8: =IFERROR('NeatRescue — Cash & scenarios ·'!C7/'NeatRescue — Hackathon subm (3)'!C5,"") -> 0.35144518 | D8: =IFERROR('NeatRescue — Cash & scenarios ·'!D7/'NeatRescue — Hackathon subm (3)'!D5,"") -> 0.47137412 | E8: =IFERROR('NeatRescue — Cash & scenarios ·'!E7/'NeatRescue — Hackathon subm (3)'!E5,"") -> 0.53150919 | F8: =IFERROR('NeatRescue — Cash & scenarios ·'!F7/'NeatRescue — Hackathon subm (3)'!F5,"") -> 0.56770829 | G8: =IFERROR('NeatRescue — Cash & scenarios ·'!G7/'NeatRescue — Hackathon subm (3)'!G5,"") -> 0.59192375 | H8: =IFERROR('NeatRescue — Cash & scenarios ·'!H7/'NeatRescue — Hackathon subm (3)'!H5,"") -> 0.60927789 | I8: =IFERROR('NeatRescue — Cash & scenarios ·'!I7/'NeatRescue — Hackathon subm (3)'!I5,"") -> 0.6223319 | ... M8: =IFERROR('NeatRescue — Cash & scenarios ·'!M7/'NeatRescue — Hackathon subm (3)'!M5,"") -> 0.65289589
A9: Security expense | B9: =IF('NeatRescue — Assumptions & simu'!B13="","",'NeatRescue — Assumptions & simu'!B13) -> 75 | C9: =IF('NeatRescue — Assumptions & simu'!B13="","",'NeatRescue — Assumptions & simu'!B13) -> 75 | D9: =IF('NeatRescue — Assumptions & simu'!B13="","",'NeatRescue — Assumptions & simu'!B13) -> 75 | E9: =IF('NeatRescue — Assumptions & simu'!B13="","",'NeatRescue — Assumptions & simu'!B13) -> 75 | F9: =IF('NeatRescue — Assumptions & simu'!B13="","",'NeatRescue — Assumptions & simu'!B13) -> 75 | G9: =IF('NeatRescue — Assumptions & simu'!B13="","",'NeatRescue — Assumptions & simu'!B13) -> 75 | H9: =IF('NeatRescue — Assumptions & simu'!B13="","",'NeatRescue — Assumptions & simu'!B13) -> 75 | I9: =IF('NeatRescue — Assumptions & simu'!B13="","",'NeatRescue — Assumptions & simu'!B13) -> 75 | J9: =IF('NeatRescue — Assumptions & simu'!B13="","",'NeatRescue — Assumptions & simu'!B13) -> 75 | K9: =IF('NeatRescue — Assumptions & simu'!B13="","",'NeatRescue — Assumptions & simu'!B13) -> 75 | L9: =IF('NeatRescue — Assumptions & simu'!B13="","",'NeatRescue — Assumptions & simu'!B13) -> 75 | M9: =IF('NeatRescue — Assumptions & simu'!B13="","",'NeatRescue — Assumptions & simu'!B13) -> 75
A10: Acquisition expense | B10: =IF('NeatRescue — Assumptions & simu'!B15="","",'NeatRescue — Assumptions & simu'!B15) -> 150 | C10: =IF('NeatRescue — Assumptions & simu'!B15="","",'NeatRescue — Assumptions & simu'!B15) -> 150 | D10: =IF('NeatRescue — Assumptions & simu'!B15="","",'NeatRescue — Assumptions & simu'!B15) -> 150 | E10: =IF('NeatRescue — Assumptions & simu'!B15="","",'NeatRescue — Assumptions & simu'!B15) -> 150 | F10: =IF('NeatRescue — Assumptions & simu'!B15="","",'NeatRescue — Assumptions & simu'!B15) -> 150 | G10: =IF('NeatRescue — Assumptions & simu'!B15="","",'NeatRescue — Assumptions & simu'!B15) -> 150 | H10: =IF('NeatRescue — Assumptions & simu'!B15="","",'NeatRescue — Assumptions & simu'!B15) -> 150 | I10: =IF('NeatRescue — Assumptions & simu'!B15="","",'NeatRescue — Assumptions & simu'!B15) -> 150 | J10: =IF('NeatRescue — Assumptions & simu'!B15="","",'NeatRescue — Assumptions & simu'!B15) -> 150 | K10: =IF('NeatRescue — Assumptions & simu'!B15="","",'NeatRescue — Assumptions & simu'!B15) -> 150 | L10: =IF('NeatRescue — Assumptions & simu'!B15="","",'NeatRescue — Assumptions & simu'!B15) -> 150 | M10: =IF('NeatRescue — Assumptions & simu'!B15="","",'NeatRescue — Assumptions & simu'!B15) -> 150
A11: Founder pay | B11: =IF('NeatRescue — Assumptions & simu'!B19="","",'NeatRescue — Assumptions & simu'!B19) -> 0 | C11: =IF('NeatRescue — Assumptions & simu'!B19="","",'NeatRescue — Assumptions & simu'!B19) -> 0 | D11: =IF('NeatRescue — Assumptions & simu'!B19="","",'NeatRescue — Assumptions & simu'!B19) -> 0 | E11: =IF('NeatRescue — Assumptions & simu'!B19="","",'NeatRescue — Assumptions & simu'!B19) -> 0 | F11: =IF('NeatRescue — Assumptions & simu'!B19="","",'NeatRescue — Assumptions & simu'!B19) -> 0 | G11: =IF('NeatRescue — Assumptions & simu'!B19="","",'NeatRescue — Assumptions & simu'!B19) -> 0 | H11: =IF('NeatRescue — Assumptions & simu'!B19="","",'NeatRescue — Assumptions & simu'!B19) -> 0 | I11: =IF('NeatRescue — Assumptions & simu'!B19="","",'NeatRescue — Assumptions & simu'!B19) -> 0 | J11: =IF('NeatRescue — Assumptions & simu'!B19="","",'NeatRescue — Assumptions & simu'!B19) -> 0 | K11: =IF('NeatRescue — Assumptions & simu'!B19="","",'NeatRescue — Assumptions & simu'!B19) -> 0 | L11: =IF('NeatRescue — Assumptions & simu'!B19="","",'NeatRescue — Assumptions & simu'!B19) -> 0 | M11: =IF('NeatRescue — Assumptions & simu'!B19="","",'NeatRescue — Assumptions & simu'!B19) -> 0
A12: One-time launch cost | B12: =IF('NeatRescue — Assumptions & simu'!B16="","",'NeatRescue — Assumptions & simu'!B16) -> 200 | C12: =0 -> 0 | D12: =0 -> 0 | E12: =0 -> 0 | F12: =0 -> 0 | G12: =0 -> 0 | H12: =0 -> 0 | I12: =0 -> 0 | J12: =0 -> 0 | ... M12: =0 -> 0
A13: Operating expenses | B13: ='NeatRescue — Cash & scenarios ·'!B9+'NeatRescue — Cash & scenarios ·'!B10+'NeatRescue — Cash & scenarios ·'!B11+'NeatRescue — Cash & scenarios ·'!B12 -> 425 | C13: ='NeatRescue — Cash & scenarios ·'!C9+'NeatRescue — Cash & scenarios ·'!C10+'NeatRescue — Cash & scenarios ·'!C11+'NeatRescue — Cash & scenarios ·'!C12 -> 225 | D13: ='NeatRescue — Cash & scenarios ·'!D9+'NeatRescue — Cash & scenarios ·'!D10+'NeatRescue — Cash & scenarios ·'!D11+'NeatRescue — Cash & scenarios ·'!D12 -> 225 | E13: ='NeatRescue — Cash & scenarios ·'!E9+'NeatRescue — Cash & scenarios ·'!E10+'NeatRescue — Cash & scenarios ·'!E11+'NeatRescue — Cash & scenarios ·'!E12 -> 225 | F13: ='NeatRescue — Cash & scenarios ·'!F9+'NeatRescue — Cash & scenarios ·'!F10+'NeatRescue — Cash & scenarios ·'!F11+'NeatRescue — Cash & scenarios ·'!F12 -> 225 | G13: ='NeatRescue — Cash & scenarios ·'!G9+'NeatRescue — Cash & scenarios ·'!G10+'NeatRescue — Cash & scenarios ·'!G11+'NeatRescue — Cash & scenarios ·'!G12 -> 225 | H13: ='NeatRescue — Cash & scenarios ·'!H9+'NeatRescue — Cash & scenarios ·'!H10+'NeatRescue — Cash & scenarios ·'!H11+'NeatRescue — Cash & scenarios ·'!H12 -> 225 | I13: ='NeatRescue — Cash & scenarios ·'!I9+'NeatRescue — Cash & scenarios ·'!I10+'NeatRescue — Cash & scenarios ·'!I11+'NeatRescue — Cash & scenarios ·'!I12 -> 225 | ... M13: ='NeatRescue — Cash & scenarios ·'!M9+'NeatRescue — Cash & scenarios ·'!M10+'NeatRescue — Cash & scenarios ·'!M11+'NeatRescue — Cash & scenarios ·'!M12 -> 225
A14: Operating profit | B14: ='NeatRescue — Cash & scenarios ·'!B7-'NeatRescue — Cash & scenarios ·'!B13 -> -427.43 | C14: ='NeatRescue — Cash & scenarios ·'!C7-'NeatRescue — Cash & scenarios ·'!C13 -> 6.2685 | D14: ='NeatRescue — Cash & scenarios ·'!D7-'NeatRescue — Cash & scenarios ·'!D13 -> 252.76478 | E14: ='NeatRescue — Cash & scenarios ·'!E7-'NeatRescue — Cash & scenarios ·'!E13 -> 513.86721 | F14: ='NeatRescue — Cash & scenarios ·'!F7-'NeatRescue — Cash & scenarios ·'!F13 -> 791.53858 | G14: ='NeatRescue — Cash & scenarios ·'!G7-'NeatRescue — Cash & scenarios ·'!G13 -> 1087.9129 | H14: ='NeatRescue — Cash & scenarios ·'!H7-'NeatRescue — Cash & scenarios ·'!H13 -> 1405.3136 | I14: ='NeatRescue — Cash & scenarios ·'!I7-'NeatRescue — Cash & scenarios ·'!I13 -> 1746.2738 | ... M14: ='NeatRescue — Cash & scenarios ·'!M7-'NeatRescue — Cash & scenarios ·'!M13 -> 3405.0137
A15: Net cash flow | B15: =IF('NeatRescue — Cash & scenarios ·'!B14="","",'NeatRescue — Cash & scenarios ·'!B14) -> -427.43 | C15: =IF('NeatRescue — Cash & scenarios ·'!C14="","",'NeatRescue — Cash & scenarios ·'!C14) -> 6.2685 | D15: =IF('NeatRescue — Cash & scenarios ·'!D14="","",'NeatRescue — Cash & scenarios ·'!D14) -> 252.76478 | E15: =IF('NeatRescue — Cash & scenarios ·'!E14="","",'NeatRescue — Cash & scenarios ·'!E14) -> 513.86721 | F15: =IF('NeatRescue — Cash & scenarios ·'!F14="","",'NeatRescue — Cash & scenarios ·'!F14) -> 791.53858 | G15: =IF('NeatRescue — Cash & scenarios ·'!G14="","",'NeatRescue — Cash & scenarios ·'!G14) -> 1087.9129 | H15: =IF('NeatRescue — Cash & scenarios ·'!H14="","",'NeatRescue — Cash & scenarios ·'!H14) -> 1405.3136 | I15: =IF('NeatRescue — Cash & scenarios ·'!I14="","",'NeatRescue — Cash & scenarios ·'!I14) -> 1746.2738 | ... M15: =IF('NeatRescue — Cash & scenarios ·'!M14="","",'NeatRescue — Cash & scenarios ·'!M14) -> 3405.0137
A16: Monthly burn | B16: =MAX(-'NeatRescue — Cash & scenarios ·'!B15,0) -> 427.43 | C16: =MAX(-'NeatRescue — Cash & scenarios ·'!C15,0) -> 0 | D16: =MAX(-'NeatRescue — Cash & scenarios ·'!D15,0) -> 0 | E16: =MAX(-'NeatRescue — Cash & scenarios ·'!E15,0) -> 0 | F16: =MAX(-'NeatRescue — Cash & scenarios ·'!F15,0) -> 0 | G16: =MAX(-'NeatRescue — Cash & scenarios ·'!G15,0) -> 0 | H16: =MAX(-'NeatRescue — Cash & scenarios ·'!H15,0) -> 0 | I16: =MAX(-'NeatRescue — Cash & scenarios ·'!I15,0) -> 0 | ... M16: =MAX(-'NeatRescue — Cash & scenarios ·'!M15,0) -> 0
A17: Closing cash | B17: =IF(IF(DATE(2026,10,1)=DATE(2026,10,1),IF('NeatRescue — Assumptions & simu'!B17="","",'NeatRescue — Assumptions & simu'!B17),IF('Model inputs'!C11="","",'Model inputs'!C11))="",0,IF(DATE(2026,10,1)=DATE(2026,10,1),IF('NeatRescue — Assumptions & simu'!B17="","",'NeatRescue — Assumptions & simu'!B17),IF('Model inputs'!C11="","",'Model inputs'!C11)))+'NeatRescue — Cash & scenarios ·'!B15 -> -427.43 | C17: =IF(IF(DATE(2026,11,1)=DATE(2026,10,1),IF('NeatRescue — Assumptions & simu'!B17="","",'NeatRescue — Assumptions & simu'!B17),IF('NeatRescue — Cash & scenarios ·'!B17="","",'NeatRescue — Cash & scenarios ·'!B17))="",0,IF(DATE(2026,11,1)=DATE(2026,10,1),IF('NeatRescue — Assumptions & simu'!B17="","",'NeatRescue — Assumptions & simu'!B17),IF('NeatRescue — Cash & scenarios ·'!B17="","",'NeatRescue — Cash & scenarios ·'!B17)))+'NeatRescue — Cash & scenarios ·'!C15 -> -421.1615 | D17: =IF(IF(DATE(2026,12,1)=DATE(2026,10,1),IF('NeatRescue — Assumptions & simu'!B17="","",'NeatRescue — Assumptions & simu'!B17),IF('NeatRescue — Cash & scenarios ·'!C17="","",'NeatRescue — Cash & scenarios ·'!C17))="",0,IF(DATE(2026,12,1)=DATE(2026,10,1),IF('NeatRescue — Assumptions & simu'!B17="","",'NeatRescue — Assumptions & simu'!B17),IF('NeatRescue — Cash & scenarios ·'!C17="","",'NeatRescue — Cash & scenarios ·'!C17)))+'NeatRescue — Cash & scenarios ·'!D15 -> -168.39672 | E17: =IF(IF(DATE(2027,1,1)=DATE(2026,10,1),IF('NeatRescue — Assumptions & simu'!B17="","",'NeatRescue — Assumptions & simu'!B17),IF('NeatRescue — Cash & scenarios ·'!D17="","",'NeatRescue — Cash & scenarios ·'!D17))="",0,IF(DATE(2027,1,1)=DATE(2026,10,1),IF('NeatRescue — Assumptions & simu'!B17="","",'NeatRescue — Assumptions & simu'!B17),IF('NeatRescue — Cash & scenarios ·'!D17="","",'NeatRescue — Cash & scenarios ·'!D17)))+'NeatRescue — Cash & scenarios ·'!E15 -> 345.47048 | F17: =IF(IF(DATE(2027,2,1)=DATE(2026,10,1),IF('NeatRescue — Assumptions & simu'!B17="","",'NeatRescue — Assumptions & simu'!B17),IF('NeatRescue — Cash & scenarios ·'!E17="","",'NeatRescue — Cash & scenarios ·'!E17))="",0,IF(DATE(2027,2,1)=DATE(2026,10,1),IF('NeatRescue — Assumptions & simu'!B17="","",'NeatRescue — Assumptions & simu'!B17),IF('NeatRescue — Cash & scenarios ·'!E17="","",'NeatRescue — Cash & scenarios ·'!E17)))+'NeatRescue — Cash & scenarios ·'!F15 -> 1137.0091 | G17: =IF(IF(DATE(2027,3,1)=DATE(2026,10,1),IF('NeatRescue — Assumptions & simu'!B17="","",'NeatRescue — Assumptions & simu'!B17),IF('NeatRescue — Cash & scenarios ·'!F17="","",'NeatRescue — Cash & scenarios ·'!F17))="",0,IF(DATE(2027,3,1)=DATE(2026,10,1),IF('NeatRescue — Assumptions & simu'!B17="","",'NeatRescue — Assumptions & simu'!B17),IF('NeatRescue — Cash & scenarios ·'!F17="","",'NeatRescue — Cash & scenarios ·'!F17)))+'NeatRescue — Cash & scenarios ·'!G15 -> 2224.9219 | H17: =IF(IF(DATE(2027,4,1)=DATE(2026,10,1),IF('NeatRescue — Assumptions & simu'!B17="","",'NeatRescue — Assumptions & simu'!B17),IF('NeatRescue — Cash & scenarios ·'!G17="","",'NeatRescue — Cash & scenarios ·'!G17))="",0,IF(DATE(2027,4,1)=DATE(2026,10,1),IF('NeatRescue — Assumptions & simu'!B17="","",'NeatRescue — Assumptions & simu'!B17),IF('NeatRescue — Cash & scenarios ·'!G17="","",'NeatRescue — Cash & scenarios ·'!G17)))+'NeatRescue — Cash & scenarios ·'!H15 -> 3630.2355 | I17: =IF(IF(DATE(2027,5,1)=DATE(2026,10,1),IF('NeatRescue — Assumptions & simu'!B17="","",'NeatRescue — Assumptions & simu'!B17),IF('NeatRescue — Cash & scenarios ·'!H17="","",'NeatRescue — Cash & scenarios ·'!H17))="",0,IF(DATE(2027,5,1)=DATE(2026,10,1),IF('NeatRescue — Assumptions & simu'!B17="","",'NeatRescue — Assumptions & simu'!B17),IF('NeatRescue — Cash & scenarios ·'!H17="","",'NeatRescue — Cash & scenarios ·'!H17)))+'NeatRescue — Cash & scenarios ·'!I15 -> 5376.5093 | J17: =IF(IF(DATE(2027,6,1)=DATE(2026,10,1),IF('NeatRescue — Assumptions & simu'!B17="","",'NeatRescue — Assumptions & simu'!B17),IF('NeatRescue — Cash & scenarios ·'!I17="","",'NeatRescue — Cash & scenarios ·'!I17))="",0,IF(DATE(2027,6,1)=DATE(2026,10,1),IF('NeatRescue — Assumptions & simu'!B17="","",'NeatRescue — Assumptions & simu'!B17),IF('NeatRescue — Cash & scenarios ·'!I17="","",'NeatRescue — Cash & scenarios ·'!I17)))+'NeatRescue — Cash & scenarios ·'!J15 -> 7490.068 | K17: =IF(IF(DATE(2027,7,1)=DATE(2026,10,1),IF('NeatRescue — Assumptions & simu'!B17="","",'NeatRescue — Assumptions & simu'!B17),IF('NeatRescue — Cash & scenarios ·'!J17="","",'NeatRescue — Cash & scenarios ·'!J17))="",0,IF(DATE(2027,7,1)=DATE(2026,10,1),IF('NeatRescue — Assumptions & simu'!B17="","",'NeatRescue — Assumptions & simu'!B17),IF('NeatRescue — Cash & scenarios ·'!J17="","",'NeatRescue — Cash & scenarios ·'!J17)))+'NeatRescue — Cash & scenarios ·'!K15 -> 10000.257 | L17: =IF(IF(DATE(2027,8,1)=DATE(2026,10,1),IF('NeatRescue — Assumptions & simu'!B17="","",'NeatRescue — Assumptions & simu'!B17),IF('NeatRescue — Cash & scenarios ·'!K17="","",'NeatRescue — Cash & scenarios ·'!K17))="",0,IF(DATE(2027,8,1)=DATE(2026,10,1),IF('NeatRescue — Assumptions & simu'!B17="","",'NeatRescue — Assumptions & simu'!B17),IF('NeatRescue — Cash & scenarios ·'!K17="","",'NeatRescue — Cash & scenarios ·'!K17)))+'NeatRescue — Cash & scenarios ·'!L15 -> 12939.726 | M17: =IF(IF(DATE(2027,9,1)=DATE(2026,10,1),IF('NeatRescue — Assumptions & simu'!B17="","",'NeatRescue — Assumptions & simu'!B17),IF('NeatRescue — Cash & scenarios ·'!L17="","",'NeatRescue — Cash & scenarios ·'!L17))="",0,IF(DATE(2027,9,1)=DATE(2026,10,1),IF('NeatRescue — Assumptions & simu'!B17="","",'NeatRescue — Assumptions & simu'!B17),IF('NeatRescue — Cash & scenarios ·'!L17="","",'NeatRescue — Cash & scenarios ·'!L17)))+'NeatRescue — Cash & scenarios ·'!M15 -> 16344.74
A18: Funding shortfall | B18: =MAX(-'NeatRescue — Cash & scenarios ·'!B17,0) -> 427.43 | C18: =MAX(-'NeatRescue — Cash & scenarios ·'!C17,0) -> 421.1615 | D18: =MAX(-'NeatRescue — Cash & scenarios ·'!D17,0) -> 168.39672 | E18: =MAX(-'NeatRescue — Cash & scenarios ·'!E17,0) -> 0 | F18: =MAX(-'NeatRescue — Cash & scenarios ·'!F17,0) -> 0 | G18: =MAX(-'NeatRescue — Cash & scenarios ·'!G17,0) -> 0 | H18: =MAX(-'NeatRescue — Cash & scenarios ·'!H17,0) -> 0 | I18: =MAX(-'NeatRescue — Cash & scenarios ·'!I17,0) -> 0 | ... M18: =MAX(-'NeatRescue — Cash & scenarios ·'!M17,0) -> 0
A19: Revenue per customer | B19: =IFERROR('NeatRescue — Hackathon subm (3)'!B5/'NeatRescue — Revenue & costs ·'!B14,"") -> 107 | C19: =IFERROR('NeatRescue — Hackathon subm (3)'!C5/'NeatRescue — Revenue & costs ·'!C14,"") -> 107 | D19: =IFERROR('NeatRescue — Hackathon subm (3)'!D5/'NeatRescue — Revenue & costs ·'!D14,"") -> 107 | E19: =IFERROR('NeatRescue — Hackathon subm (3)'!E5/'NeatRescue — Revenue & costs ·'!E14,"") -> 107 | F19: =IFERROR('NeatRescue — Hackathon subm (3)'!F5/'NeatRescue — Revenue & costs ·'!F14,"") -> 107 | G19: =IFERROR('NeatRescue — Hackathon subm (3)'!G5/'NeatRescue — Revenue & costs ·'!G14,"") -> 107 | H19: =IFERROR('NeatRescue — Hackathon subm (3)'!H5/'NeatRescue — Revenue & costs ·'!H14,"") -> 107 | I19: =IFERROR('NeatRescue — Hackathon subm (3)'!I5/'NeatRescue — Revenue & costs ·'!I14,"") -> 107 | ... M19: =IFERROR('NeatRescue — Hackathon subm (3)'!M5/'NeatRescue — Revenue & costs ·'!M14,"") -> 107
A20: Contribution per customer | B20: =IFERROR('NeatRescue — Revenue & costs ·'!B47/'NeatRescue — Revenue & costs ·'!B14,"") -> 74.19 | C20: =IFERROR('NeatRescue — Revenue & costs ·'!C47/'NeatRescue — Revenue & costs ·'!C14,"") -> 74.19 | D20: =IFERROR('NeatRescue — Revenue & costs ·'!D47/'NeatRescue — Revenue & costs ·'!D14,"") -> 74.19 | E20: =IFERROR('NeatRescue — Revenue & costs ·'!E47/'NeatRescue — Revenue & costs ·'!E14,"") -> 74.19 | F20: =IFERROR('NeatRescue — Revenue & costs ·'!F47/'NeatRescue — Revenue & costs ·'!F14,"") -> 74.19 | G20: =IFERROR('NeatRescue — Revenue & costs ·'!G47/'NeatRescue — Revenue & costs ·'!G14,"") -> 74.19 | H20: =IFERROR('NeatRescue — Revenue & costs ·'!H47/'NeatRescue — Revenue & costs ·'!H14,"") -> 74.19 | I20: =IFERROR('NeatRescue — Revenue & costs ·'!I47/'NeatRescue — Revenue & costs ·'!I14,"") -> 74.19 | ... M20: =IFERROR('NeatRescue — Revenue & costs ·'!M47/'NeatRescue — Revenue & costs ·'!M14,"") -> 74.19
A21: Break-even customers | B21: =IF(IF(IF(ISERROR('NeatRescue — Cash & scenarios ·'!B20>0),'NeatRescue — Cash & scenarios ·'!B20>0,IF('NeatRescue — Cash & scenarios ·'!B20="","",'NeatRescue — Cash & scenarios ·'!B20>0))="",FALSE,IF(ISERROR('NeatRescue — Cash & scenarios ·'!B20>0),'NeatRescue — Cash & scenarios ·'!B20>0,IF('NeatRescue — Cash & scenarios ·'!B20="","",'NeatRescue — Cash & scenarios ·'!B20>0))),CEILING(('NeatRescue — Cash & scenarios ·'!B5+'NeatRescue — Cash & scenarios ·'!B9+'NeatRescue — Cash & scenarios ·'!B10+'NeatRescue — Cash & scenarios ·'!B11)/'NeatRescue — Cash & scenarios ·'!B20,1),"") -> 7 | C21: =IF(IF(IF(ISERROR('NeatRescue — Cash & scenarios ·'!C20>0),'NeatRescue — Cash & scenarios ·'!C20>0,IF('NeatRescue — Cash & scenarios ·'!C20="","",'NeatRescue — Cash & scenarios ·'!C20>0))="",FALSE,IF(ISERROR('NeatRescue — Cash & scenarios ·'!C20>0),'NeatRescue — Cash & scenarios ·'!C20>0,IF('NeatRescue — Cash & scenarios ·'!C20="","",'NeatRescue — Cash & scenarios ·'!C20>0))),CEILING(('NeatRescue — Cash & scenarios ·'!C5+'NeatRescue — Cash & scenarios ·'!C9+'NeatRescue — Cash & scenarios ·'!C10+'NeatRescue — Cash & scenarios ·'!C11)/'NeatRescue — Cash & scenarios ·'!C20,1),"") -> 7 | D21: =IF(IF(IF(ISERROR('NeatRescue — Cash & scenarios ·'!D20>0),'NeatRescue — Cash & scenarios ·'!D20>0,IF('NeatRescue — Cash & scenarios ·'!D20="","",'NeatRescue — Cash & scenarios ·'!D20>0))="",FALSE,IF(ISERROR('NeatRescue — Cash & scenarios ·'!D20>0),'NeatRescue — Cash & scenarios ·'!D20>0,IF('NeatRescue — Cash & scenarios ·'!D20="","",'NeatRescue — Cash & scenarios ·'!D20>0))),CEILING(('NeatRescue — Cash & scenarios ·'!D5+'NeatRescue — Cash & scenarios ·'!D9+'NeatRescue — Cash & scenarios ·'!D10+'NeatRescue — Cash & scenarios ·'!D11)/'NeatRescue — Cash & scenarios ·'!D20,1),"") -> 7 | E21: =IF(IF(IF(ISERROR('NeatRescue — Cash & scenarios ·'!E20>0),'NeatRescue — Cash & scenarios ·'!E20>0,IF('NeatRescue — Cash & scenarios ·'!E20="","",'NeatRescue — Cash & scenarios ·'!E20>0))="",FALSE,IF(ISERROR('NeatRescue — Cash & scenarios ·'!E20>0),'NeatRescue — Cash & scenarios ·'!E20>0,IF('NeatRescue — Cash & scenarios ·'!E20="","",'NeatRescue — Cash & scenarios ·'!E20>0))),CEILING(('NeatRescue — Cash & scenarios ·'!E5+'NeatRescue — Cash & scenarios ·'!E9+'NeatRescue — Cash & scenarios ·'!E10+'NeatRescue — Cash & scenarios ·'!E11)/'NeatRescue — Cash & scenarios ·'!E20,1),"") -> 7 | F21: =IF(IF(IF(ISERROR('NeatRescue — Cash & scenarios ·'!F20>0),'NeatRescue — Cash & scenarios ·'!F20>0,IF('NeatRescue — Cash & scenarios ·'!F20="","",'NeatRescue — Cash & scenarios ·'!F20>0))="",FALSE,IF(ISERROR('NeatRescue — Cash & scenarios ·'!F20>0),'NeatRescue — Cash & scenarios ·'!F20>0,IF('NeatRescue — Cash & scenarios ·'!F20="","",'NeatRescue — Cash & scenarios ·'!F20>0))),CEILING(('NeatRescue — Cash & scenarios ·'!F5+'NeatRescue — Cash & scenarios ·'!F9+'NeatRescue — Cash & scenarios ·'!F10+'NeatRescue — Cash & scenarios ·'!F11)/'NeatRescue — Cash & scenarios ·'!F20,1),"") -> 7 | G21: =IF(IF(IF(ISERROR('NeatRescue — Cash & scenarios ·'!G20>0),'NeatRescue — Cash & scenarios ·'!G20>0,IF('NeatRescue — Cash & scenarios ·'!G20="","",'NeatRescue — Cash & scenarios ·'!G20>0))="",FALSE,IF(ISERROR('NeatRescue — Cash & scenarios ·'!G20>0),'NeatRescue — Cash & scenarios ·'!G20>0,IF('NeatRescue — Cash & scenarios ·'!G20="","",'NeatRescue — Cash & scenarios ·'!G20>0))),CEILING(('NeatRescue — Cash & scenarios ·'!G5+'NeatRescue — Cash & scenarios ·'!G9+'NeatRescue — Cash & scenarios ·'!G10+'NeatRescue — Cash & scenarios ·'!G11)/'NeatRescue — Cash & scenarios ·'!G20,1),"") -> 7 | H21: =IF(IF(IF(ISERROR('NeatRescue — Cash & scenarios ·'!H20>0),'NeatRescue — Cash & scenarios ·'!H20>0,IF('NeatRescue — Cash & scenarios ·'!H20="","",'NeatRescue — Cash & scenarios ·'!H20>0))="",FALSE,IF(ISERROR('NeatRescue — Cash & scenarios ·'!H20>0),'NeatRescue — Cash & scenarios ·'!H20>0,IF('NeatRescue — Cash & scenarios ·'!H20="","",'NeatRescue — Cash & scenarios ·'!H20>0))),CEILING(('NeatRescue — Cash & scenarios ·'!H5+'NeatRescue — Cash & scenarios ·'!H9+'NeatRescue — Cash & scenarios ·'!H10+'NeatRescue — Cash & scenarios ·'!H11)/'NeatRescue — Cash & scenarios ·'!H20,1),"") -> 7 | I21: =IF(IF(IF(ISERROR('NeatRescue — Cash & scenarios ·'!I20>0),'NeatRescue — Cash & scenarios ·'!I20>0,IF('NeatRescue — Cash & scenarios ·'!I20="","",'NeatRescue — Cash & scenarios ·'!I20>0))="",FALSE,IF(ISERROR('NeatRescue — Cash & scenarios ·'!I20>0),'NeatRescue — Cash & scenarios ·'!I20>0,IF('NeatRescue — Cash & scenarios ·'!I20="","",'NeatRescue — Cash & scenarios ·'!I20>0))),CEILING(('NeatRescue — Cash & scenarios ·'!I5+'NeatRescue — Cash & scenarios ·'!I9+'NeatRescue — Cash & scenarios ·'!I10+'NeatRescue — Cash & scenarios ·'!I11)/'NeatRescue — Cash & scenarios ·'!I20,1),"") -> 7 | ... M21: =IF(IF(IF(ISERROR('NeatRescue — Cash & scenarios ·'!M20>0),'NeatRescue — Cash & scenarios ·'!M20>0,IF('NeatRescue — Cash & scenarios ·'!M20="","",'NeatRescue — Cash & scenarios ·'!M20>0))="",FALSE,IF(ISERROR('NeatRescue — Cash & scenarios ·'!M20>0),'NeatRescue — Cash & scenarios ·'!M20>0,IF('NeatRescue — Cash & scenarios ·'!M20="","",'NeatRescue — Cash & scenarios ·'!M20>0))),CEILING(('NeatRescue — Cash & scenarios ·'!M5+'NeatRescue — Cash & scenarios ·'!M9+'NeatRescue — Cash & scenarios ·'!M10+'NeatRescue — Cash & scenarios ·'!M11)/'NeatRescue — Cash & scenarios ·'!M20,1),"") -> 7

Sheet NeatRescue — Cash & scenari (2)
A1: NeatRescue — Cash & scenarios · Monthly cash — actual-zero and hypothetical bootstrap cases
A2: Financial model (5 pages) · Main Scenario
A4: Variable / dimension | B4: 2026-10 | C4: 2026-11 | D4: 2026-12 | E4: 2027-01 | F4: 2027-02 | G4: 2027-03 | H4: 2027-04 | I4: 2027-05 | J4: 2027-06 | K4: 2027-07 | L4: 2027-08 | M4: 2027-09
A5: Closing cash | B5: =IF(IF(DATE(2026,10,1)=DATE(2026,10,1),IF('NeatRescue — Assumptions & simu'!B17="","",'NeatRescue — Assumptions & simu'!B17),IF('Model inputs'!C11="","",'Model inputs'!C11))="",0,IF(DATE(2026,10,1)=DATE(2026,10,1),IF('NeatRescue — Assumptions & simu'!B17="","",'NeatRescue — Assumptions & simu'!B17),IF('Model inputs'!C11="","",'Model inputs'!C11)))+'NeatRescue — Cash & scenarios ·'!B15 -> -427.43 | C5: =IF(IF(DATE(2026,11,1)=DATE(2026,10,1),IF('NeatRescue — Assumptions & simu'!B17="","",'NeatRescue — Assumptions & simu'!B17),IF('NeatRescue — Cash & scenari (2)'!B5="","",'NeatRescue — Cash & scenari (2)'!B5))="",0,IF(DATE(2026,11,1)=DATE(2026,10,1),IF('NeatRescue — Assumptions & simu'!B17="","",'NeatRescue — Assumptions & simu'!B17),IF('NeatRescue — Cash & scenari (2)'!B5="","",'NeatRescue — Cash & scenari (2)'!B5)))+'NeatRescue — Cash & scenarios ·'!C15 -> -421.1615 | D5: =IF(IF(DATE(2026,12,1)=DATE(2026,10,1),IF('NeatRescue — Assumptions & simu'!B17="","",'NeatRescue — Assumptions & simu'!B17),IF('NeatRescue — Cash & scenari (2)'!C5="","",'NeatRescue — Cash & scenari (2)'!C5))="",0,IF(DATE(2026,12,1)=DATE(2026,10,1),IF('NeatRescue — Assumptions & simu'!B17="","",'NeatRescue — Assumptions & simu'!B17),IF('NeatRescue — Cash & scenari (2)'!C5="","",'NeatRescue — Cash & scenari (2)'!C5)))+'NeatRescue — Cash & scenarios ·'!D15 -> -168.39672 | E5: =IF(IF(DATE(2027,1,1)=DATE(2026,10,1),IF('NeatRescue — Assumptions & simu'!B17="","",'NeatRescue — Assumptions & simu'!B17),IF('NeatRescue — Cash & scenari (2)'!D5="","",'NeatRescue — Cash & scenari (2)'!D5))="",0,IF(DATE(2027,1,1)=DATE(2026,10,1),IF('NeatRescue — Assumptions & simu'!B17="","",'NeatRescue — Assumptions & simu'!B17),IF('NeatRescue — Cash & scenari (2)'!D5="","",'NeatRescue — Cash & scenari (2)'!D5)))+'NeatRescue — Cash & scenarios ·'!E15 -> 345.47048 | F5: =IF(IF(DATE(2027,2,1)=DATE(2026,10,1),IF('NeatRescue — Assumptions & simu'!B17="","",'NeatRescue — Assumptions & simu'!B17),IF('NeatRescue — Cash & scenari (2)'!E5="","",'NeatRescue — Cash & scenari (2)'!E5))="",0,IF(DATE(2027,2,1)=DATE(2026,10,1),IF('NeatRescue — Assumptions & simu'!B17="","",'NeatRescue — Assumptions & simu'!B17),IF('NeatRescue — Cash & scenari (2)'!E5="","",'NeatRescue — Cash & scenari (2)'!E5)))+'NeatRescue — Cash & scenarios ·'!F15 -> 1137.0091 | G5: =IF(IF(DATE(2027,3,1)=DATE(2026,10,1),IF('NeatRescue — Assumptions & simu'!B17="","",'NeatRescue — Assumptions & simu'!B17),IF('NeatRescue — Cash & scenari (2)'!F5="","",'NeatRescue — Cash & scenari (2)'!F5))="",0,IF(DATE(2027,3,1)=DATE(2026,10,1),IF('NeatRescue — Assumptions & simu'!B17="","",'NeatRescue — Assumptions & simu'!B17),IF('NeatRescue — Cash & scenari (2)'!F5="","",'NeatRescue — Cash & scenari (2)'!F5)))+'NeatRescue — Cash & scenarios ·'!G15 -> 2224.9219 | H5: =IF(IF(DATE(2027,4,1)=DATE(2026,10,1),IF('NeatRescue — Assumptions & simu'!B17="","",'NeatRescue — Assumptions & simu'!B17),IF('NeatRescue — Cash & scenari (2)'!G5="","",'NeatRescue — Cash & scenari (2)'!G5))="",0,IF(DATE(2027,4,1)=DATE(2026,10,1),IF('NeatRescue — Assumptions & simu'!B17="","",'NeatRescue — Assumptions & simu'!B17),IF('NeatRescue — Cash & scenari (2)'!G5="","",'NeatRescue — Cash & scenari (2)'!G5)))+'NeatRescue — Cash & scenarios ·'!H15 -> 3630.2355 | I5: =IF(IF(DATE(2027,5,1)=DATE(2026,10,1),IF('NeatRescue — Assumptions & simu'!B17="","",'NeatRescue — Assumptions & simu'!B17),IF('NeatRescue — Cash & scenari (2)'!H5="","",'NeatRescue — Cash & scenari (2)'!H5))="",0,IF(DATE(2027,5,1)=DATE(2026,10,1),IF('NeatRescue — Assumptions & simu'!B17="","",'NeatRescue — Assumptions & simu'!B17),IF('NeatRescue — Cash & scenari (2)'!H5="","",'NeatRescue — Cash & scenari (2)'!H5)))+'NeatRescue — Cash & scenarios ·'!I15 -> 5376.5093 | J5: =IF(IF(DATE(2027,6,1)=DATE(2026,10,1),IF('NeatRescue — Assumptions & simu'!B17="","",'NeatRescue — Assumptions & simu'!B17),IF('NeatRescue — Cash & scenari (2)'!I5="","",'NeatRescue — Cash & scenari (2)'!I5))="",0,IF(DATE(2027,6,1)=DATE(2026,10,1),IF('NeatRescue — Assumptions & simu'!B17="","",'NeatRescue — Assumptions & simu'!B17),IF('NeatRescue — Cash & scenari (2)'!I5="","",'NeatRescue — Cash & scenari (2)'!I5)))+'NeatRescue — Cash & scenarios ·'!J15 -> 7490.068 | K5: =IF(IF(DATE(2027,7,1)=DATE(2026,10,1),IF('NeatRescue — Assumptions & simu'!B17="","",'NeatRescue — Assumptions & simu'!B17),IF('NeatRescue — Cash & scenari (2)'!J5="","",'NeatRescue — Cash & scenari (2)'!J5))="",0,IF(DATE(2027,7,1)=DATE(2026,10,1),IF('NeatRescue — Assumptions & simu'!B17="","",'NeatRescue — Assumptions & simu'!B17),IF('NeatRescue — Cash & scenari (2)'!J5="","",'NeatRescue — Cash & scenari (2)'!J5)))+'NeatRescue — Cash & scenarios ·'!K15 -> 10000.257 | L5: =IF(IF(DATE(2027,8,1)=DATE(2026,10,1),IF('NeatRescue — Assumptions & simu'!B17="","",'NeatRescue — Assumptions & simu'!B17),IF('NeatRescue — Cash & scenari (2)'!K5="","",'NeatRescue — Cash & scenari (2)'!K5))="",0,IF(DATE(2027,8,1)=DATE(2026,10,1),IF('NeatRescue — Assumptions & simu'!B17="","",'NeatRescue — Assumptions & simu'!B17),IF('NeatRescue — Cash & scenari (2)'!K5="","",'NeatRescue — Cash & scenari (2)'!K5)))+'NeatRescue — Cash & scenarios ·'!L15 -> 12939.726 | M5: =IF(IF(DATE(2027,9,1)=DATE(2026,10,1),IF('NeatRescue — Assumptions & simu'!B17="","",'NeatRescue — Assumptions & simu'!B17),IF('NeatRescue — Cash & scenari (2)'!L5="","",'NeatRescue — Cash & scenari (2)'!L5))="",0,IF(DATE(2027,9,1)=DATE(2026,10,1),IF('NeatRescue — Assumptions & simu'!B17="","",'NeatRescue — Assumptions & simu'!B17),IF('NeatRescue — Cash & scenari (2)'!L5="","",'NeatRescue — Cash & scenari (2)'!L5)))+'NeatRescue — Cash & scenarios ·'!M15 -> 16344.74
A6: Closing cash > Bootstrap $5,000 — hypothetical | B6: =IF(IF(DATE(2026,10,1)=DATE(2026,10,1),IF('Model inputs'!O47="","",'Model inputs'!O47),IF('Model inputs'!C14="","",'Model inputs'!C14))="",0,IF(DATE(2026,10,1)=DATE(2026,10,1),IF('Model inputs'!O47="","",'Model inputs'!O47),IF('Model inputs'!C14="","",'Model inputs'!C14)))+'Model inputs'!D44 -> 4572.57 | C6: =IF(IF(DATE(2026,11,1)=DATE(2026,10,1),IF('Model inputs'!O47="","",'Model inputs'!O47),IF('NeatRescue — Cash & scenari (2)'!B6="","",'NeatRescue — Cash & scenari (2)'!B6))="",0,IF(DATE(2026,11,1)=DATE(2026,10,1),IF('Model inputs'!O47="","",'Model inputs'!O47),IF('NeatRescue — Cash & scenari (2)'!B6="","",'NeatRescue — Cash & scenari (2)'!B6)))+'Model inputs'!E44 -> 4578.8385 | D6: =IF(IF(DATE(2026,12,1)=DATE(2026,10,1),IF('Model inputs'!O47="","",'Model inputs'!O47),IF('NeatRescue — Cash & scenari (2)'!C6="","",'NeatRescue — Cash & scenari (2)'!C6))="",0,IF(DATE(2026,12,1)=DATE(2026,10,1),IF('Model inputs'!O47="","",'Model inputs'!O47),IF('NeatRescue — Cash & scenari (2)'!C6="","",'NeatRescue — Cash & scenari (2)'!C6)))+'Model inputs'!F44 -> 4831.6033 | E6: =IF(IF(DATE(2027,1,1)=DATE(2026,10,1),IF('Model inputs'!O47="","",'Model inputs'!O47),IF('NeatRescue — Cash & scenari (2)'!D6="","",'NeatRescue — Cash & scenari (2)'!D6))="",0,IF(DATE(2027,1,1)=DATE(2026,10,1),IF('Model inputs'!O47="","",'Model inputs'!O47),IF('NeatRescue — Cash & scenari (2)'!D6="","",'NeatRescue — Cash & scenari (2)'!D6)))+'Model inputs'!G44 -> 5345.4705 | F6: =IF(IF(DATE(2027,2,1)=DATE(2026,10,1),IF('Model inputs'!O47="","",'Model inputs'!O47),IF('NeatRescue — Cash & scenari (2)'!E6="","",'NeatRescue — Cash & scenari (2)'!E6))="",0,IF(DATE(2027,2,1)=DATE(2026,10,1),IF('Model inputs'!O47="","",'Model inputs'!O47),IF('NeatRescue — Cash & scenari (2)'!E6="","",'NeatRescue — Cash & scenari (2)'!E6)))+'Model inputs'!H44 -> 6137.0091 | G6: =IF(IF(DATE(2027,3,1)=DATE(2026,10,1),IF('Model inputs'!O47="","",'Model inputs'!O47),IF('NeatRescue — Cash & scenari (2)'!F6="","",'NeatRescue — Cash & scenari (2)'!F6))="",0,IF(DATE(2027,3,1)=DATE(2026,10,1),IF('Model inputs'!O47="","",'Model inputs'!O47),IF('NeatRescue — Cash & scenari (2)'!F6="","",'NeatRescue — Cash & scenari (2)'!F6)))+'Model inputs'!I44 -> 7224.9219 | H6: =IF(IF(DATE(2027,4,1)=DATE(2026,10,1),IF('Model inputs'!O47="","",'Model inputs'!O47),IF('NeatRescue — Cash & scenari (2)'!G6="","",'NeatRescue — Cash & scenari (2)'!G6))="",0,IF(DATE(2027,4,1)=DATE(2026,10,1),IF('Model inputs'!O47="","",'Model inputs'!O47),IF('NeatRescue — Cash & scenari (2)'!G6="","",'NeatRescue — Cash & scenari (2)'!G6)))+'Model inputs'!J44 -> 8630.2355 | I6: =IF(IF(DATE(2027,5,1)=DATE(2026,10,1),IF('Model inputs'!O47="","",'Model inputs'!O47),IF('NeatRescue — Cash & scenari (2)'!H6="","",'NeatRescue — Cash & scenari (2)'!H6))="",0,IF(DATE(2027,5,1)=DATE(2026,10,1),IF('Model inputs'!O47="","",'Model inputs'!O47),IF('NeatRescue — Cash & scenari (2)'!H6="","",'NeatRescue — Cash & scenari (2)'!H6)))+'Model inputs'!K44 -> 10376.509 | J6: =IF(IF(DATE(2027,6,1)=DATE(2026,10,1),IF('Model inputs'!O47="","",'Model inputs'!O47),IF('NeatRescue — Cash & scenari (2)'!I6="","",'NeatRescue — Cash & scenari (2)'!I6))="",0,IF(DATE(2027,6,1)=DATE(2026,10,1),IF('Model inputs'!O47="","",'Model inputs'!O47),IF('NeatRescue — Cash & scenari (2)'!I6="","",'NeatRescue — Cash & scenari (2)'!I6)))+'Model inputs'!L44 -> 12490.068 | K6: =IF(IF(DATE(2027,7,1)=DATE(2026,10,1),IF('Model inputs'!O47="","",'Model inputs'!O47),IF('NeatRescue — Cash & scenari (2)'!J6="","",'NeatRescue — Cash & scenari (2)'!J6))="",0,IF(DATE(2027,7,1)=DATE(2026,10,1),IF('Model inputs'!O47="","",'Model inputs'!O47),IF('NeatRescue — Cash & scenari (2)'!J6="","",'NeatRescue — Cash & scenari (2)'!J6)))+'Model inputs'!M44 -> 15000.257 | L6: =IF(IF(DATE(2027,8,1)=DATE(2026,10,1),IF('Model inputs'!O47="","",'Model inputs'!O47),IF('NeatRescue — Cash & scenari (2)'!K6="","",'NeatRescue — Cash & scenari (2)'!K6))="",0,IF(DATE(2027,8,1)=DATE(2026,10,1),IF('Model inputs'!O47="","",'Model inputs'!O47),IF('NeatRescue — Cash & scenari (2)'!K6="","",'NeatRescue — Cash & scenari (2)'!K6)))+'Model inputs'!N44 -> 17939.726 | M6: =IF(IF(DATE(2027,9,1)=DATE(2026,10,1),IF('Model inputs'!O47="","",'Model inputs'!O47),IF('NeatRescue — Cash & scenari (2)'!L6="","",'NeatRescue — Cash & scenari (2)'!L6))="",0,IF(DATE(2027,9,1)=DATE(2026,10,1),IF('Model inputs'!O47="","",'Model inputs'!O47),IF('NeatRescue — Cash & scenari (2)'!L6="","",'NeatRescue — Cash & scenari (2)'!L6)))+'Model inputs'!B44 -> 21344.74
A7: Closing cash > Bootstrap no-sales stress — hypothetical | B7: =IF(IF(DATE(2026,10,1)=DATE(2026,10,1),IF('Model inputs'!O46="","",'Model inputs'!O46),IF('Model inputs'!C12="","",'Model inputs'!C12))="",0,IF(DATE(2026,10,1)=DATE(2026,10,1),IF('Model inputs'!O46="","",'Model inputs'!O46),IF('Model inputs'!C12="","",'Model inputs'!C12)))+'Model inputs'!D43 -> 4350 | C7: =IF(IF(DATE(2026,11,1)=DATE(2026,10,1),IF('Model inputs'!O46="","",'Model inputs'!O46),IF('NeatRescue — Cash & scenari (2)'!B7="","",'NeatRescue — Cash & scenari (2)'!B7))="",0,IF(DATE(2026,11,1)=DATE(2026,10,1),IF('Model inputs'!O46="","",'Model inputs'!O46),IF('NeatRescue — Cash & scenari (2)'!B7="","",'NeatRescue — Cash & scenari (2)'!B7)))+'Model inputs'!E43 -> 3900 | D7: =IF(IF(DATE(2026,12,1)=DATE(2026,10,1),IF('Model inputs'!O46="","",'Model inputs'!O46),IF('NeatRescue — Cash & scenari (2)'!C7="","",'NeatRescue — Cash & scenari (2)'!C7))="",0,IF(DATE(2026,12,1)=DATE(2026,10,1),IF('Model inputs'!O46="","",'Model inputs'!O46),IF('NeatRescue — Cash & scenari (2)'!C7="","",'NeatRescue — Cash & scenari (2)'!C7)))+'Model inputs'!F43 -> 3450 | E7: =IF(IF(DATE(2027,1,1)=DATE(2026,10,1),IF('Model inputs'!O46="","",'Model inputs'!O46),IF('NeatRescue — Cash & scenari (2)'!D7="","",'NeatRescue — Cash & scenari (2)'!D7))="",0,IF(DATE(2027,1,1)=DATE(2026,10,1),IF('Model inputs'!O46="","",'Model inputs'!O46),IF('NeatRescue — Cash & scenari (2)'!D7="","",'NeatRescue — Cash & scenari (2)'!D7)))+'Model inputs'!G43 -> 3000 | F7: =IF(IF(DATE(2027,2,1)=DATE(2026,10,1),IF('Model inputs'!O46="","",'Model inputs'!O46),IF('NeatRescue — Cash & scenari (2)'!E7="","",'NeatRescue — Cash & scenari (2)'!E7))="",0,IF(DATE(2027,2,1)=DATE(2026,10,1),IF('Model inputs'!O46="","",'Model inputs'!O46),IF('NeatRescue — Cash & scenari (2)'!E7="","",'NeatRescue — Cash & scenari (2)'!E7)))+'Model inputs'!H43 -> 2550 | G7: =IF(IF(DATE(2027,3,1)=DATE(2026,10,1),IF('Model inputs'!O46="","",'Model inputs'!O46),IF('NeatRescue — Cash & scenari (2)'!F7="","",'NeatRescue — Cash & scenari (2)'!F7))="",0,IF(DATE(2027,3,1)=DATE(2026,10,1),IF('Model inputs'!O46="","",'Model inputs'!O46),IF('NeatRescue — Cash & scenari (2)'!F7="","",'NeatRescue — Cash & scenari (2)'!F7)))+'Model inputs'!I43 -> 2100 | H7: =IF(IF(DATE(2027,4,1)=DATE(2026,10,1),IF('Model inputs'!O46="","",'Model inputs'!O46),IF('NeatRescue — Cash & scenari (2)'!G7="","",'NeatRescue — Cash & scenari (2)'!G7))="",0,IF(DATE(2027,4,1)=DATE(2026,10,1),IF('Model inputs'!O46="","",'Model inputs'!O46),IF('NeatRescue — Cash & scenari (2)'!G7="","",'NeatRescue — Cash & scenari (2)'!G7)))+'Model inputs'!J43 -> 1650 | I7: =IF(IF(DATE(2027,5,1)=DATE(2026,10,1),IF('Model inputs'!O46="","",'Model inputs'!O46),IF('NeatRescue — Cash & scenari (2)'!H7="","",'NeatRescue — Cash & scenari (2)'!H7))="",0,IF(DATE(2027,5,1)=DATE(2026,10,1),IF('Model inputs'!O46="","",'Model inputs'!O46),IF('NeatRescue — Cash & scenari (2)'!H7="","",'NeatRescue — Cash & scenari (2)'!H7)))+'Model inputs'!K43 -> 1200 | J7: =IF(IF(DATE(2027,6,1)=DATE(2026,10,1),IF('Model inputs'!O46="","",'Model inputs'!O46),IF('NeatRescue — Cash & scenari (2)'!I7="","",'NeatRescue — Cash & scenari (2)'!I7))="",0,IF(DATE(2027,6,1)=DATE(2026,10,1),IF('Model inputs'!O46="","",'Model inputs'!O46),IF('NeatRescue — Cash & scenari (2)'!I7="","",'NeatRescue — Cash & scenari (2)'!I7)))+'Model inputs'!L43 -> 750 | K7: =IF(IF(DATE(2027,7,1)=DATE(2026,10,1),IF('Model inputs'!O46="","",'Model inputs'!O46),IF('NeatRescue — Cash & scenari (2)'!J7="","",'NeatRescue — Cash & scenari (2)'!J7))="",0,IF(DATE(2027,7,1)=DATE(2026,10,1),IF('Model inputs'!O46="","",'Model inputs'!O46),IF('NeatRescue — Cash & scenari (2)'!J7="","",'NeatRescue — Cash & scenari (2)'!J7)))+'Model inputs'!M43 -> 300 | L7: =IF(IF(DATE(2027,8,1)=DATE(2026,10,1),IF('Model inputs'!O46="","",'Model inputs'!O46),IF('NeatRescue — Cash & scenari (2)'!K7="","",'NeatRescue — Cash & scenari (2)'!K7))="",0,IF(DATE(2027,8,1)=DATE(2026,10,1),IF('Model inputs'!O46="","",'Model inputs'!O46),IF('NeatRescue — Cash & scenari (2)'!K7="","",'NeatRescue — Cash & scenari (2)'!K7)))+'Model inputs'!N43 -> -150 | M7: =IF(IF(DATE(2027,9,1)=DATE(2026,10,1),IF('Model inputs'!O46="","",'Model inputs'!O46),IF('NeatRescue — Cash & scenari (2)'!L7="","",'NeatRescue — Cash & scenari (2)'!L7))="",0,IF(DATE(2027,9,1)=DATE(2026,10,1),IF('Model inputs'!O46="","",'Model inputs'!O46),IF('NeatRescue — Cash & scenari (2)'!L7="","",'NeatRescue — Cash & scenari (2)'!L7)))+'Model inputs'!B43 -> -600
A8: Monthly burn | B8: =MAX(-'NeatRescue — Cash & scenarios ·'!B15,0) -> 427.43 | C8: =MAX(-'NeatRescue — Cash & scenarios ·'!C15,0) -> 0 | D8: =MAX(-'NeatRescue — Cash & scenarios ·'!D15,0) -> 0 | E8: =MAX(-'NeatRescue — Cash & scenarios ·'!E15,0) -> 0 | F8: =MAX(-'NeatRescue — Cash & scenarios ·'!F15,0) -> 0 | G8: =MAX(-'NeatRescue — Cash & scenarios ·'!G15,0) -> 0 | H8: =MAX(-'NeatRescue — Cash & scenarios ·'!H15,0) -> 0 | I8: =MAX(-'NeatRescue — Cash & scenarios ·'!I15,0) -> 0 | ... M8: =MAX(-'NeatRescue — Cash & scenarios ·'!M15,0) -> 0
A9: Monthly burn > Bootstrap $5,000 — hypothetical | B9: =MAX(-'Model inputs'!D44,0) -> 427.43 | C9: =MAX(-'Model inputs'!E44,0) -> 0 | D9: =MAX(-'Model inputs'!F44,0) -> 0 | E9: =MAX(-'Model inputs'!G44,0) -> 0 | F9: =MAX(-'Model inputs'!H44,0) -> 0 | G9: =MAX(-'Model inputs'!I44,0) -> 0 | H9: =MAX(-'Model inputs'!J44,0) -> 0 | I9: =MAX(-'Model inputs'!K44,0) -> 0 | ... L9: =MAX(-'Model inputs'!N44,0) -> 0 | M9: =MAX(-'Model inputs'!B44,0) -> 0
A10: Monthly burn > Bootstrap no-sales stress — hypothetical | B10: =MAX(-'Model inputs'!D43,0) -> 650 | C10: =MAX(-'Model inputs'!E43,0) -> 450 | D10: =MAX(-'Model inputs'!F43,0) -> 450 | E10: =MAX(-'Model inputs'!G43,0) -> 450 | F10: =MAX(-'Model inputs'!H43,0) -> 450 | G10: =MAX(-'Model inputs'!I43,0) -> 450 | H10: =MAX(-'Model inputs'!J43,0) -> 450 | I10: =MAX(-'Model inputs'!K43,0) -> 450 | ... L10: =MAX(-'Model inputs'!N43,0) -> 450 | M10: =MAX(-'Model inputs'!B43,0) -> 450

Sheet NeatRescue — Sensitivity · Sens
A1: NeatRescue — Sensitivity · Sensitivity capital assumption
A2: Financial model (5 pages) · Main Scenario
A4: Variable / dimension | B4: Value
A5: Sensitivity bootstrap cash | B5: =5000 -> 5000

Sheet NeatRescue — Sensitivity · Infe
A1: NeatRescue — Sensitivity · Inference cost × churn sensitivity — hypothetical
A2: Financial model (5 pages) · Main Scenario
A4: Variable / dimension | B4: Sensitivity inference cost | C4: Sensitivity churn | D4: Sensitivity month 12 customers | E4: Sensitivity month 12 revenue | F4: Sensitivity month 12 gross margin | G4: Sensitivity month 12 operating profit | H4: Sensitivity 12-month operating profit | I4: Sensitivity month 12 bootstrap cash
A5: Inference $0.025 / churn 10% | B5: =0.025 -> 0.025 | C5: =0.1 -> 0.1 | D5: ='Model inputs'!P86*('NeatRescue — Assumptions & (2)'!G5+'NeatRescue — Assumptions & (2)'!G6) -> 42.839983 | E5: ='Model inputs'!P86*('NeatRescue — Assumptions & (2)'!G5*('NeatRescue — Assumptions & (2)'!B5+MAX('NeatRescue — Assumptions & (2)'!D5-'NeatRescue — Assumptions & (2)'!C5,0)*'NeatRescue — Assumptions & (2)'!E5)+'NeatRescue — Assumptions & (2)'!G6*('NeatRescue — Assumptions & (2)'!B6+MAX('NeatRescue — Assumptions & (2)'!D6-'NeatRescue — Assumptions & (2)'!C6,0)*'NeatRescue — Assumptions & (2)'!E6)) -> 4583.8781 | F5: =IFERROR(('Model inputs'!P86*('NeatRescue — Assumptions & (2)'!G5*(('NeatRescue — Assumptions & (2)'!B5+MAX('NeatRescue — Assumptions & (2)'!D5-'NeatRescue — Assumptions & (2)'!C5,0)*'NeatRescue — Assumptions & (2)'!E5)*(1-'NeatRescue — Assumptions & simu'!B18)-'NeatRescue — Assumptions & (2)'!D5*('NeatRescue — Sensitivity · Infe'!B5+'NeatRescue — Assumptions & simu'!B8+'NeatRescue — Assumptions & simu'!B9)-'NeatRescue — Assumptions & (2)'!F5)+'NeatRescue — Assumptions & (2)'!G6*(('NeatRescue — Assumptions & (2)'!B6+MAX('NeatRescue — Assumptions & (2)'!D6-'NeatRescue — Assumptions & (2)'!C6,0)*'NeatRescue — Assumptions & (2)'!E6)*(1-'NeatRescue — Assumptions & simu'!B18)-'NeatRescue — Assumptions & (2)'!D6*('NeatRescue — Sensitivity · Infe'!B5+'NeatRescue — Assumptions & simu'!B8+'NeatRescue — Assumptions & simu'!B9)-'NeatRescue — Assumptions & (2)'!F6))-('NeatRescue — Assumptions & simu'!B10+'NeatRescue — Assumptions & simu'!B11+'NeatRescue — Assumptions & simu'!B12+'NeatRescue — Assumptions & simu'!B14))/'NeatRescue — Sensitivity · Infe'!E5,"") -> 0.7252763 | G5: ='Model inputs'!P86*('NeatRescue — Assumptions & (2)'!G5*(('NeatRescue — Assumptions & (2)'!B5+MAX('NeatRescue — Assumptions & (2)'!D5-'NeatRescue — Assumptions & (2)'!C5,0)*'NeatRescue — Assumptions & (2)'!E5)*(1-'NeatRescue — Assumptions & simu'!B18)-'NeatRescue — Assumptions & (2)'!D5*('NeatRescue — Sensitivity · Infe'!B5+'NeatRescue — Assumptions & simu'!B8+'NeatRescue — Assumptions & simu'!B9)-'NeatRescue — Assumptions & (2)'!F5)+'NeatRescue — Assumptions & (2)'!G6*(('NeatRescue — Assumptions & (2)'!B6+MAX('NeatRescue — Assumptions & (2)'!D6-'NeatRescue — Assumptions & (2)'!C6,0)*'NeatRescue — Assumptions & (2)'!E6)*(1-'NeatRescue — Assumptions & simu'!B18)-'NeatRescue — Assumptions & (2)'!D6*('NeatRescue — Sensitivity · Infe'!B5+'NeatRescue — Assumptions & simu'!B8+'NeatRescue — Assumptions & simu'!B9)-'NeatRescue — Assumptions & (2)'!F6))-('NeatRescue — Assumptions & simu'!B10+'NeatRescue — Assumptions & simu'!B11+'NeatRescue — Assumptions & simu'!B12+'NeatRescue — Assumptions & simu'!B14+'NeatRescue — Assumptions & simu'!B13+'NeatRescue — Assumptions & simu'!B15+'NeatRescue — Assumptions & simu'!B19) -> 3099.5782 | H5: ='Model inputs'!P73*('NeatRescue — Assumptions & (2)'!G5*(('NeatRescue — Assumptions & (2)'!B5+MAX('NeatRescue — Assumptions & (2)'!D5-'NeatRescue — Assumptions & (2)'!C5,0)*'NeatRescue — Assumptions & (2)'!E5)*(1-'NeatRescue — Assumptions & simu'!B18)-'NeatRescue — Assumptions & (2)'!D5*('NeatRescue — Sensitivity · Infe'!B5+'NeatRescue — Assumptions & simu'!B8+'NeatRescue — Assumptions & simu'!B9)-'NeatRescue — Assumptions & (2)'!F5)+'NeatRescue — Assumptions & (2)'!G6*(('NeatRescue — Assumptions & (2)'!B6+MAX('NeatRescue — Assumptions & (2)'!D6-'NeatRescue — Assumptions & (2)'!C6,0)*'NeatRescue — Assumptions & (2)'!E6)*(1-'NeatRescue — Assumptions & simu'!B18)-'NeatRescue — Assumptions & (2)'!D6*('NeatRescue — Sensitivity · Infe'!B5+'NeatRescue — Assumptions & simu'!B8+'NeatRescue — Assumptions & simu'!B9)-'NeatRescue — Assumptions & (2)'!F6))-12*('NeatRescue — Assumptions & simu'!B10+'NeatRescue — Assumptions & simu'!B11+'NeatRescue — Assumptions & simu'!B12+'NeatRescue — Assumptions & simu'!B14+'NeatRescue — Assumptions & simu'!B13+'NeatRescue — Assumptions & simu'!B15+'NeatRescue — Assumptions & simu'!B19)-'NeatRescue — Assumptions & simu'!B16 -> 15608.711 | I5: ='NeatRescue — Sensitivity · Sens'!B5+'NeatRescue — Sensitivity · Infe'!H5 -> 20608.711
A6: Inference $0.025 / churn 2% | B6: =0.025 -> 0.025 | C6: =0.02 -> 0.02 | D6: ='Model inputs'!P87*('NeatRescue — Assumptions & (2)'!G5+'NeatRescue — Assumptions & (2)'!G6) -> 58.842791 | E6: ='Model inputs'!P87*('NeatRescue — Assumptions & (2)'!G5*('NeatRescue — Assumptions & (2)'!B5+MAX('NeatRescue — Assumptions & (2)'!D5-'NeatRescue — Assumptions & (2)'!C5,0)*'NeatRescue — Assumptions & (2)'!E5)+'NeatRescue — Assumptions & (2)'!G6*('NeatRescue — Assumptions & (2)'!B6+MAX('NeatRescue — Assumptions & (2)'!D6-'NeatRescue — Assumptions & (2)'!C6,0)*'NeatRescue — Assumptions & (2)'!E6)) -> 6296.1787 | F6: =IFERROR(('Model inputs'!P87*('NeatRescue — Assumptions & (2)'!G5*(('NeatRescue — Assumptions & (2)'!B5+MAX('NeatRescue — Assumptions & (2)'!D5-'NeatRescue — Assumptions & (2)'!C5,0)*'NeatRescue — Assumptions & (2)'!E5)*(1-'NeatRescue — Assumptions & simu'!B18)-'NeatRescue — Assumptions & (2)'!D5*('NeatRescue — Sensitivity · Infe'!B6+'NeatRescue — Assumptions & simu'!B8+'NeatRescue — Assumptions & simu'!B9)-'NeatRescue — Assumptions & (2)'!F5)+'NeatRescue — Assumptions & (2)'!G6*(('NeatRescue — Assumptions & (2)'!B6+MAX('NeatRescue — Assumptions & (2)'!D6-'NeatRescue — Assumptions & (2)'!C6,0)*'NeatRescue — Assumptions & (2)'!E6)*(1-'NeatRescue — Assumptions & simu'!B18)-'NeatRescue — Assumptions & (2)'!D6*('NeatRescue — Sensitivity · Infe'!B6+'NeatRescue — Assumptions & simu'!B8+'NeatRescue — Assumptions & simu'!B9)-'NeatRescue — Assumptions & (2)'!F6))-('NeatRescue — Assumptions & simu'!B10+'NeatRescue — Assumptions & simu'!B11+'NeatRescue — Assumptions & simu'!B12+'NeatRescue — Assumptions & simu'!B14))/'NeatRescue — Sensitivity · Infe'!E6,"") -> 0.73862541 | G6: ='Model inputs'!P87*('NeatRescue — Assumptions & (2)'!G5*(('NeatRescue — Assumptions & (2)'!B5+MAX('NeatRescue — Assumptions & (2)'!D5-'NeatRescue — Assumptions & (2)'!C5,0)*'NeatRescue — Assumptions & (2)'!E5)*(1-'NeatRescue — Assumptions & simu'!B18)-'NeatRescue — Assumptions & (2)'!D5*('NeatRescue — Sensitivity · Infe'!B6+'NeatRescue — Assumptions & simu'!B8+'NeatRescue — Assumptions & simu'!B9)-'NeatRescue — Assumptions & (2)'!F5)+'NeatRescue — Assumptions & (2)'!G6*(('NeatRescue — Assumptions & (2)'!B6+MAX('NeatRescue — Assumptions & (2)'!D6-'NeatRescue — Assumptions & (2)'!C6,0)*'NeatRescue — Assumptions & (2)'!E6)*(1-'NeatRescue — Assumptions & simu'!B18)-'NeatRescue — Assumptions & (2)'!D6*('NeatRescue — Sensitivity · Infe'!B6+'NeatRescue — Assumptions & simu'!B8+'NeatRescue — Assumptions & simu'!B9)-'NeatRescue — Assumptions & (2)'!F6))-('NeatRescue — Assumptions & simu'!B10+'NeatRescue — Assumptions & simu'!B11+'NeatRescue — Assumptions & simu'!B12+'NeatRescue — Assumptions & simu'!B14+'NeatRescue — Assumptions & simu'!B13+'NeatRescue — Assumptions & simu'!B15+'NeatRescue — Assumptions & simu'!B19) -> 4425.5175 | H6: ='Model inputs'!P74*('NeatRescue — Assumptions & (2)'!G5*(('NeatRescue — Assumptions & (2)'!B5+MAX('NeatRescue — Assumptions & (2)'!D5-'NeatRescue — Assumptions & (2)'!C5,0)*'NeatRescue — Assumptions & (2)'!E5)*(1-'NeatRescue — Assumptions & simu'!B18)-'NeatRescue — Assumptions & (2)'!D5*('NeatRescue — Sensitivity · Infe'!B6+'NeatRescue — Assumptions & simu'!B8+'NeatRescue — Assumptions & simu'!B9)-'NeatRescue — Assumptions & (2)'!F5)+'NeatRescue — Assumptions & (2)'!G6*(('NeatRescue — Assumptions & (2)'!B6+MAX('NeatRescue — Assumptions & (2)'!D6-'NeatRescue — Assumptions & (2)'!C6,0)*'NeatRescue — Assumptions & (2)'!E6)*(1-'NeatRescue — Assumptions & simu'!B18)-'NeatRescue — Assumptions & (2)'!D6*('NeatRescue — Sensitivity · Infe'!B6+'NeatRescue — Assumptions & simu'!B8+'NeatRescue — Assumptions & simu'!B9)-'NeatRescue — Assumptions & (2)'!F6))-12*('NeatRescue — Assumptions & simu'!B10+'NeatRescue — Assumptions & simu'!B11+'NeatRescue — Assumptions & simu'!B12+'NeatRescue — Assumptions & simu'!B14+'NeatRescue — Assumptions & simu'!B13+'NeatRescue — Assumptions & simu'!B15+'NeatRescue — Assumptions & simu'!B19)-'NeatRescue — Assumptions & simu'!B16 -> 21274.211 | I6: ='NeatRescue — Sensitivity · Sens'!B5+'NeatRescue — Sensitivity · Infe'!H6 -> 26274.211
A7: Inference $0.025 / churn 5% | B7: =0.025 -> 0.025 | C7: =0.05 -> 0.05 | D7: ='Model inputs'!P88*('NeatRescue — Assumptions & (2)'!G5+'NeatRescue — Assumptions & (2)'!G6) -> 51.961366 | E7: ='Model inputs'!P88*('NeatRescue — Assumptions & (2)'!G5*('NeatRescue — Assumptions & (2)'!B5+MAX('NeatRescue — Assumptions & (2)'!D5-'NeatRescue — Assumptions & (2)'!C5,0)*'NeatRescue — Assumptions & (2)'!E5)+'NeatRescue — Assumptions & (2)'!G6*('NeatRescue — Assumptions & (2)'!B6+MAX('NeatRescue — Assumptions & (2)'!D6-'NeatRescue — Assumptions & (2)'!C6,0)*'NeatRescue — Assumptions & (2)'!E6)) -> 5559.8661 | F7: =IFERROR(('Model inputs'!P88*('NeatRescue — Assumptions & (2)'!G5*(('NeatRescue — Assumptions & (2)'!B5+MAX('NeatRescue — Assumptions & (2)'!D5-'NeatRescue — Assumptions & (2)'!C5,0)*'NeatRescue — Assumptions & (2)'!E5)*(1-'NeatRescue — Assumptions & simu'!B18)-'NeatRescue — Assumptions & (2)'!D5*('NeatRescue — Sensitivity · Infe'!B7+'NeatRescue — Assumptions & simu'!B8+'NeatRescue — Assumptions & simu'!B9)-'NeatRescue — Assumptions & (2)'!F5)+'NeatRescue — Assumptions & (2)'!G6*(('NeatRescue — Assumptions & (2)'!B6+MAX('NeatRescue — Assumptions & (2)'!D6-'NeatRescue — Assumptions & (2)'!C6,0)*'NeatRescue — Assumptions & (2)'!E6)*(1-'NeatRescue — Assumptions & simu'!B18)-'NeatRescue — Assumptions & (2)'!D6*('NeatRescue — Sensitivity · Infe'!B7+'NeatRescue — Assumptions & simu'!B8+'NeatRescue — Assumptions & simu'!B9)-'NeatRescue — Assumptions & (2)'!F6))-('NeatRescue — Assumptions & simu'!B10+'NeatRescue — Assumptions & simu'!B11+'NeatRescue — Assumptions & simu'!B12+'NeatRescue — Assumptions & simu'!B14))/'NeatRescue — Sensitivity · Infe'!E7,"") -> 0.73389277 | G7: ='Model inputs'!P88*('NeatRescue — Assumptions & (2)'!G5*(('NeatRescue — Assumptions & (2)'!B5+MAX('NeatRescue — Assumptions & (2)'!D5-'NeatRescue — Assumptions & (2)'!C5,0)*'NeatRescue — Assumptions & (2)'!E5)*(1-'NeatRescue — Assumptions & simu'!B18)-'NeatRescue — Assumptions & (2)'!D5*('NeatRescue — Sensitivity · Infe'!B7+'NeatRescue — Assumptions & simu'!B8+'NeatRescue — Assumptions & simu'!B9)-'NeatRescue — Assumptions & (2)'!F5)+'NeatRescue — Assumptions & (2)'!G6*(('NeatRescue — Assumptions & (2)'!B6+MAX('NeatRescue — Assumptions & (2)'!D6-'NeatRescue — Assumptions & (2)'!C6,0)*'NeatRescue — Assumptions & (2)'!E6)*(1-'NeatRescue — Assumptions & simu'!B18)-'NeatRescue — Assumptions & (2)'!D6*('NeatRescue — Sensitivity · Infe'!B7+'NeatRescue — Assumptions & simu'!B8+'NeatRescue — Assumptions & simu'!B9)-'NeatRescue — Assumptions & (2)'!F6))-('NeatRescue — Assumptions & simu'!B10+'NeatRescue — Assumptions & simu'!B11+'NeatRescue — Assumptions & simu'!B12+'NeatRescue — Assumptions & simu'!B14+'NeatRescue — Assumptions & simu'!B13+'NeatRescue — Assumptions & simu'!B15+'NeatRescue — Assumptions & simu'!B19) -> 3855.3456 | H7: ='Model inputs'!P75*('NeatRescue — Assumptions & (2)'!G5*(('NeatRescue — Assumptions & (2)'!B5+MAX('NeatRescue — Assumptions & (2)'!D5-'NeatRescue — Assumptions & (2)'!C5,0)*'NeatRescue — Assumptions & (2)'!E5)*(1-'NeatRescue — Assumptions & simu'!B18)-'NeatRescue — Assumptions & (2)'!D5*('NeatRescue — Sensitivity · Infe'!B7+'NeatRescue — Assumptions & simu'!B8+'NeatRescue — Assumptions & simu'!B9)-'NeatRescue — Assumptions & (2)'!F5)+'NeatRescue — Assumptions & (2)'!G6*(('NeatRescue — Assumptions & (2)'!B6+MAX('NeatRescue — Assumptions & (2)'!D6-'NeatRescue — Assumptions & (2)'!C6,0)*'NeatRescue — Assumptions & (2)'!E6)*(1-'NeatRescue — Assumptions & simu'!B18)-'NeatRescue — Assumptions & (2)'!D6*('NeatRescue — Sensitivity · Infe'!B7+'NeatRescue — Assumptions & simu'!B8+'NeatRescue — Assumptions & simu'!B9)-'NeatRescue — Assumptions & (2)'!F6))-12*('NeatRescue — Assumptions & simu'!B10+'NeatRescue — Assumptions & simu'!B11+'NeatRescue — Assumptions & simu'!B12+'NeatRescue — Assumptions & simu'!B14+'NeatRescue — Assumptions & simu'!B13+'NeatRescue — Assumptions & simu'!B15+'NeatRescue — Assumptions & simu'!B19)-'NeatRescue — Assumptions & simu'!B16 -> 18908.263 | I7: ='NeatRescue — Sensitivity · Sens'!B5+'NeatRescue — Sensitivity · Infe'!H7 -> 23908.263
A8: Inference $0.050 / churn 10% | B8: =0.05 -> 0.05 | C8: =0.1 -> 0.1 | D8: ='Model inputs'!P89*('NeatRescue — Assumptions & (2)'!G5+'NeatRescue — Assumptions & (2)'!G6) -> 42.839983 | E8: ='Model inputs'!P89*('NeatRescue — Assumptions & (2)'!G5*('NeatRescue — Assumptions & (2)'!B5+MAX('NeatRescue — Assumptions & (2)'!D5-'NeatRescue — Assumptions & (2)'!C5,0)*'NeatRescue — Assumptions & (2)'!E5)+'NeatRescue — Assumptions & (2)'!G6*('NeatRescue — Assumptions & (2)'!B6+MAX('NeatRescue — Assumptions & (2)'!D6-'NeatRescue — Assumptions & (2)'!C6,0)*'NeatRescue — Assumptions & (2)'!E6)) -> 4583.8781 | F8: =IFERROR(('Model inputs'!P89*('NeatRescue — Assumptions & (2)'!G5*(('NeatRescue — Assumptions & (2)'!B5+MAX('NeatRescue — Assumptions & (2)'!D5-'NeatRescue — Assumptions & (2)'!C5,0)*'NeatRescue — Assumptions & (2)'!E5)*(1-'NeatRescue — Assumptions & simu'!B18)-'NeatRescue — Assumptions & (2)'!D5*('NeatRescue — Sensitivity · Infe'!B8+'NeatRescue — Assumptions & simu'!B8+'NeatRescue — Assumptions & simu'!B9)-'NeatRescue — Assumptions & (2)'!F5)+'NeatRescue — Assumptions & (2)'!G6*(('NeatRescue — Assumptions & (2)'!B6+MAX('NeatRescue — Assumptions & (2)'!D6-'NeatRescue — Assumptions & (2)'!C6,0)*'NeatRescue — Assumptions & (2)'!E6)*(1-'NeatRescue — Assumptions & simu'!B18)-'NeatRescue — Assumptions & (2)'!D6*('NeatRescue — Sensitivity · Infe'!B8+'NeatRescue — Assumptions & simu'!B8+'NeatRescue — Assumptions & simu'!B9)-'NeatRescue — Assumptions & (2)'!F6))-('NeatRescue — Assumptions & simu'!B10+'NeatRescue — Assumptions & simu'!B11+'NeatRescue — Assumptions & simu'!B12+'NeatRescue — Assumptions & simu'!B14))/'NeatRescue — Sensitivity · Infe'!E8,"") -> 0.64427941 | G8: ='Model inputs'!P89*('NeatRescue — Assumptions & (2)'!G5*(('NeatRescue — Assumptions & (2)'!B5+MAX('NeatRescue — Assumptions & (2)'!D5-'NeatRescue — Assumptions & (2)'!C5,0)*'NeatRescue — Assumptions & (2)'!E5)*(1-'NeatRescue — Assumptions & simu'!B18)-'NeatRescue — Assumptions & (2)'!D5*('NeatRescue — Sensitivity · Infe'!B8+'NeatRescue — Assumptions & simu'!B8+'NeatRescue — Assumptions & simu'!B9)-'NeatRescue — Assumptions & (2)'!F5)+'NeatRescue — Assumptions & (2)'!G6*(('NeatRescue — Assumptions & (2)'!B6+MAX('NeatRescue — Assumptions & (2)'!D6-'NeatRescue — Assumptions & (2)'!C6,0)*'NeatRescue — Assumptions & (2)'!E6)*(1-'NeatRescue — Assumptions & simu'!B18)-'NeatRescue — Assumptions & (2)'!D6*('NeatRescue — Sensitivity · Infe'!B8+'NeatRescue — Assumptions & simu'!B8+'NeatRescue — Assumptions & simu'!B9)-'NeatRescue — Assumptions & (2)'!F6))-('NeatRescue — Assumptions & simu'!B10+'NeatRescue — Assumptions & simu'!B11+'NeatRescue — Assumptions & simu'!B12+'NeatRescue — Assumptions & simu'!B14+'NeatRescue — Assumptions & simu'!B13+'NeatRescue — Assumptions & simu'!B15+'NeatRescue — Assumptions & simu'!B19) -> 2728.2983 | H8: ='Model inputs'!P76*('NeatRescue — Assumptions & (2)'!G5*(('NeatRescue — Assumptions & (2)'!B5+MAX('NeatRescue — Assumptions & (2)'!D5-'NeatRescue — Assumptions & (2)'!C5,0)*'NeatRescue — Assumptions & (2)'!E5)*(1-'NeatRescue — Assumptions & simu'!B18)-'NeatRescue — Assumptions & (2)'!D5*('NeatRescue — Sensitivity · Infe'!B8+'NeatRescue — Assumptions & simu'!B8+'NeatRescue — Assumptions & simu'!B9)-'NeatRescue — Assumptions & (2)'!F5)+'NeatRescue — Assumptions & (2)'!G6*(('NeatRescue — Assumptions & (2)'!B6+MAX('NeatRescue — Assumptions & (2)'!D6-'NeatRescue — Assumptions & (2)'!C6,0)*'NeatRescue — Assumptions & (2)'!E6)*(1-'NeatRescue — Assumptions & simu'!B18)-'NeatRescue — Assumptions & (2)'!D6*('NeatRescue — Sensitivity · Infe'!B8+'NeatRescue — Assumptions & simu'!B8+'NeatRescue — Assumptions & simu'!B9)-'NeatRescue — Assumptions & (2)'!F6))-12*('NeatRescue — Assumptions & simu'!B10+'NeatRescue — Assumptions & simu'!B11+'NeatRescue — Assumptions & simu'!B12+'NeatRescue — Assumptions & simu'!B14+'NeatRescue — Assumptions & simu'!B13+'NeatRescue — Assumptions & simu'!B15+'NeatRescue — Assumptions & simu'!B19)-'NeatRescue — Assumptions & simu'!B16 -> 13390.316 | I8: ='NeatRescue — Sensitivity · Sens'!B5+'NeatRescue — Sensitivity · Infe'!H8 -> 18390.316
A9: Inference $0.050 / churn 2% | B9: =0.05 -> 0.05 | C9: =0.02 -> 0.02 | D9: ='Model inputs'!P90*('NeatRescue — Assumptions & (2)'!G5+'NeatRescue — Assumptions & (2)'!G6) -> 58.842791 | E9: ='Model inputs'!P90*('NeatRescue — Assumptions & (2)'!G5*('NeatRescue — Assumptions & (2)'!B5+MAX('NeatRescue — Assumptions & (2)'!D5-'NeatRescue — Assumptions & (2)'!C5,0)*'NeatRescue — Assumptions & (2)'!E5)+'NeatRescue — Assumptions & (2)'!G6*('NeatRescue — Assumptions & (2)'!B6+MAX('NeatRescue — Assumptions & (2)'!D6-'NeatRescue — Assumptions & (2)'!C6,0)*'NeatRescue — Assumptions & (2)'!E6)) -> 6296.1787 | F9: =IFERROR(('Model inputs'!P90*('NeatRescue — Assumptions & (2)'!G5*(('NeatRescue — Assumptions & (2)'!B5+MAX('NeatRescue — Assumptions & (2)'!D5-'NeatRescue — Assumptions & (2)'!C5,0)*'NeatRescue — Assumptions & (2)'!E5)*(1-'NeatRescue — Assumptions & simu'!B18)-'NeatRescue — Assumptions & (2)'!D5*('NeatRescue — Sensitivity · Infe'!B9+'NeatRescue — Assumptions & simu'!B8+'NeatRescue — Assumptions & simu'!B9)-'NeatRescue — Assumptions & (2)'!F5)+'NeatRescue — Assumptions & (2)'!G6*(('NeatRescue — Assumptions & (2)'!B6+MAX('NeatRescue — Assumptions & (2)'!D6-'NeatRescue — Assumptions & (2)'!C6,0)*'NeatRescue — Assumptions & (2)'!E6)*(1-'NeatRescue — Assumptions & simu'!B18)-'NeatRescue — Assumptions & (2)'!D6*('NeatRescue — Sensitivity · Infe'!B9+'NeatRescue — Assumptions & simu'!B8+'NeatRescue — Assumptions & simu'!B9)-'NeatRescue — Assumptions & (2)'!F6))-('NeatRescue — Assumptions & simu'!B10+'NeatRescue — Assumptions & simu'!B11+'NeatRescue — Assumptions & simu'!B12+'NeatRescue — Assumptions & simu'!B14))/'NeatRescue — Sensitivity · Infe'!E9,"") -> 0.65762852 | G9: ='Model inputs'!P90*('NeatRescue — Assumptions & (2)'!G5*(('NeatRescue — Assumptions & (2)'!B5+MAX('NeatRescue — Assumptions & (2)'!D5-'NeatRescue — Assumptions & (2)'!C5,0)*'NeatRescue — Assumptions & (2)'!E5)*(1-'NeatRescue — Assumptions & simu'!B18)-'NeatRescue — Assumptions & (2)'!D5*('NeatRescue — Sensitivity · Infe'!B9+'NeatRescue — Assumptions & simu'!B8+'NeatRescue — Assumptions & simu'!B9)-'NeatRescue — Assumptions & (2)'!F5)+'NeatRescue — Assumptions & (2)'!G6*(('NeatRescue — Assumptions & (2)'!B6+MAX('NeatRescue — Assumptions & (2)'!D6-'NeatRescue — Assumptions & (2)'!C6,0)*'NeatRescue — Assumptions & (2)'!E6)*(1-'NeatRescue — Assumptions & simu'!B18)-'NeatRescue — Assumptions & (2)'!D6*('NeatRescue — Sensitivity · Infe'!B9+'NeatRescue — Assumptions & simu'!B8+'NeatRescue — Assumptions & simu'!B9)-'NeatRescue — Assumptions & (2)'!F6))-('NeatRescue — Assumptions & simu'!B10+'NeatRescue — Assumptions & simu'!B11+'NeatRescue — Assumptions & simu'!B12+'NeatRescue — Assumptions & simu'!B14+'NeatRescue — Assumptions & simu'!B13+'NeatRescue — Assumptions & simu'!B15+'NeatRescue — Assumptions & simu'!B19) -> 3915.5467 | H9: ='Model inputs'!P77*('NeatRescue — Assumptions & (2)'!G5*(('NeatRescue — Assumptions & (2)'!B5+MAX('NeatRescue — Assumptions & (2)'!D5-'NeatRescue — Assumptions & (2)'!C5,0)*'NeatRescue — Assumptions & (2)'!E5)*(1-'NeatRescue — Assumptions & simu'!B18)-'NeatRescue — Assumptions & (2)'!D5*('NeatRescue — Sensitivity · Infe'!B9+'NeatRescue — Assumptions & simu'!B8+'NeatRescue — Assumptions & simu'!B9)-'NeatRescue — Assumptions & (2)'!F5)+'NeatRescue — Assumptions & (2)'!G6*(('NeatRescue — Assumptions & (2)'!B6+MAX('NeatRescue — Assumptions & (2)'!D6-'NeatRescue — Assumptions & (2)'!C6,0)*'NeatRescue — Assumptions & (2)'!E6)*(1-'NeatRescue — Assumptions & simu'!B18)-'NeatRescue — Assumptions & (2)'!D6*('NeatRescue — Sensitivity · Infe'!B9+'NeatRescue — Assumptions & simu'!B8+'NeatRescue — Assumptions & simu'!B9)-'NeatRescue — Assumptions & (2)'!F6))-12*('NeatRescue — Assumptions & simu'!B10+'NeatRescue — Assumptions & simu'!B11+'NeatRescue — Assumptions & simu'!B12+'NeatRescue — Assumptions & simu'!B14+'NeatRescue — Assumptions & simu'!B13+'NeatRescue — Assumptions & simu'!B15+'NeatRescue — Assumptions & simu'!B19)-'NeatRescue — Assumptions & simu'!B16 -> 18463.214 | I9: ='NeatRescue — Sensitivity · Sens'!B5+'NeatRescue — Sensitivity · Infe'!H9 -> 23463.214
A10: Inference $0.050 / churn 5% | B10: =0.05 -> 0.05 | C10: =0.05 -> 0.05 | D10: ='Model inputs'!P91*('NeatRescue — Assumptions & (2)'!G5+'NeatRescue — Assumptions & (2)'!G6) -> 51.961366 | E10: ='Model inputs'!P91*('NeatRescue — Assumptions & (2)'!G5*('NeatRescue — Assumptions & (2)'!B5+MAX('NeatRescue — Assumptions & (2)'!D5-'NeatRescue — Assumptions & (2)'!C5,0)*'NeatRescue — Assumptions & (2)'!E5)+'NeatRescue — Assumptions & (2)'!G6*('NeatRescue — Assumptions & (2)'!B6+MAX('NeatRescue — Assumptions & (2)'!D6-'NeatRescue — Assumptions & (2)'!C6,0)*'NeatRescue — Assumptions & (2)'!E6)) -> 5559.8661 | F10: =IFERROR(('Model inputs'!P91*('NeatRescue — Assumptions & (2)'!G5*(('NeatRescue — Assumptions & (2)'!B5+MAX('NeatRescue — Assumptions & (2)'!D5-'NeatRescue — Assumptions & (2)'!C5,0)*'NeatRescue — Assumptions & (2)'!E5)*(1-'NeatRescue — Assumptions & simu'!B18)-'NeatRescue — Assumptions & (2)'!D5*('NeatRescue — Sensitivity · Infe'!B10+'NeatRescue — Assumptions & simu'!B8+'NeatRescue — Assumptions & simu'!B9)-'NeatRescue — Assumptions & (2)'!F5)+'NeatRescue — Assumptions & (2)'!G6*(('NeatRescue — Assumptions & (2)'!B6+MAX('NeatRescue — Assumptions & (2)'!D6-'NeatRescue — Assumptions & (2)'!C6,0)*'NeatRescue — Assumptions & (2)'!E6)*(1-'NeatRescue — Assumptions & simu'!B18)-'NeatRescue — Assumptions & (2)'!D6*('NeatRescue — Sensitivity · Infe'!B10+'NeatRescue — Assumptions & simu'!B8+'NeatRescue — Assumptions & simu'!B9)-'NeatRescue — Assumptions & (2)'!F6))-('NeatRescue — Assumptions & simu'!B10+'NeatRescue — Assumptions & simu'!B11+'NeatRescue — Assumptions & simu'!B12+'NeatRescue — Assumptions & simu'!B14))/'NeatRescue — Sensitivity · Infe'!E10,"") -> 0.65289589 | G10: ='Model inputs'!P91*('NeatRescue — Assumptions & (2)'!G5*(('NeatRescue — Assumptions & (2)'!B5+MAX('NeatRescue — Assumptions & (2)'!D5-'NeatRescue — Assumptions & (2)'!C5,0)*'NeatRescue — Assumptions & (2)'!E5)*(1-'NeatRescue — Assumptions & simu'!B18)-'NeatRescue — Assumptions & (2)'!D5*('NeatRescue — Sensitivity · Infe'!B10+'NeatRescue — Assumptions & simu'!B8+'NeatRescue — Assumptions & simu'!B9)-'NeatRescue — Assumptions & (2)'!F5)+'NeatRescue — Assumptions & (2)'!G6*(('NeatRescue — Assumptions & (2)'!B6+MAX('NeatRescue — Assumptions & (2)'!D6-'NeatRescue — Assumptions & (2)'!C6,0)*'NeatRescue — Assumptions & (2)'!E6)*(1-'NeatRescue — Assumptions & simu'!B18)-'NeatRescue — Assumptions & (2)'!D6*('NeatRescue — Sensitivity · Infe'!B10+'NeatRescue — Assumptions & simu'!B8+'NeatRescue — Assumptions & simu'!B9)-'NeatRescue — Assumptions & (2)'!F6))-('NeatRescue — Assumptions & simu'!B10+'NeatRescue — Assumptions & simu'!B11+'NeatRescue — Assumptions & simu'!B12+'NeatRescue — Assumptions & simu'!B14+'NeatRescue — Assumptions & simu'!B13+'NeatRescue — Assumptions & simu'!B15+'NeatRescue — Assumptions & simu'!B19) -> 3405.0137 | H10: ='Model inputs'!P78*('NeatRescue — Assumptions & (2)'!G5*(('NeatRescue — Assumptions & (2)'!B5+MAX('NeatRescue — Assumptions & (2)'!D5-'NeatRescue — Assumptions & (2)'!C5,0)*'NeatRescue — Assumptions & (2)'!E5)*(1-'NeatRescue — Assumptions & simu'!B18)-'NeatRescue — Assumptions & (2)'!D5*('NeatRescue — Sensitivity · Infe'!B10+'NeatRescue — Assumptions & simu'!B8+'NeatRescue — Assumptions & simu'!B9)-'NeatRescue — Assumptions & (2)'!F5)+'NeatRescue — Assumptions & (2)'!G6*(('NeatRescue — Assumptions & (2)'!B6+MAX('NeatRescue — Assumptions & (2)'!D6-'NeatRescue — Assumptions & (2)'!C6,0)*'NeatRescue — Assumptions & (2)'!E6)*(1-'NeatRescue — Assumptions & simu'!B18)-'NeatRescue — Assumptions & (2)'!D6*('NeatRescue — Sensitivity · Infe'!B10+'NeatRescue — Assumptions & simu'!B8+'NeatRescue — Assumptions & simu'!B9)-'NeatRescue — Assumptions & (2)'!F6))-12*('NeatRescue — Assumptions & simu'!B10+'NeatRescue — Assumptions & simu'!B11+'NeatRescue — Assumptions & simu'!B12+'NeatRescue — Assumptions & simu'!B14+'NeatRescue — Assumptions & simu'!B13+'NeatRescue — Assumptions & simu'!B15+'NeatRescue — Assumptions & simu'!B19)-'NeatRescue — Assumptions & simu'!B16 -> 16344.74 | I10: ='NeatRescue — Sensitivity · Sens'!B5+'NeatRescue — Sensitivity · Infe'!H10 -> 21344.74
A11: Inference $0.150 / churn 10% | B11: =0.15 -> 0.15 | C11: =0.1 -> 0.1 | D11: ='Model inputs'!P92*('NeatRescue — Assumptions & (2)'!G5+'NeatRescue — Assumptions & (2)'!G6) -> 42.839983 | E11: ='Model inputs'!P92*('NeatRescue — Assumptions & (2)'!G5*('NeatRescue — Assumptions & (2)'!B5+MAX('NeatRescue — Assumptions & (2)'!D5-'NeatRescue — Assumptions & (2)'!C5,0)*'NeatRescue — Assumptions & (2)'!E5)+'NeatRescue — Assumptions & (2)'!G6*('NeatRescue — Assumptions & (2)'!B6+MAX('NeatRescue — Assumptions & (2)'!D6-'NeatRescue — Assumptions & (2)'!C6,0)*'NeatRescue — Assumptions & (2)'!E6)) -> 4583.8781 | F11: =IFERROR(('Model inputs'!P92*('NeatRescue — Assumptions & (2)'!G5*(('NeatRescue — Assumptions & (2)'!B5+MAX('NeatRescue — Assumptions & (2)'!D5-'NeatRescue — Assumptions & (2)'!C5,0)*'NeatRescue — Assumptions & (2)'!E5)*(1-'NeatRescue — Assumptions & simu'!B18)-'NeatRescue — Assumptions & (2)'!D5*('NeatRescue — Sensitivity · Infe'!B11+'NeatRescue — Assumptions & simu'!B8+'NeatRescue — Assumptions & simu'!B9)-'NeatRescue — Assumptions & (2)'!F5)+'NeatRescue — Assumptions & (2)'!G6*(('NeatRescue — Assumptions & (2)'!B6+MAX('NeatRescue — Assumptions & (2)'!D6-'NeatRescue — Assumptions & (2)'!C6,0)*'NeatRescue — Assumptions & (2)'!E6)*(1-'NeatRescue — Assumptions & simu'!B18)-'NeatRescue — Assumptions & (2)'!D6*('NeatRescue — Sensitivity · Infe'!B11+'NeatRescue — Assumptions & simu'!B8+'NeatRescue — Assumptions & simu'!B9)-'NeatRescue — Assumptions & (2)'!F6))-('NeatRescue — Assumptions & simu'!B10+'NeatRescue — Assumptions & simu'!B11+'NeatRescue — Assumptions & simu'!B12+'NeatRescue — Assumptions & simu'!B14))/'NeatRescue — Sensitivity · Infe'!E11,"") -> 0.32029187 | G11: ='Model inputs'!P92*('NeatRescue — Assumptions & (2)'!G5*(('NeatRescue — Assumptions & (2)'!B5+MAX('NeatRescue — Assumptions & (2)'!D5-'NeatRescue — Assumptions & (2)'!C5,0)*'NeatRescue — Assumptions & (2)'!E5)*(1-'NeatRescue — Assumptions & simu'!B18)-'NeatRescue — Assumptions & (2)'!D5*('NeatRescue — Sensitivity · Infe'!B11+'NeatRescue — Assumptions & simu'!B8+'NeatRescue — Assumptions & simu'!B9)-'NeatRescue — Assumptions & (2)'!F5)+'NeatRescue — Assumptions & (2)'!G6*(('NeatRescue — Assumptions & (2)'!B6+MAX('NeatRescue — Assumptions & (2)'!D6-'NeatRescue — Assumptions & (2)'!C6,0)*'NeatRescue — Assumptions & (2)'!E6)*(1-'NeatRescue — Assumptions & simu'!B18)-'NeatRescue — Assumptions & (2)'!D6*('NeatRescue — Sensitivity · Infe'!B11+'NeatRescue — Assumptions & simu'!B8+'NeatRescue — Assumptions & simu'!B9)-'NeatRescue — Assumptions & (2)'!F6))-('NeatRescue — Assumptions & simu'!B10+'NeatRescue — Assumptions & simu'!B11+'NeatRescue — Assumptions & simu'!B12+'NeatRescue — Assumptions & simu'!B14+'NeatRescue — Assumptions & simu'!B13+'NeatRescue — Assumptions & simu'!B15+'NeatRescue — Assumptions & simu'!B19) -> 1243.1789 | H11: ='Model inputs'!P79*('NeatRescue — Assumptions & (2)'!G5*(('NeatRescue — Assumptions & (2)'!B5+MAX('NeatRescue — Assumptions & (2)'!D5-'NeatRescue — Assumptions & (2)'!C5,0)*'NeatRescue — Assumptions & (2)'!E5)*(1-'NeatRescue — Assumptions & simu'!B18)-'NeatRescue — Assumptions & (2)'!D5*('NeatRescue — Sensitivity · Infe'!B11+'NeatRescue — Assumptions & simu'!B8+'NeatRescue — Assumptions & simu'!B9)-'NeatRescue — Assumptions & (2)'!F5)+'NeatRescue — Assumptions & (2)'!G6*(('NeatRescue — Assumptions & (2)'!B6+MAX('NeatRescue — Assumptions & (2)'!D6-'NeatRescue — Assumptions & (2)'!C6,0)*'NeatRescue — Assumptions & (2)'!E6)*(1-'NeatRescue — Assumptions & simu'!B18)-'NeatRescue — Assumptions & (2)'!D6*('NeatRescue — Sensitivity · Infe'!B11+'NeatRescue — Assumptions & simu'!B8+'NeatRescue — Assumptions & simu'!B9)-'NeatRescue — Assumptions & (2)'!F6))-12*('NeatRescue — Assumptions & simu'!B10+'NeatRescue — Assumptions & simu'!B11+'NeatRescue — Assumptions & simu'!B12+'NeatRescue — Assumptions & simu'!B14+'NeatRescue — Assumptions & simu'!B13+'NeatRescue — Assumptions & simu'!B15+'NeatRescue — Assumptions & simu'!B19)-'NeatRescue — Assumptions & simu'!B16 -> 4516.7351 | I11: ='NeatRescue — Sensitivity · Sens'!B5+'NeatRescue — Sensitivity · Infe'!H11 -> 9516.7351
A12: Inference $0.150 / churn 2% | B12: =0.15 -> 0.15 | C12: =0.02 -> 0.02 | D12: ='Model inputs'!P93*('NeatRescue — Assumptions & (2)'!G5+'NeatRescue — Assumptions & (2)'!G6) -> 58.842791 | E12: ='Model inputs'!P93*('NeatRescue — Assumptions & (2)'!G5*('NeatRescue — Assumptions & (2)'!B5+MAX('NeatRescue — Assumptions & (2)'!D5-'NeatRescue — Assumptions & (2)'!C5,0)*'NeatRescue — Assumptions & (2)'!E5)+'NeatRescue — Assumptions & (2)'!G6*('NeatRescue — Assumptions & (2)'!B6+MAX('NeatRescue — Assumptions & (2)'!D6-'NeatRescue — Assumptions & (2)'!C6,0)*'NeatRescue — Assumptions & (2)'!E6)) -> 6296.1787 | F12: =IFERROR(('Model inputs'!P93*('NeatRescue — Assumptions & (2)'!G5*(('NeatRescue — Assumptions & (2)'!B5+MAX('NeatRescue — Assumptions & (2)'!D5-'NeatRescue — Assumptions & (2)'!C5,0)*'NeatRescue — Assumptions & (2)'!E5)*(1-'NeatRescue — Assumptions & simu'!B18)-'NeatRescue — Assumptions & (2)'!D5*('NeatRescue — Sensitivity · Infe'!B12+'NeatRescue — Assumptions & simu'!B8+'NeatRescue — Assumptions & simu'!B9)-'NeatRescue — Assumptions & (2)'!F5)+'NeatRescue — Assumptions & (2)'!G6*(('NeatRescue — Assumptions & (2)'!B6+MAX('NeatRescue — Assumptions & (2)'!D6-'NeatRescue — Assumptions & (2)'!C6,0)*'NeatRescue — Assumptions & (2)'!E6)*(1-'NeatRescue — Assumptions & simu'!B18)-'NeatRescue — Assumptions & (2)'!D6*('NeatRescue — Sensitivity · Infe'!B12+'NeatRescue — Assumptions & simu'!B8+'NeatRescue — Assumptions & simu'!B9)-'NeatRescue — Assumptions & (2)'!F6))-('NeatRescue — Assumptions & simu'!B10+'NeatRescue — Assumptions & simu'!B11+'NeatRescue — Assumptions & simu'!B12+'NeatRescue — Assumptions & simu'!B14))/'NeatRescue — Sensitivity · Infe'!E12,"") -> 0.33364099 | G12: ='Model inputs'!P93*('NeatRescue — Assumptions & (2)'!G5*(('NeatRescue — Assumptions & (2)'!B5+MAX('NeatRescue — Assumptions & (2)'!D5-'NeatRescue — Assumptions & (2)'!C5,0)*'NeatRescue — Assumptions & (2)'!E5)*(1-'NeatRescue — Assumptions & simu'!B18)-'NeatRescue — Assumptions & (2)'!D5*('NeatRescue — Sensitivity · Infe'!B12+'NeatRescue — Assumptions & simu'!B8+'NeatRescue — Assumptions & simu'!B9)-'NeatRescue — Assumptions & (2)'!F5)+'NeatRescue — Assumptions & (2)'!G6*(('NeatRescue — Assumptions & (2)'!B6+MAX('NeatRescue — Assumptions & (2)'!D6-'NeatRescue — Assumptions & (2)'!C6,0)*'NeatRescue — Assumptions & (2)'!E6)*(1-'NeatRescue — Assumptions & simu'!B18)-'NeatRescue — Assumptions & (2)'!D6*('NeatRescue — Sensitivity · Infe'!B12+'NeatRescue — Assumptions & simu'!B8+'NeatRescue — Assumptions & simu'!B9)-'NeatRescue — Assumptions & (2)'!F6))-('NeatRescue — Assumptions & simu'!B10+'NeatRescue — Assumptions & simu'!B11+'NeatRescue — Assumptions & simu'!B12+'NeatRescue — Assumptions & simu'!B14+'NeatRescue — Assumptions & simu'!B13+'NeatRescue — Assumptions & simu'!B15+'NeatRescue — Assumptions & simu'!B19) -> 1875.6633 | H12: ='Model inputs'!P80*('NeatRescue — Assumptions & (2)'!G5*(('NeatRescue — Assumptions & (2)'!B5+MAX('NeatRescue — Assumptions & (2)'!D5-'NeatRescue — Assumptions & (2)'!C5,0)*'NeatRescue — Assumptions & (2)'!E5)*(1-'NeatRescue — Assumptions & simu'!B18)-'NeatRescue — Assumptions & (2)'!D5*('NeatRescue — Sensitivity · Infe'!B12+'NeatRescue — Assumptions & simu'!B8+'NeatRescue — Assumptions & simu'!B9)-'NeatRescue — Assumptions & (2)'!F5)+'NeatRescue — Assumptions & (2)'!G6*(('NeatRescue — Assumptions & (2)'!B6+MAX('NeatRescue — Assumptions & (2)'!D6-'NeatRescue — Assumptions & (2)'!C6,0)*'NeatRescue — Assumptions & (2)'!E6)*(1-'NeatRescue — Assumptions & simu'!B18)-'NeatRescue — Assumptions & (2)'!D6*('NeatRescue — Sensitivity · Infe'!B12+'NeatRescue — Assumptions & simu'!B8+'NeatRescue — Assumptions & simu'!B9)-'NeatRescue — Assumptions & (2)'!F6))-12*('NeatRescue — Assumptions & simu'!B10+'NeatRescue — Assumptions & simu'!B11+'NeatRescue — Assumptions & simu'!B12+'NeatRescue — Assumptions & simu'!B14+'NeatRescue — Assumptions & simu'!B13+'NeatRescue — Assumptions & simu'!B15+'NeatRescue — Assumptions & simu'!B19)-'NeatRescue — Assumptions & simu'!B16 -> 7219.2268 | I12: ='NeatRescue — Sensitivity · Sens'!B5+'NeatRescue — Sensitivity · Infe'!H12 -> 12219.227
A13: Inference $0.150 / churn 5% | B13: =0.15 -> 0.15 | C13: =0.05 -> 0.05 | D13: ='Model inputs'!P94*('NeatRescue — Assumptions & (2)'!G5+'NeatRescue — Assumptions & (2)'!G6) -> 51.961366 | E13: ='Model inputs'!P94*('NeatRescue — Assumptions & (2)'!G5*('NeatRescue — Assumptions & (2)'!B5+MAX('NeatRescue — Assumptions & (2)'!D5-'NeatRescue — Assumptions & (2)'!C5,0)*'NeatRescue — Assumptions & (2)'!E5)+'NeatRescue — Assumptions & (2)'!G6*('NeatRescue — Assumptions & (2)'!B6+MAX('NeatRescue — Assumptions & (2)'!D6-'NeatRescue — Assumptions & (2)'!C6,0)*'NeatRescue — Assumptions & (2)'!E6)) -> 5559.8661 | F13: =IFERROR(('Model inputs'!P94*('NeatRescue — Assumptions & (2)'!G5*(('NeatRescue — Assumptions & (2)'!B5+MAX('NeatRescue — Assumptions & (2)'!D5-'NeatRescue — Assumptions & (2)'!C5,0)*'NeatRescue — Assumptions & (2)'!E5)*(1-'NeatRescue — Assumptions & simu'!B18)-'NeatRescue — Assumptions & (2)'!D5*('NeatRescue — Sensitivity · Infe'!B13+'NeatRescue — Assumptions & simu'!B8+'NeatRescue — Assumptions & simu'!B9)-'NeatRescue — Assumptions & (2)'!F5)+'NeatRescue — Assumptions & (2)'!G6*(('NeatRescue — Assumptions & (2)'!B6+MAX('NeatRescue — Assumptions & (2)'!D6-'NeatRescue — Assumptions & (2)'!C6,0)*'NeatRescue — Assumptions & (2)'!E6)*(1-'NeatRescue — Assumptions & simu'!B18)-'NeatRescue — Assumptions & (2)'!D6*('NeatRescue — Sensitivity · Infe'!B13+'NeatRescue — Assumptions & simu'!B8+'NeatRescue — Assumptions & simu'!B9)-'NeatRescue — Assumptions & (2)'!F6))-('NeatRescue — Assumptions & simu'!B10+'NeatRescue — Assumptions & simu'!B11+'NeatRescue — Assumptions & simu'!B12+'NeatRescue — Assumptions & simu'!B14))/'NeatRescue — Sensitivity · Infe'!E13,"") -> 0.32890835 | G13: ='Model inputs'!P94*('NeatRescue — Assumptions & (2)'!G5*(('NeatRescue — Assumptions & (2)'!B5+MAX('NeatRescue — Assumptions & (2)'!D5-'NeatRescue — Assumptions & (2)'!C5,0)*'NeatRescue — Assumptions & (2)'!E5)*(1-'NeatRescue — Assumptions & simu'!B18)-'NeatRescue — Assumptions & (2)'!D5*('NeatRescue — Sensitivity · Infe'!B13+'NeatRescue — Assumptions & simu'!B8+'NeatRescue — Assumptions & simu'!B9)-'NeatRescue — Assumptions & (2)'!F5)+'NeatRescue — Assumptions & (2)'!G6*(('NeatRescue — Assumptions & (2)'!B6+MAX('NeatRescue — Assumptions & (2)'!D6-'NeatRescue — Assumptions & (2)'!C6,0)*'NeatRescue — Assumptions & (2)'!E6)*(1-'NeatRescue — Assumptions & simu'!B18)-'NeatRescue — Assumptions & (2)'!D6*('NeatRescue — Sensitivity · Infe'!B13+'NeatRescue — Assumptions & simu'!B8+'NeatRescue — Assumptions & simu'!B9)-'NeatRescue — Assumptions & (2)'!F6))-('NeatRescue — Assumptions & simu'!B10+'NeatRescue — Assumptions & simu'!B11+'NeatRescue — Assumptions & simu'!B12+'NeatRescue — Assumptions & simu'!B14+'NeatRescue — Assumptions & simu'!B13+'NeatRescue — Assumptions & simu'!B15+'NeatRescue — Assumptions & simu'!B19) -> 1603.6864 | H13: ='Model inputs'!P81*('NeatRescue — Assumptions & (2)'!G5*(('NeatRescue — Assumptions & (2)'!B5+MAX('NeatRescue — Assumptions & (2)'!D5-'NeatRescue — Assumptions & (2)'!C5,0)*'NeatRescue — Assumptions & (2)'!E5)*(1-'NeatRescue — Assumptions & simu'!B18)-'NeatRescue — Assumptions & (2)'!D5*('NeatRescue — Sensitivity · Infe'!B13+'NeatRescue — Assumptions & simu'!B8+'NeatRescue — Assumptions & simu'!B9)-'NeatRescue — Assumptions & (2)'!F5)+'NeatRescue — Assumptions & (2)'!G6*(('NeatRescue — Assumptions & (2)'!B6+MAX('NeatRescue — Assumptions & (2)'!D6-'NeatRescue — Assumptions & (2)'!C6,0)*'NeatRescue — Assumptions & (2)'!E6)*(1-'NeatRescue — Assumptions & simu'!B18)-'NeatRescue — Assumptions & (2)'!D6*('NeatRescue — Sensitivity · Infe'!B13+'NeatRescue — Assumptions & simu'!B8+'NeatRescue — Assumptions & simu'!B9)-'NeatRescue — Assumptions & (2)'!F6))-12*('NeatRescue — Assumptions & simu'!B10+'NeatRescue — Assumptions & simu'!B11+'NeatRescue — Assumptions & simu'!B12+'NeatRescue — Assumptions & simu'!B14+'NeatRescue — Assumptions & simu'!B13+'NeatRescue — Assumptions & simu'!B15+'NeatRescue — Assumptions & simu'!B19)-'NeatRescue — Assumptions & simu'!B16 -> 6090.6493 | I13: ='NeatRescue — Sensitivity · Sens'!B5+'NeatRescue — Sensitivity · Infe'!H13 -> 11090.649
A14: Inference $0.300 / churn 10% | B14: =0.3 -> 0.3 | C14: =0.1 -> 0.1 | D14: ='Model inputs'!P95*('NeatRescue — Assumptions & (2)'!G5+'NeatRescue — Assumptions & (2)'!G6) -> 42.839983 | E14: ='Model inputs'!P95*('NeatRescue — Assumptions & (2)'!G5*('NeatRescue — Assumptions & (2)'!B5+MAX('NeatRescue — Assumptions & (2)'!D5-'NeatRescue — Assumptions & (2)'!C5,0)*'NeatRescue — Assumptions & (2)'!E5)+'NeatRescue — Assumptions & (2)'!G6*('NeatRescue — Assumptions & (2)'!B6+MAX('NeatRescue — Assumptions & (2)'!D6-'NeatRescue — Assumptions & (2)'!C6,0)*'NeatRescue — Assumptions & (2)'!E6)) -> 4583.8781 | F14: =IFERROR(('Model inputs'!P95*('NeatRescue — Assumptions & (2)'!G5*(('NeatRescue — Assumptions & (2)'!B5+MAX('NeatRescue — Assumptions & (2)'!D5-'NeatRescue — Assumptions & (2)'!C5,0)*'NeatRescue — Assumptions & (2)'!E5)*(1-'NeatRescue — Assumptions & simu'!B18)-'NeatRescue — Assumptions & (2)'!D5*('NeatRescue — Sensitivity · Infe'!B14+'NeatRescue — Assumptions & simu'!B8+'NeatRescue — Assumptions & simu'!B9)-'NeatRescue — Assumptions & (2)'!F5)+'NeatRescue — Assumptions & (2)'!G6*(('NeatRescue — Assumptions & (2)'!B6+MAX('NeatRescue — Assumptions & (2)'!D6-'NeatRescue — Assumptions & (2)'!C6,0)*'NeatRescue — Assumptions & (2)'!E6)*(1-'NeatRescue — Assumptions & simu'!B18)-'NeatRescue — Assumptions & (2)'!D6*('NeatRescue — Sensitivity · Infe'!B14+'NeatRescue — Assumptions & simu'!B8+'NeatRescue — Assumptions & simu'!B9)-'NeatRescue — Assumptions & (2)'!F6))-('NeatRescue — Assumptions & simu'!B10+'NeatRescue — Assumptions & simu'!B11+'NeatRescue — Assumptions & simu'!B12+'NeatRescue — Assumptions & simu'!B14))/'NeatRescue — Sensitivity · Infe'!E14,"") -> -0.16568944 | G14: ='Model inputs'!P95*('NeatRescue — Assumptions & (2)'!G5*(('NeatRescue — Assumptions & (2)'!B5+MAX('NeatRescue — Assumptions & (2)'!D5-'NeatRescue — Assumptions & (2)'!C5,0)*'NeatRescue — Assumptions & (2)'!E5)*(1-'NeatRescue — Assumptions & simu'!B18)-'NeatRescue — Assumptions & (2)'!D5*('NeatRescue — Sensitivity · Infe'!B14+'NeatRescue — Assumptions & simu'!B8+'NeatRescue — Assumptions & simu'!B9)-'NeatRescue — Assumptions & (2)'!F5)+'NeatRescue — Assumptions & (2)'!G6*(('NeatRescue — Assumptions & (2)'!B6+MAX('NeatRescue — Assumptions & (2)'!D6-'NeatRescue — Assumptions & (2)'!C6,0)*'NeatRescue — Assumptions & (2)'!E6)*(1-'NeatRescue — Assumptions & simu'!B18)-'NeatRescue — Assumptions & (2)'!D6*('NeatRescue — Sensitivity · Infe'!B14+'NeatRescue — Assumptions & simu'!B8+'NeatRescue — Assumptions & simu'!B9)-'NeatRescue — Assumptions & (2)'!F6))-('NeatRescue — Assumptions & simu'!B10+'NeatRescue — Assumptions & simu'!B11+'NeatRescue — Assumptions & simu'!B12+'NeatRescue — Assumptions & simu'!B14+'NeatRescue — Assumptions & simu'!B13+'NeatRescue — Assumptions & simu'!B15+'NeatRescue — Assumptions & simu'!B19) -> -984.50018 | H14: ='Model inputs'!P82*('NeatRescue — Assumptions & (2)'!G5*(('NeatRescue — Assumptions & (2)'!B5+MAX('NeatRescue — Assumptions & (2)'!D5-'NeatRescue — Assumptions & (2)'!C5,0)*'NeatRescue — Assumptions & (2)'!E5)*(1-'NeatRescue — Assumptions & simu'!B18)-'NeatRescue — Assumptions & (2)'!D5*('NeatRescue — Sensitivity · Infe'!B14+'NeatRescue — Assumptions & simu'!B8+'NeatRescue — Assumptions & simu'!B9)-'NeatRescue — Assumptions & (2)'!F5)+'NeatRescue — Assumptions & (2)'!G6*(('NeatRescue — Assumptions & (2)'!B6+MAX('NeatRescue — Assumptions & (2)'!D6-'NeatRescue — Assumptions & (2)'!C6,0)*'NeatRescue — Assumptions & (2)'!E6)*(1-'NeatRescue — Assumptions & simu'!B18)-'NeatRescue — Assumptions & (2)'!D6*('NeatRescue — Sensitivity · Infe'!B14+'NeatRescue — Assumptions & simu'!B8+'NeatRescue — Assumptions & simu'!B9)-'NeatRescue — Assumptions & (2)'!F6))-12*('NeatRescue — Assumptions & simu'!B10+'NeatRescue — Assumptions & simu'!B11+'NeatRescue — Assumptions & simu'!B12+'NeatRescue — Assumptions & simu'!B14+'NeatRescue — Assumptions & simu'!B13+'NeatRescue — Assumptions & simu'!B15+'NeatRescue — Assumptions & simu'!B19)-'NeatRescue — Assumptions & simu'!B16 -> -8793.6358 | I14: ='NeatRescue — Sensitivity · Sens'!B5+'NeatRescue — Sensitivity · Infe'!H14 -> -3793.6358
A15: Inference $0.300 / churn 2% | B15: =0.3 -> 0.3 | C15: =0.02 -> 0.02 | D15: ='Model inputs'!P96*('NeatRescue — Assumptions & (2)'!G5+'NeatRescue — Assumptions & (2)'!G6) -> 58.842791 | E15: ='Model inputs'!P96*('NeatRescue — Assumptions & (2)'!G5*('NeatRescue — Assumptions & (2)'!B5+MAX('NeatRescue — Assumptions & (2)'!D5-'NeatRescue — Assumptions & (2)'!C5,0)*'NeatRescue — Assumptions & (2)'!E5)+'NeatRescue — Assumptions & (2)'!G6*('NeatRescue — Assumptions & (2)'!B6+MAX('NeatRescue — Assumptions & (2)'!D6-'NeatRescue — Assumptions & (2)'!C6,0)*'NeatRescue — Assumptions & (2)'!E6)) -> 6296.1787 | F15: =IFERROR(('Model inputs'!P96*('NeatRescue — Assumptions & (2)'!G5*(('NeatRescue — Assumptions & (2)'!B5+MAX('NeatRescue — Assumptions & (2)'!D5-'NeatRescue — Assumptions & (2)'!C5,0)*'NeatRescue — Assumptions & (2)'!E5)*(1-'NeatRescue — Assumptions & simu'!B18)-'NeatRescue — Assumptions & (2)'!D5*('NeatRescue — Sensitivity · Infe'!B15+'NeatRescue — Assumptions & simu'!B8+'NeatRescue — Assumptions & simu'!B9)-'NeatRescue — Assumptions & (2)'!F5)+'NeatRescue — Assumptions & (2)'!G6*(('NeatRescue — Assumptions & (2)'!B6+MAX('NeatRescue — Assumptions & (2)'!D6-'NeatRescue — Assumptions & (2)'!C6,0)*'NeatRescue — Assumptions & (2)'!E6)*(1-'NeatRescue — Assumptions & simu'!B18)-'NeatRescue — Assumptions & (2)'!D6*('NeatRescue — Sensitivity · Infe'!B15+'NeatRescue — Assumptions & simu'!B8+'NeatRescue — Assumptions & simu'!B9)-'NeatRescue — Assumptions & (2)'!F6))-('NeatRescue — Assumptions & simu'!B10+'NeatRescue — Assumptions & simu'!B11+'NeatRescue — Assumptions & simu'!B12+'NeatRescue — Assumptions & simu'!B14))/'NeatRescue — Sensitivity · Infe'!E15,"") -> -0.15234032 | G15: ='Model inputs'!P96*('NeatRescue — Assumptions & (2)'!G5*(('NeatRescue — Assumptions & (2)'!B5+MAX('NeatRescue — Assumptions & (2)'!D5-'NeatRescue — Assumptions & (2)'!C5,0)*'NeatRescue — Assumptions & (2)'!E5)*(1-'NeatRescue — Assumptions & simu'!B18)-'NeatRescue — Assumptions & (2)'!D5*('NeatRescue — Sensitivity · Infe'!B15+'NeatRescue — Assumptions & simu'!B8+'NeatRescue — Assumptions & simu'!B9)-'NeatRescue — Assumptions & (2)'!F5)+'NeatRescue — Assumptions & (2)'!G6*(('NeatRescue — Assumptions & (2)'!B6+MAX('NeatRescue — Assumptions & (2)'!D6-'NeatRescue — Assumptions & (2)'!C6,0)*'NeatRescue — Assumptions & (2)'!E6)*(1-'NeatRescue — Assumptions & simu'!B18)-'NeatRescue — Assumptions & (2)'!D6*('NeatRescue — Sensitivity · Infe'!B15+'NeatRescue — Assumptions & simu'!B8+'NeatRescue — Assumptions & simu'!B9)-'NeatRescue — Assumptions & (2)'!F6))-('NeatRescue — Assumptions & simu'!B10+'NeatRescue — Assumptions & simu'!B11+'NeatRescue — Assumptions & simu'!B12+'NeatRescue — Assumptions & simu'!B14+'NeatRescue — Assumptions & simu'!B13+'NeatRescue — Assumptions & simu'!B15+'NeatRescue — Assumptions & simu'!B19) -> -1184.1619 | H15: ='Model inputs'!P83*('NeatRescue — Assumptions & (2)'!G5*(('NeatRescue — Assumptions & (2)'!B5+MAX('NeatRescue — Assumptions & (2)'!D5-'NeatRescue — Assumptions & (2)'!C5,0)*'NeatRescue — Assumptions & (2)'!E5)*(1-'NeatRescue — Assumptions & simu'!B18)-'NeatRescue — Assumptions & (2)'!D5*('NeatRescue — Sensitivity · Infe'!B15+'NeatRescue — Assumptions & simu'!B8+'NeatRescue — Assumptions & simu'!B9)-'NeatRescue — Assumptions & (2)'!F5)+'NeatRescue — Assumptions & (2)'!G6*(('NeatRescue — Assumptions & (2)'!B6+MAX('NeatRescue — Assumptions & (2)'!D6-'NeatRescue — Assumptions & (2)'!C6,0)*'NeatRescue — Assumptions & (2)'!E6)*(1-'NeatRescue — Assumptions & simu'!B18)-'NeatRescue — Assumptions & (2)'!D6*('NeatRescue — Sensitivity · Infe'!B15+'NeatRescue — Assumptions & simu'!B8+'NeatRescue — Assumptions & simu'!B9)-'NeatRescue — Assumptions & (2)'!F6))-12*('NeatRescue — Assumptions & simu'!B10+'NeatRescue — Assumptions & simu'!B11+'NeatRescue — Assumptions & simu'!B12+'NeatRescue — Assumptions & simu'!B14+'NeatRescue — Assumptions & simu'!B13+'NeatRescue — Assumptions & simu'!B15+'NeatRescue — Assumptions & simu'!B19)-'NeatRescue — Assumptions & simu'!B16 -> -9646.7543 | I15: ='NeatRescue — Sensitivity · Sens'!B5+'NeatRescue — Sensitivity · Infe'!H15 -> -4646.7543
A16: Inference $0.300 / churn 5% | B16: =0.3 -> 0.3 | C16: =0.05 -> 0.05 | D16: ='Model inputs'!P97*('NeatRescue — Assumptions & (2)'!G5+'NeatRescue — Assumptions & (2)'!G6) -> 51.961366 | E16: ='Model inputs'!P97*('NeatRescue — Assumptions & (2)'!G5*('NeatRescue — Assumptions & (2)'!B5+MAX('NeatRescue — Assumptions & (2)'!D5-'NeatRescue — Assumptions & (2)'!C5,0)*'NeatRescue — Assumptions & (2)'!E5)+'NeatRescue — Assumptions & (2)'!G6*('NeatRescue — Assumptions & (2)'!B6+MAX('NeatRescue — Assumptions & (2)'!D6-'NeatRescue — Assumptions & (2)'!C6,0)*'NeatRescue — Assumptions & (2)'!E6)) -> 5559.8661 | F16: =IFERROR(('Model inputs'!P97*('NeatRescue — Assumptions & (2)'!G5*(('NeatRescue — Assumptions & (2)'!B5+MAX('NeatRescue — Assumptions & (2)'!D5-'NeatRescue — Assumptions & (2)'!C5,0)*'NeatRescue — Assumptions & (2)'!E5)*(1-'NeatRescue — Assumptions & simu'!B18)-'NeatRescue — Assumptions & (2)'!D5*('NeatRescue — Sensitivity · Infe'!B16+'NeatRescue — Assumptions & simu'!B8+'NeatRescue — Assumptions & simu'!B9)-'NeatRescue — Assumptions & (2)'!F5)+'NeatRescue — Assumptions & (2)'!G6*(('NeatRescue — Assumptions & (2)'!B6+MAX('NeatRescue — Assumptions & (2)'!D6-'NeatRescue — Assumptions & (2)'!C6,0)*'NeatRescue — Assumptions & (2)'!E6)*(1-'NeatRescue — Assumptions & simu'!B18)-'NeatRescue — Assumptions & (2)'!D6*('NeatRescue — Sensitivity · Infe'!B16+'NeatRescue — Assumptions & simu'!B8+'NeatRescue — Assumptions & simu'!B9)-'NeatRescue — Assumptions & (2)'!F6))-('NeatRescue — Assumptions & simu'!B10+'NeatRescue — Assumptions & simu'!B11+'NeatRescue — Assumptions & simu'!B12+'NeatRescue — Assumptions & simu'!B14))/'NeatRescue — Sensitivity · Infe'!E16,"") -> -0.15707296 | G16: ='Model inputs'!P97*('NeatRescue — Assumptions & (2)'!G5*(('NeatRescue — Assumptions & (2)'!B5+MAX('NeatRescue — Assumptions & (2)'!D5-'NeatRescue — Assumptions & (2)'!C5,0)*'NeatRescue — Assumptions & (2)'!E5)*(1-'NeatRescue — Assumptions & simu'!B18)-'NeatRescue — Assumptions & (2)'!D5*('NeatRescue — Sensitivity · Infe'!B16+'NeatRescue — Assumptions & simu'!B8+'NeatRescue — Assumptions & simu'!B9)-'NeatRescue — Assumptions & (2)'!F5)+'NeatRescue — Assumptions & (2)'!G6*(('NeatRescue — Assumptions & (2)'!B6+MAX('NeatRescue — Assumptions & (2)'!D6-'NeatRescue — Assumptions & (2)'!C6,0)*'NeatRescue — Assumptions & (2)'!E6)*(1-'NeatRescue — Assumptions & simu'!B18)-'NeatRescue — Assumptions & (2)'!D6*('NeatRescue — Sensitivity · Infe'!B16+'NeatRescue — Assumptions & simu'!B8+'NeatRescue — Assumptions & simu'!B9)-'NeatRescue — Assumptions & (2)'!F6))-('NeatRescue — Assumptions & simu'!B10+'NeatRescue — Assumptions & simu'!B11+'NeatRescue — Assumptions & simu'!B12+'NeatRescue — Assumptions & simu'!B14+'NeatRescue — Assumptions & simu'!B13+'NeatRescue — Assumptions & simu'!B15+'NeatRescue — Assumptions & simu'!B19) -> -1098.3046 | H16: ='Model inputs'!P84*('NeatRescue — Assumptions & (2)'!G5*(('NeatRescue — Assumptions & (2)'!B5+MAX('NeatRescue — Assumptions & (2)'!D5-'NeatRescue — Assumptions & (2)'!C5,0)*'NeatRescue — Assumptions & (2)'!E5)*(1-'NeatRescue — Assumptions & simu'!B18)-'NeatRescue — Assumptions & (2)'!D5*('NeatRescue — Sensitivity · Infe'!B16+'NeatRescue — Assumptions & simu'!B8+'NeatRescue — Assumptions & simu'!B9)-'NeatRescue — Assumptions & (2)'!F5)+'NeatRescue — Assumptions & (2)'!G6*(('NeatRescue — Assumptions & (2)'!B6+MAX('NeatRescue — Assumptions & (2)'!D6-'NeatRescue — Assumptions & (2)'!C6,0)*'NeatRescue — Assumptions & (2)'!E6)*(1-'NeatRescue — Assumptions & simu'!B18)-'NeatRescue — Assumptions & (2)'!D6*('NeatRescue — Sensitivity · Infe'!B16+'NeatRescue — Assumptions & simu'!B8+'NeatRescue — Assumptions & simu'!B9)-'NeatRescue — Assumptions & (2)'!F6))-12*('NeatRescue — Assumptions & simu'!B10+'NeatRescue — Assumptions & simu'!B11+'NeatRescue — Assumptions & simu'!B12+'NeatRescue — Assumptions & simu'!B14+'NeatRescue — Assumptions & simu'!B13+'NeatRescue — Assumptions & simu'!B15+'NeatRescue — Assumptions & simu'!B19)-'NeatRescue — Assumptions & simu'!B16 -> -9290.4867 | I16: ='NeatRescue — Sensitivity · Sens'!B5+'NeatRescue — Sensitivity · Infe'!H16 -> -4290.4867

Sheet Model inputs
A1: Model inputs
A2: Integration values are aggregated snapshots; raw source records are not included.
A4: Variables
A5: Variable / segment | B5: 2027-09 | C5: 2026-09 | D5: 2026-10 | E5: 2026-11 | F5: 2026-12 | G5: 2027-01 | H5: 2027-02 | I5: 2027-03 | J5: 2027-04 | K5: 2027-05 | L5: 2027-06 | M5: 2027-07 | N5: 2027-08 | O5: Value | P5: Value
A6: Break-even customers · Main Scenario | B6: =IF(IF(IF(ISERROR('Model inputs'!B102>0),'Model inputs'!B102>0,IF('Model inputs'!B102="","",'Model inputs'!B102>0))="",FALSE,IF(ISERROR('Model inputs'!B102>0),'Model inputs'!B102>0,IF('Model inputs'!B102="","",'Model inputs'!B102>0))),CEILING(('Model inputs'!B103+'Model inputs'!B112+'Model inputs'!B98+'Model inputs'!B104)/'Model inputs'!B102,1),"") -> 7
A7: Break-even customers · Bootstrap no-sales stress — hypothetical | B7: =IF(IF(IF(ISERROR('Model inputs'!B223>0),'Model inputs'!B223>0,IF('Model inputs'!B223="","",'Model inputs'!B223>0))="",FALSE,IF(ISERROR('Model inputs'!B223>0),'Model inputs'!B223>0,IF('Model inputs'!B223="","",'Model inputs'!B223>0))),CEILING(('Model inputs'!B227+'Model inputs'!B255+'Model inputs'!B205+'Model inputs'!B231)/IF('Model inputs'!B223="",0,'Model inputs'!B223),1),"")
A8: Break-even customers · Growth | B8: =IF(IF(IF(ISERROR('Model inputs'!B224>0),'Model inputs'!B224>0,IF('Model inputs'!B224="","",'Model inputs'!B224>0))="",FALSE,IF(ISERROR('Model inputs'!B224>0),'Model inputs'!B224>0,IF('Model inputs'!B224="","",'Model inputs'!B224>0))),CEILING(('Model inputs'!B228+'Model inputs'!B256+'Model inputs'!B206+'Model inputs'!B232)/'Model inputs'!B224,1),"") -> 9
A9: Break-even customers · Bootstrap $5,000 — hypothetical | B9: =IF(IF(IF(ISERROR('Model inputs'!B225>0),'Model inputs'!B225>0,IF('Model inputs'!B225="","",'Model inputs'!B225>0))="",FALSE,IF(ISERROR('Model inputs'!B225>0),'Model inputs'!B225>0,IF('Model inputs'!B225="","",'Model inputs'!B225>0))),CEILING(('Model inputs'!B229+'Model inputs'!B257+'Model inputs'!B207+'Model inputs'!B233)/'Model inputs'!B225,1),"") -> 7
A10: Break-even customers · Conservative | B10: =IF(IF(IF(ISERROR('Model inputs'!B226>0),'Model inputs'!B226>0,IF('Model inputs'!B226="","",'Model inputs'!B226>0))="",FALSE,IF(ISERROR('Model inputs'!B226>0),'Model inputs'!B226>0,IF('Model inputs'!B226="","",'Model inputs'!B226>0))),CEILING(('Model inputs'!B230+'Model inputs'!B258+'Model inputs'!B208+'Model inputs'!B234)/'Model inputs'!B226,1),"") -> 7
A11: Closing cash · NeatRescue — Hackathon submission · 12-month scenario comparison — hypothetical · Main Scenario | B11: =IF(IF(DATE(2027,9,1)=DATE(2026,10,1),IF('Model inputs'!O45="","",'Model inputs'!O45),IF('Model inputs'!N11="","",'Model inputs'!N11))="",0,IF(DATE(2027,9,1)=DATE(2026,10,1),IF('Model inputs'!O45="","",'Model inputs'!O45),IF('Model inputs'!N11="","",'Model inputs'!N11)))+'Model inputs'!B42 -> 16344.74 | C11: 0 | D11: =IF(IF(DATE(2026,10,1)=DATE(2026,10,1),IF('Model inputs'!O45="","",'Model inputs'!O45),IF('Model inputs'!C11="","",'Model inputs'!C11))="",0,IF(DATE(2026,10,1)=DATE(2026,10,1),IF('Model inputs'!O45="","",'Model inputs'!O45),IF('Model inputs'!C11="","",'Model inputs'!C11)))+'Model inputs'!D42 -> -427.43 | E11: =IF(IF(DATE(2026,11,1)=DATE(2026,10,1),IF('Model inputs'!O45="","",'Model inputs'!O45),IF('Model inputs'!D11="","",'Model inputs'!D11))="",0,IF(DATE(2026,11,1)=DATE(2026,10,1),IF('Model inputs'!O45="","",'Model inputs'!O45),IF('Model inputs'!D11="","",'Model inputs'!D11)))+'Model inputs'!E42 -> -421.1615 | F11: =IF(IF(DATE(2026,12,1)=DATE(2026,10,1),IF('Model inputs'!O45="","",'Model inputs'!O45),IF('Model inputs'!E11="","",'Model inputs'!E11))="",0,IF(DATE(2026,12,1)=DATE(2026,10,1),IF('Model inputs'!O45="","",'Model inputs'!O45),IF('Model inputs'!E11="","",'Model inputs'!E11)))+'Model inputs'!F42 -> -168.39672 | G11: =IF(IF(DATE(2027,1,1)=DATE(2026,10,1),IF('Model inputs'!O45="","",'Model inputs'!O45),IF('Model inputs'!F11="","",'Model inputs'!F11))="",0,IF(DATE(2027,1,1)=DATE(2026,10,1),IF('Model inputs'!O45="","",'Model inputs'!O45),IF('Model inputs'!F11="","",'Model inputs'!F11)))+'Model inputs'!G42 -> 345.47048 | H11: =IF(IF(DATE(2027,2,1)=DATE(2026,10,1),IF('Model inputs'!O45="","",'Model inputs'!O45),IF('Model inputs'!G11="","",'Model inputs'!G11))="",0,IF(DATE(2027,2,1)=DATE(2026,10,1),IF('Model inputs'!O45="","",'Model inputs'!O45),IF('Model inputs'!G11="","",'Model inputs'!G11)))+'Model inputs'!H42 -> 1137.0091 | I11: =IF(IF(DATE(2027,3,1)=DATE(2026,10,1),IF('Model inputs'!O45="","",'Model inputs'!O45),IF('Model inputs'!H11="","",'Model inputs'!H11))="",0,IF(DATE(2027,3,1)=DATE(2026,10,1),IF('Model inputs'!O45="","",'Model inputs'!O45),IF('Model inputs'!H11="","",'Model inputs'!H11)))+'Model inputs'!I42 -> 2224.9219 | J11: =IF(IF(DATE(2027,4,1)=DATE(2026,10,1),IF('Model inputs'!O45="","",'Model inputs'!O45),IF('Model inputs'!I11="","",'Model inputs'!I11))="",0,IF(DATE(2027,4,1)=DATE(2026,10,1),IF('Model inputs'!O45="","",'Model inputs'!O45),IF('Model inputs'!I11="","",'Model inputs'!I11)))+'Model inputs'!J42 -> 3630.2355 | K11: =IF(IF(DATE(2027,5,1)=DATE(2026,10,1),IF('Model inputs'!O45="","",'Model inputs'!O45),IF('Model inputs'!J11="","",'Model inputs'!J11))="",0,IF(DATE(2027,5,1)=DATE(2026,10,1),IF('Model inputs'!O45="","",'Model inputs'!O45),IF('Model inputs'!J11="","",'Model inputs'!J11)))+'Model inputs'!K42 -> 5376.5093 | L11: =IF(IF(DATE(2027,6,1)=DATE(2026,10,1),IF('Model inputs'!O45="","",'Model inputs'!O45),IF('Model inputs'!K11="","",'Model inputs'!K11))="",0,IF(DATE(2027,6,1)=DATE(2026,10,1),IF('Model inputs'!O45="","",'Model inputs'!O45),IF('Model inputs'!K11="","",'Model inputs'!K11)))+'Model inputs'!L42 -> 7490.068 | M11: =IF(IF(DATE(2027,7,1)=DATE(2026,10,1),IF('Model inputs'!O45="","",'Model inputs'!O45),IF('Model inputs'!L11="","",'Model inputs'!L11))="",0,IF(DATE(2027,7,1)=DATE(2026,10,1),IF('Model inputs'!O45="","",'Model inputs'!O45),IF('Model inputs'!L11="","",'Model inputs'!L11)))+'Model inputs'!M42 -> 10000.257 | N11: =IF(IF(DATE(2027,8,1)=DATE(2026,10,1),IF('Model inputs'!O45="","",'Model inputs'!O45),IF('Model inputs'!M11="","",'Model inputs'!M11))="",0,IF(DATE(2027,8,1)=DATE(2026,10,1),IF('Model inputs'!O45="","",'Model inputs'!O45),IF('Model inputs'!M11="","",'Model inputs'!M11)))+'Model inputs'!N42 -> 12939.726
A12: Closing cash · NeatRescue — Hackathon submission · 12-month scenario comparison — hypothetical · Bootstrap no-sales stress — hypothetical | B12: =IF(IF(DATE(2027,9,1)=DATE(2026,10,1),IF('Model inputs'!O46="","",'Model inputs'!O46),IF('Model inputs'!N12="","",'Model inputs'!N12))="",0,IF(DATE(2027,9,1)=DATE(2026,10,1),IF('Model inputs'!O46="","",'Model inputs'!O46),IF('Model inputs'!N12="","",'Model inputs'!N12)))+'Model inputs'!B43 -> -600 | C12: 0 | D12: =IF(IF(DATE(2026,10,1)=DATE(2026,10,1),IF('Model inputs'!O46="","",'Model inputs'!O46),IF('Model inputs'!C12="","",'Model inputs'!C12))="",0,IF(DATE(2026,10,1)=DATE(2026,10,1),IF('Model inputs'!O46="","",'Model inputs'!O46),IF('Model inputs'!C12="","",'Model inputs'!C12)))+'Model inputs'!D43 -> 4350 | E12: =IF(IF(DATE(2026,11,1)=DATE(2026,10,1),IF('Model inputs'!O46="","",'Model inputs'!O46),IF('Model inputs'!D12="","",'Model inputs'!D12))="",0,IF(DATE(2026,11,1)=DATE(2026,10,1),IF('Model inputs'!O46="","",'Model inputs'!O46),IF('Model inputs'!D12="","",'Model inputs'!D12)))+'Model inputs'!E43 -> 3900 | F12: =IF(IF(DATE(2026,12,1)=DATE(2026,10,1),IF('Model inputs'!O46="","",'Model inputs'!O46),IF('Model inputs'!E12="","",'Model inputs'!E12))="",0,IF(DATE(2026,12,1)=DATE(2026,10,1),IF('Model inputs'!O46="","",'Model inputs'!O46),IF('Model inputs'!E12="","",'Model inputs'!E12)))+'Model inputs'!F43 -> 3450 | G12: =IF(IF(DATE(2027,1,1)=DATE(2026,10,1),IF('Model inputs'!O46="","",'Model inputs'!O46),IF('Model inputs'!F12="","",'Model inputs'!F12))="",0,IF(DATE(2027,1,1)=DATE(2026,10,1),IF('Model inputs'!O46="","",'Model inputs'!O46),IF('Model inputs'!F12="","",'Model inputs'!F12)))+'Model inputs'!G43 -> 3000 | H12: =IF(IF(DATE(2027,2,1)=DATE(2026,10,1),IF('Model inputs'!O46="","",'Model inputs'!O46),IF('Model inputs'!G12="","",'Model inputs'!G12))="",0,IF(DATE(2027,2,1)=DATE(2026,10,1),IF('Model inputs'!O46="","",'Model inputs'!O46),IF('Model inputs'!G12="","",'Model inputs'!G12)))+'Model inputs'!H43 -> 2550 | I12: =IF(IF(DATE(2027,3,1)=DATE(2026,10,1),IF('Model inputs'!O46="","",'Model inputs'!O46),IF('Model inputs'!H12="","",'Model inputs'!H12))="",0,IF(DATE(2027,3,1)=DATE(2026,10,1),IF('Model inputs'!O46="","",'Model inputs'!O46),IF('Model inputs'!H12="","",'Model inputs'!H12)))+'Model inputs'!I43 -> 2100 | J12: =IF(IF(DATE(2027,4,1)=DATE(2026,10,1),IF('Model inputs'!O46="","",'Model inputs'!O46),IF('Model inputs'!I12="","",'Model inputs'!I12))="",0,IF(DATE(2027,4,1)=DATE(2026,10,1),IF('Model inputs'!O46="","",'Model inputs'!O46),IF('Model inputs'!I12="","",'Model inputs'!I12)))+'Model inputs'!J43 -> 1650 | K12: =IF(IF(DATE(2027,5,1)=DATE(2026,10,1),IF('Model inputs'!O46="","",'Model inputs'!O46),IF('Model inputs'!J12="","",'Model inputs'!J12))="",0,IF(DATE(2027,5,1)=DATE(2026,10,1),IF('Model inputs'!O46="","",'Model inputs'!O46),IF('Model inputs'!J12="","",'Model inputs'!J12)))+'Model inputs'!K43 -> 1200 | L12: =IF(IF(DATE(2027,6,1)=DATE(2026,10,1),IF('Model inputs'!O46="","",'Model inputs'!O46),IF('Model inputs'!K12="","",'Model inputs'!K12))="",0,IF(DATE(2027,6,1)=DATE(2026,10,1),IF('Model inputs'!O46="","",'Model inputs'!O46),IF('Model inputs'!K12="","",'Model inputs'!K12)))+'Model inputs'!L43 -> 750 | M12: =IF(IF(DATE(2027,7,1)=DATE(2026,10,1),IF('Model inputs'!O46="","",'Model inputs'!O46),IF('Model inputs'!L12="","",'Model inputs'!L12))="",0,IF(DATE(2027,7,1)=DATE(2026,10,1),IF('Model inputs'!O46="","",'Model inputs'!O46),IF('Model inputs'!L12="","",'Model inputs'!L12)))+'Model inputs'!M43 -> 300 | N12: =IF(IF(DATE(2027,8,1)=DATE(2026,10,1),IF('Model inputs'!O46="","",'Model inputs'!O46),IF('Model inputs'!M12="","",'Model inputs'!M12))="",0,IF(DATE(2027,8,1)=DATE(2026,10,1),IF('Model inputs'!O46="","",'Model inputs'!O46),IF('Model inputs'!M12="","",'Model inputs'!M12)))+'Model inputs'!N43 -> -150
A13: Closing cash · Growth | B13: =IF(IF(DATE(2027,9,1)=DATE(2026,10,1),IF('Model inputs'!O245="","",'Model inputs'!O245),IF('Model inputs'!N13="","",'Model inputs'!N13))="",0,IF(DATE(2027,9,1)=DATE(2026,10,1),IF('Model inputs'!O245="","",'Model inputs'!O245),IF('Model inputs'!N13="","",'Model inputs'!N13)))+'Model inputs'!B239 -> 50598.825 | D13: =IF(IF(DATE(2026,10,1)=DATE(2026,10,1),IF('Model inputs'!O245="","",'Model inputs'!O245),IF('Model inputs'!C209="","",'Model inputs'!C209))="",0,IF(DATE(2026,10,1)=DATE(2026,10,1),IF('Model inputs'!O245="","",'Model inputs'!O245),IF('Model inputs'!C209="","",'Model inputs'!C209)))+'Model inputs'!D239 -> -354.86 | E13: =IF(IF(DATE(2026,11,1)=DATE(2026,10,1),IF('Model inputs'!O245="","",'Model inputs'!O245),IF('Model inputs'!D13="","",'Model inputs'!D13))="",0,IF(DATE(2026,11,1)=DATE(2026,10,1),IF('Model inputs'!O245="","",'Model inputs'!O245),IF('Model inputs'!D13="","",'Model inputs'!D13)))+'Model inputs'!E239 -> -11.1632 | F13: =IF(IF(DATE(2026,12,1)=DATE(2026,10,1),IF('Model inputs'!O245="","",'Model inputs'!O245),IF('Model inputs'!E13="","",'Model inputs'!E13))="",0,IF(DATE(2026,12,1)=DATE(2026,10,1),IF('Model inputs'!O245="","",'Model inputs'!O245),IF('Model inputs'!E13="","",'Model inputs'!E13)))+'Model inputs'!F239 -> 892.92035 | G13: =IF(IF(DATE(2027,1,1)=DATE(2026,10,1),IF('Model inputs'!O245="","",'Model inputs'!O245),IF('Model inputs'!F13="","",'Model inputs'!F13))="",0,IF(DATE(2027,1,1)=DATE(2026,10,1),IF('Model inputs'!O245="","",'Model inputs'!O245),IF('Model inputs'!F13="","",'Model inputs'!F13)))+'Model inputs'!G239 -> 2428.8837 | H13: =IF(IF(DATE(2027,2,1)=DATE(2026,10,1),IF('Model inputs'!O245="","",'Model inputs'!O245),IF('Model inputs'!G13="","",'Model inputs'!G13))="",0,IF(DATE(2027,2,1)=DATE(2026,10,1),IF('Model inputs'!O245="","",'Model inputs'!O245),IF('Model inputs'!G13="","",'Model inputs'!G13)))+'Model inputs'!H239 -> 4679.3208 | I13: =IF(IF(DATE(2027,3,1)=DATE(2026,10,1),IF('Model inputs'!O245="","",'Model inputs'!O245),IF('Model inputs'!H13="","",'Model inputs'!H13))="",0,IF(DATE(2027,3,1)=DATE(2026,10,1),IF('Model inputs'!O245="","",'Model inputs'!O245),IF('Model inputs'!H13="","",'Model inputs'!H13)))+'Model inputs'!I239 -> 7739.5803 | J13: =IF(IF(DATE(2027,4,1)=DATE(2026,10,1),IF('Model inputs'!O245="","",'Model inputs'!O245),IF('Model inputs'!I13="","",'Model inputs'!I13))="",0,IF(DATE(2027,4,1)=DATE(2026,10,1),IF('Model inputs'!O245="","",'Model inputs'!O245),IF('Model inputs'!I13="","",'Model inputs'!I13)))+'Model inputs'!J239 -> 11719.668 | K13: =IF(IF(DATE(2027,5,1)=DATE(2026,10,1),IF('Model inputs'!O245="","",'Model inputs'!O245),IF('Model inputs'!J13="","",'Model inputs'!J13))="",0,IF(DATE(2027,5,1)=DATE(2026,10,1),IF('Model inputs'!O245="","",'Model inputs'!O245),IF('Model inputs'!J13="","",'Model inputs'!J13)))+'Model inputs'!K239 -> 16746.434 | L13: =IF(IF(DATE(2027,6,1)=DATE(2026,10,1),IF('Model inputs'!O245="","",'Model inputs'!O245),IF('Model inputs'!K13="","",'Model inputs'!K13))="",0,IF(DATE(2027,6,1)=DATE(2026,10,1),IF('Model inputs'!O245="","",'Model inputs'!O245),IF('Model inputs'!K13="","",'Model inputs'!K13)))+'Model inputs'!L239 -> 22966.091 | M13: =IF(IF(DATE(2027,7,1)=DATE(2026,10,1),IF('Model inputs'!O245="","",'Model inputs'!O245),IF('Model inputs'!L13="","",'Model inputs'!L13))="",0,IF(DATE(2027,7,1)=DATE(2026,10,1),IF('Model inputs'!O245="","",'Model inputs'!O245),IF('Model inputs'!L13="","",'Model inputs'!L13)))+'Model inputs'!M239 -> 30547.105 | N13: =IF(IF(DATE(2027,8,1)=DATE(2026,10,1),IF('Model inputs'!O245="","",'Model inputs'!O245),IF('Model inputs'!M13="","",'Model inputs'!M13))="",0,IF(DATE(2027,8,1)=DATE(2026,10,1),IF('Model inputs'!O245="","",'Model inputs'!O245),IF('Model inputs'!M13="","",'Model inputs'!M13)))+'Model inputs'!N239 -> 39683.529
A14: Closing cash · NeatRescue — Hackathon submission · 12-month scenario comparison — hypothetical · Bootstrap $5,000 — hypothetical | B14: =IF(IF(DATE(2027,9,1)=DATE(2026,10,1),IF('Model inputs'!O47="","",'Model inputs'!O47),IF('Model inputs'!N14="","",'Model inputs'!N14))="",0,IF(DATE(2027,9,1)=DATE(2026,10,1),IF('Model inputs'!O47="","",'Model inputs'!O47),IF('Model inputs'!N14="","",'Model inputs'!N14)))+'Model inputs'!B44 -> 21344.74 | C14: 0 | D14: =IF(IF(DATE(2026,10,1)=DATE(2026,10,1),IF('Model inputs'!O47="","",'Model inputs'!O47),IF('Model inputs'!C14="","",'Model inputs'!C14))="",0,IF(DATE(2026,10,1)=DATE(2026,10,1),IF('Model inputs'!O47="","",'Model inputs'!O47),IF('Model inputs'!C14="","",'Model inputs'!C14)))+'Model inputs'!D44 -> 4572.57 | E14: =IF(IF(DATE(2026,11,1)=DATE(2026,10,1),IF('Model inputs'!O47="","",'Model inputs'!O47),IF('Model inputs'!D14="","",'Model inputs'!D14))="",0,IF(DATE(2026,11,1)=DATE(2026,10,1),IF('Model inputs'!O47="","",'Model inputs'!O47),IF('Model inputs'!D14="","",'Model inputs'!D14)))+'Model inputs'!E44 -> 4578.8385 | F14: =IF(IF(DATE(2026,12,1)=DATE(2026,10,1),IF('Model inputs'!O47="","",'Model inputs'!O47),IF('Model inputs'!E14="","",'Model inputs'!E14))="",0,IF(DATE(2026,12,1)=DATE(2026,10,1),IF('Model inputs'!O47="","",'Model inputs'!O47),IF('Model inputs'!E14="","",'Model inputs'!E14)))+'Model inputs'!F44 -> 4831.6033 | G14: =IF(IF(DATE(2027,1,1)=DATE(2026,10,1),IF('Model inputs'!O47="","",'Model inputs'!O47),IF('Model inputs'!F14="","",'Model inputs'!F14))="",0,IF(DATE(2027,1,1)=DATE(2026,10,1),IF('Model inputs'!O47="","",'Model inputs'!O47),IF('Model inputs'!F14="","",'Model inputs'!F14)))+'Model inputs'!G44 -> 5345.4705 | H14: =IF(IF(DATE(2027,2,1)=DATE(2026,10,1),IF('Model inputs'!O47="","",'Model inputs'!O47),IF('Model inputs'!G14="","",'Model inputs'!G14))="",0,IF(DATE(2027,2,1)=DATE(2026,10,1),IF('Model inputs'!O47="","",'Model inputs'!O47),IF('Model inputs'!G14="","",'Model inputs'!G14)))+'Model inputs'!H44 -> 6137.0091 | I14: =IF(IF(DATE(2027,3,1)=DATE(2026,10,1),IF('Model inputs'!O47="","",'Model inputs'!O47),IF('Model inputs'!H14="","",'Model inputs'!H14))="",0,IF(DATE(2027,3,1)=DATE(2026,10,1),IF('Model inputs'!O47="","",'Model inputs'!O47),IF('Model inputs'!H14="","",'Model inputs'!H14)))+'Model inputs'!I44 -> 7224.9219 | J14: =IF(IF(DATE(2027,4,1)=DATE(2026,10,1),IF('Model inputs'!O47="","",'Model inputs'!O47),IF('Model inputs'!I14="","",'Model inputs'!I14))="",0,IF(DATE(2027,4,1)=DATE(2026,10,1),IF('Model inputs'!O47="","",'Model inputs'!O47),IF('Model inputs'!I14="","",'Model inputs'!I14)))+'Model inputs'!J44 -> 8630.2355 | K14: =IF(IF(DATE(2027,5,1)=DATE(2026,10,1),IF('Model inputs'!O47="","",'Model inputs'!O47),IF('Model inputs'!J14="","",'Model inputs'!J14))="",0,IF(DATE(2027,5,1)=DATE(2026,10,1),IF('Model inputs'!O47="","",'Model inputs'!O47),IF('Model inputs'!J14="","",'Model inputs'!J14)))+'Model inputs'!K44 -> 10376.509 | L14: =IF(IF(DATE(2027,6,1)=DATE(2026,10,1),IF('Model inputs'!O47="","",'Model inputs'!O47),IF('Model inputs'!K14="","",'Model inputs'!K14))="",0,IF(DATE(2027,6,1)=DATE(2026,10,1),IF('Model inputs'!O47="","",'Model inputs'!O47),IF('Model inputs'!K14="","",'Model inputs'!K14)))+'Model inputs'!L44 -> 12490.068 | M14: =IF(IF(DATE(2027,7,1)=DATE(2026,10,1),IF('Model inputs'!O47="","",'Model inputs'!O47),IF('Model inputs'!L14="","",'Model inputs'!L14))="",0,IF(DATE(2027,7,1)=DATE(2026,10,1),IF('Model inputs'!O47="","",'Model inputs'!O47),IF('Model inputs'!L14="","",'Model inputs'!L14)))+'Model inputs'!M44 -> 15000.257 | N14: =IF(IF(DATE(2027,8,1)=DATE(2026,10,1),IF('Model inputs'!O47="","",'Model inputs'!O47),IF('Model inputs'!M14="","",'Model inputs'!M14))="",0,IF(DATE(2027,8,1)=DATE(2026,10,1),IF('Model inputs'!O47="","",'Model inputs'!O47),IF('Model inputs'!M14="","",'Model inputs'!M14)))+'Model inputs'!N44 -> 17939.726
A15: Closing cash · Conservative | B15: =IF(IF(DATE(2027,9,1)=DATE(2026,10,1),IF('Model inputs'!O246="","",'Model inputs'!O246),IF('Model inputs'!N15="","",'Model inputs'!N15))="",0,IF(DATE(2027,9,1)=DATE(2026,10,1),IF('Model inputs'!O246="","",'Model inputs'!O246),IF('Model inputs'!N15="","",'Model inputs'!N15)))+'Model inputs'!B240 -> 320.45863 | D15: =IF(IF(DATE(2026,10,1)=DATE(2026,10,1),IF('Model inputs'!O246="","",'Model inputs'!O246),IF('Model inputs'!C210="","",'Model inputs'!C210))="",0,IF(DATE(2026,10,1)=DATE(2026,10,1),IF('Model inputs'!O246="","",'Model inputs'!O246),IF('Model inputs'!C210="","",'Model inputs'!C210)))+'Model inputs'!D240 -> -499.8225 | E15: =IF(IF(DATE(2026,11,1)=DATE(2026,10,1),IF('Model inputs'!O246="","",'Model inputs'!O246),IF('Model inputs'!D15="","",'Model inputs'!D15))="",0,IF(DATE(2026,11,1)=DATE(2026,10,1),IF('Model inputs'!O246="","",'Model inputs'!O246),IF('Model inputs'!D15="","",'Model inputs'!D15)))+'Model inputs'!E240 -> -728.22637 | F15: =IF(IF(DATE(2026,12,1)=DATE(2026,10,1),IF('Model inputs'!O246="","",'Model inputs'!O246),IF('Model inputs'!E15="","",'Model inputs'!E15))="",0,IF(DATE(2026,12,1)=DATE(2026,10,1),IF('Model inputs'!O246="","",'Model inputs'!O246),IF('Model inputs'!E15="","",'Model inputs'!E15)))+'Model inputs'!F240 -> -888.60213 | G15: =IF(IF(DATE(2027,1,1)=DATE(2026,10,1),IF('Model inputs'!O246="","",'Model inputs'!O246),IF('Model inputs'!F15="","",'Model inputs'!F15))="",0,IF(DATE(2027,1,1)=DATE(2026,10,1),IF('Model inputs'!O246="","",'Model inputs'!O246),IF('Model inputs'!F15="","",'Model inputs'!F15)))+'Model inputs'!G240 -> -983.99934 | H15: =IF(IF(DATE(2027,2,1)=DATE(2026,10,1),IF('Model inputs'!O246="","",'Model inputs'!O246),IF('Model inputs'!G15="","",'Model inputs'!G15))="",0,IF(DATE(2027,2,1)=DATE(2026,10,1),IF('Model inputs'!O246="","",'Model inputs'!O246),IF('Model inputs'!G15="","",'Model inputs'!G15)))+'Model inputs'!H240 -> -1017.1518 | I15: =IF(IF(DATE(2027,3,1)=DATE(2026,10,1),IF('Model inputs'!O246="","",'Model inputs'!O246),IF('Model inputs'!H15="","",'Model inputs'!H15))="",0,IF(DATE(2027,3,1)=DATE(2026,10,1),IF('Model inputs'!O246="","",'Model inputs'!O246),IF('Model inputs'!H15="","",'Model inputs'!H15)))+'Model inputs'!I240 -> -990.50081 | J15: =IF(IF(DATE(2027,4,1)=DATE(2026,10,1),IF('Model inputs'!O246="","",'Model inputs'!O246),IF('Model inputs'!I15="","",'Model inputs'!I15))="",0,IF(DATE(2027,4,1)=DATE(2026,10,1),IF('Model inputs'!O246="","",'Model inputs'!O246),IF('Model inputs'!I15="","",'Model inputs'!I15)))+'Model inputs'!J240 -> -906.21599 | K15: =IF(IF(DATE(2027,5,1)=DATE(2026,10,1),IF('Model inputs'!O246="","",'Model inputs'!O246),IF('Model inputs'!J15="","",'Model inputs'!J15))="",0,IF(DATE(2027,5,1)=DATE(2026,10,1),IF('Model inputs'!O246="","",'Model inputs'!O246),IF('Model inputs'!J15="","",'Model inputs'!J15)))+'Model inputs'!K240 -> -766.21512 | L15: =IF(IF(DATE(2027,6,1)=DATE(2026,10,1),IF('Model inputs'!O246="","",'Model inputs'!O246),IF('Model inputs'!K15="","",'Model inputs'!K15))="",0,IF(DATE(2027,6,1)=DATE(2026,10,1),IF('Model inputs'!O246="","",'Model inputs'!O246),IF('Model inputs'!K15="","",'Model inputs'!K15)))+'Model inputs'!L240 -> -572.18171 | M15: =IF(IF(DATE(2027,7,1)=DATE(2026,10,1),IF('Model inputs'!O246="","",'Model inputs'!O246),IF('Model inputs'!L15="","",'Model inputs'!L15))="",0,IF(DATE(2027,7,1)=DATE(2026,10,1),IF('Model inputs'!O246="","",'Model inputs'!O246),IF('Model inputs'!L15="","",'Model inputs'!L15)))+'Model inputs'!M240 -> -325.58138 | N15: =IF(IF(DATE(2027,8,1)=DATE(2026,10,1),IF('Model inputs'!O246="","",'Model inputs'!O246),IF('Model inputs'!M15="","",'Model inputs'!M15))="",0,IF(DATE(2027,8,1)=DATE(2026,10,1),IF('Model inputs'!O246="","",'Model inputs'!O246),IF('Model inputs'!M15="","",'Model inputs'!M15)))+'Model inputs'!N240 -> -27.676813
A16: Closing customers · by · NeatRescue — Hackathon submission · 12-month scenario comparison — hypothetical · Main Scenario | B16: =SUM('Model inputs'!B18,'Model inputs'!B19) -> 51.961366 | C16: =SUM('Model inputs'!C18,'Model inputs'!C19) -> 0 | D16: =SUM('Model inputs'!D18,'Model inputs'!D19) -> 3 | E16: =SUM('Model inputs'!E18,'Model inputs'!E19) -> 6.15 | F16: =SUM('Model inputs'!F18,'Model inputs'!F19) -> 9.4725 | G16: =SUM('Model inputs'!G18,'Model inputs'!G19) -> 12.991875 | H16: =SUM('Model inputs'!H18,'Model inputs'!H19) -> 16.734581 | I16: =SUM('Model inputs'!I18,'Model inputs'!I19) -> 20.729382 | ... N16: =SUM('Model inputs'!N18,'Model inputs'!N19) -> 45.686332
A17: Closing customers | B17: =IF('Model inputs'!B16="","",'Model inputs'!B16) -> 51.961366 | C17: =IF('Model inputs'!C16="","",'Model inputs'!C16) -> 0 | D17: =IF('Model inputs'!D16="","",'Model inputs'!D16) -> 3 | E17: =IF('Model inputs'!E16="","",'Model inputs'!E16) -> 6.15 | F17: =IF('Model inputs'!F16="","",'Model inputs'!F16) -> 9.4725 | G17: =IF('Model inputs'!G16="","",'Model inputs'!G16) -> 12.991875 | H17: =IF('Model inputs'!H16="","",'Model inputs'!H16) -> 16.734581 | I17: =IF('Model inputs'!I16="","",'Model inputs'!I16) -> 20.729382 | ... N17: =IF('Model inputs'!N16="","",'Model inputs'!N16) -> 45.686332
A18: Closing customers > Starter | B18: ='Model inputs'!B110+'Model inputs'!B106-'Model inputs'!B100 -> 34.640911 | C18: =0 -> 0 | D18: ='Model inputs'!D110+'Model inputs'!D106-'Model inputs'!D100 -> 2 | E18: ='Model inputs'!E110+'Model inputs'!E106-'Model inputs'!E100 -> 4.1 | F18: ='Model inputs'!F110+'Model inputs'!F106-'Model inputs'!F100 -> 6.315 | G18: ='Model inputs'!G110+'Model inputs'!G106-'Model inputs'!G100 -> 8.66125 | H18: ='Model inputs'!H110+'Model inputs'!H106-'Model inputs'!H100 -> 11.156388 | I18: ='Model inputs'!I110+'Model inputs'!I106-'Model inputs'!I100 -> 13.819588 | J18: ='Model inputs'!J110+'Model inputs'!J106-'Model inputs'!J100 -> 16.671731 | K18: ='Model inputs'!K110+'Model inputs'!K106-'Model inputs'!K100 -> 19.735578 | ... N18: ='Model inputs'!N110+'Model inputs'!N106-'Model inputs'!N100 -> 30.457555
A19: Closing customers > Team | B19: ='Model inputs'!B111+'Model inputs'!B107-'Model inputs'!B101 -> 17.320455 | C19: =0 -> 0 | D19: ='Model inputs'!D111+'Model inputs'!D107-'Model inputs'!D101 -> 1 | E19: ='Model inputs'!E111+'Model inputs'!E107-'Model inputs'!E101 -> 2.05 | F19: ='Model inputs'!F111+'Model inputs'!F107-'Model inputs'!F101 -> 3.1575 | G19: ='Model inputs'!G111+'Model inputs'!G107-'Model inputs'!G101 -> 4.330625 | H19: ='Model inputs'!H111+'Model inputs'!H107-'Model inputs'!H101 -> 5.5781938 | I19: ='Model inputs'!I111+'Model inputs'!I107-'Model inputs'!I101 -> 6.9097941 | J19: ='Model inputs'!J111+'Model inputs'!J107-'Model inputs'!J101 -> 8.3358654 | K19: ='Model inputs'!K111+'Model inputs'!K107-'Model inputs'!K101 -> 9.8677892 | ... N19: ='Model inputs'!N111+'Model inputs'!N107-'Model inputs'!N101 -> 15.228777
A20: Closing customers · Bootstrap no-sales stress — hypothetical | B20: =SUM('Model inputs'!B212,'Model inputs'!B213) -> 0 | C20: =SUM('Model inputs'!C212,'Model inputs'!C213) -> 0 | D20: =SUM('Model inputs'!D212,'Model inputs'!D213) -> 0 | E20: =SUM('Model inputs'!E212,'Model inputs'!E213) -> 0 | F20: =SUM('Model inputs'!F212,'Model inputs'!F213) -> 0 | G20: =SUM('Model inputs'!G212,'Model inputs'!G213) -> 0 | H20: =SUM('Model inputs'!H212,'Model inputs'!H213) -> 0 | I20: =SUM('Model inputs'!I212,'Model inputs'!I213) -> 0 | ... N20: =SUM('Model inputs'!N212,'Model inputs'!N213) -> 0
A21: Closing customers · Growth | B21: =SUM('Model inputs'!B215,'Model inputs'!B216) -> 155.21359 | D21: =SUM('Model inputs'!D215,'Model inputs'!D216) -> 6 | E21: =SUM('Model inputs'!E215,'Model inputs'!E216) -> 12.72 | F21: =SUM('Model inputs'!F215,'Model inputs'!F216) -> 20.2734 | G21: =SUM('Model inputs'!G215,'Model inputs'!G216) -> 28.790448 | H21: =SUM('Model inputs'!H215,'Model inputs'!H216) -> 38.420772 | I21: =SUM('Model inputs'!I215,'Model inputs'!I216) -> 49.336292 | J21: =SUM('Model inputs'!J215,'Model inputs'!J216) -> 61.734568 | K21: =SUM('Model inputs'!K215,'Model inputs'!K216) -> 75.84265 | ... N21: =SUM('Model inputs'!N215,'Model inputs'!N216) -> 131.23633
A22: Closing customers · Bootstrap $5,000 — hypothetical | B22: =SUM('Model inputs'!B218,'Model inputs'!B219) -> 51.961366 | C22: =SUM('Model inputs'!C218,'Model inputs'!C219) -> 0 | D22: =SUM('Model inputs'!D218,'Model inputs'!D219) -> 3 | E22: =SUM('Model inputs'!E218,'Model inputs'!E219) -> 6.15 | F22: =SUM('Model inputs'!F218,'Model inputs'!F219) -> 9.4725 | G22: =SUM('Model inputs'!G218,'Model inputs'!G219) -> 12.991875 | H22: =SUM('Model inputs'!H218,'Model inputs'!H219) -> 16.734581 | I22: =SUM('Model inputs'!I218,'Model inputs'!I219) -> 20.729382 | ... N22: =SUM('Model inputs'!N218,'Model inputs'!N219) -> 45.686332
A23: Closing customers · Conservative | B23: =SUM('Model inputs'!B221,'Model inputs'!B222) -> 12.023801 | D23: =SUM('Model inputs'!D221,'Model inputs'!D222) -> 1.25 | E23: =SUM('Model inputs'!E221,'Model inputs'!E222) -> 2.4375 | F23: =SUM('Model inputs'!F221,'Model inputs'!F222) -> 3.568625 | G23: =SUM('Model inputs'!G221,'Model inputs'!G222) -> 4.6490438 | H23: =SUM('Model inputs'!H221,'Model inputs'!H222) -> 5.6840063 | I23: =SUM('Model inputs'!I221,'Model inputs'!I222) -> 6.6783784 | J23: =SUM('Model inputs'!J221,'Model inputs'!J222) -> 7.6366735 | K23: =SUM('Model inputs'!K221,'Model inputs'!K222) -> 8.5630819 | ... N23: =SUM('Model inputs'!N221,'Model inputs'!N222) -> 11.188597
A24: Cost of revenue · NeatRescue — Hackathon submission · 12-month scenario comparison — hypothetical · Main Scenario | B24: ='Model inputs'!B116+'Model inputs'!B103 -> 1929.8524 | C24: 0 | D24: ='Model inputs'!D116+'Model inputs'!D103 -> 323.43 | E24: ='Model inputs'!E116+'Model inputs'!E103 -> 426.7815 | F24: ='Model inputs'!F116+'Model inputs'!F103 -> 535.79273 | G24: ='Model inputs'!G116+'Model inputs'!G103 -> 651.26342 | H24: ='Model inputs'!H116+'Model inputs'!H103 -> 774.06161 | I24: ='Model inputs'!I116+'Model inputs'!I103 -> 905.13103 | J24: ='Model inputs'!J116+'Model inputs'!J103 -> 1045.4992 | K24: ='Model inputs'!K116+'Model inputs'!K103 -> 1196.2865 | ... N24: ='Model inputs'!N116+'Model inputs'!N103 -> 1723.9686
A25: Cost of revenue · Bootstrap no-sales stress — hypothetical | B25: ='Model inputs'!B278+'Model inputs'!B227 -> 225 | C25: 0 | D25: ='Model inputs'!D278+'Model inputs'!D227 -> 225 | E25: ='Model inputs'!E278+'Model inputs'!E227 -> 225 | F25: ='Model inputs'!F278+'Model inputs'!F227 -> 225 | G25: ='Model inputs'!G278+'Model inputs'!G227 -> 225 | H25: ='Model inputs'!H278+'Model inputs'!H227 -> 225 | I25: ='Model inputs'!I278+'Model inputs'!I227 -> 225 | J25: ='Model inputs'!J278+'Model inputs'!J227 -> 225 | K25: ='Model inputs'!K278+'Model inputs'!K227 -> 225 | ... N25: ='Model inputs'!N278+'Model inputs'!N227 -> 225
A26: Cost of revenue · Growth | B26: ='Model inputs'!B279+'Model inputs'!B228 -> 5317.5579 | D26: ='Model inputs'!D279+'Model inputs'!D228 -> 421.86 | E26: ='Model inputs'!E279+'Model inputs'!E228 -> 642.3432 | F26: ='Model inputs'!F279+'Model inputs'!F228 -> 890.17025 | G26: ='Model inputs'!G279+'Model inputs'!G228 -> 1169.6146 | H26: ='Model inputs'!H279+'Model inputs'!H228 -> 1485.5855 | I26: ='Model inputs'!I279+'Model inputs'!I228 -> 1843.7237 | J26: ='Model inputs'!J279+'Model inputs'!J228 -> 2250.5112 | K26: ='Model inputs'!K279+'Model inputs'!K228 -> 2713.3973 | ... N26: ='Model inputs'!N279+'Model inputs'!N228 -> 4530.8641
A27: Cost of revenue · Bootstrap $5,000 — hypothetical | B27: ='Model inputs'!B280+'Model inputs'!B229 -> 1929.8524 | C27: 0 | D27: ='Model inputs'!D280+'Model inputs'!D229 -> 323.43 | E27: ='Model inputs'!E280+'Model inputs'!E229 -> 426.7815 | F27: ='Model inputs'!F280+'Model inputs'!F229 -> 535.79273 | G27: ='Model inputs'!G280+'Model inputs'!G229 -> 651.26342 | H27: ='Model inputs'!H280+'Model inputs'!H229 -> 774.06161 | I27: ='Model inputs'!I280+'Model inputs'!I229 -> 905.13103 | J27: ='Model inputs'!J280+'Model inputs'!J229 -> 1045.4992 | K27: ='Model inputs'!K280+'Model inputs'!K229 -> 1196.2865 | ... N27: ='Model inputs'!N280+'Model inputs'!N229 -> 1723.9686
A28: Cost of revenue · Conservative | B28: ='Model inputs'!B281+'Model inputs'!B230 -> 519.07813 | D28: ='Model inputs'!D281+'Model inputs'!D230 -> 255.5725 | E28: ='Model inputs'!E281+'Model inputs'!E230 -> 284.61638 | F28: ='Model inputs'!F281+'Model inputs'!F230 -> 312.28143 | G28: ='Model inputs'!G281+'Model inputs'!G230 -> 338.70631 | H28: ='Model inputs'!H281+'Model inputs'!H230 -> 364.01943 | I28: ='Model inputs'!I281+'Model inputs'!I230 -> 388.33978 | J28: ='Model inputs'!J281+'Model inputs'!J230 -> 411.77776 | K28: ='Model inputs'!K281+'Model inputs'!K230 -> 434.43586 | ... N28: ='Model inputs'!N281+'Model inputs'!N230 -> 498.65069
A29: Funding shortfall · Main Scenario | B29: =MAX(-'Model inputs'!B11,0) -> 0 | D29: =MAX(-'Model inputs'!D11,0) -> 427.43 | E29: =MAX(-'Model inputs'!E11,0) -> 421.1615 | F29: =MAX(-'Model inputs'!F11,0) -> 168.39672 | G29: =MAX(-'Model inputs'!G11,0) -> 0 | H29: =MAX(-'Model inputs'!H11,0) -> 0 | I29: =MAX(-'Model inputs'!I11,0) -> 0 | J29: =MAX(-'Model inputs'!J11,0) -> 0 | K29: =MAX(-'Model inputs'!K11,0) -> 0 | ... N29: =MAX(-'Model inputs'!N11,0) -> 0
A30: Funding shortfall · Bootstrap no-sales stress — hypothetical | B30: =MAX(-'Model inputs'!B12,0) -> 600 | D30: =MAX(-'Model inputs'!D12,0) -> 0 | E30: =MAX(-'Model inputs'!E12,0) -> 0 | F30: =MAX(-'Model inputs'!F12,0) -> 0 | G30: =MAX(-'Model inputs'!G12,0) -> 0 | H30: =MAX(-'Model inputs'!H12,0) -> 0 | I30: =MAX(-'Model inputs'!I12,0) -> 0 | J30: =MAX(-'Model inputs'!J12,0) -> 0 | K30: =MAX(-'Model inputs'!K12,0) -> 0 | ... N30: =MAX(-'Model inputs'!N12,0) -> 150
